Workbook

Sheet ЛИК_дляСкорингаДП
A1: ОГРН | B1: ИНН | C1: Краткое наименование | D1: Полное наименование | E1: ОКПО | F1: ОКАТО | G1: ОКФС | H1: ОКОПФ | I1: КПП | J1: Регистрация | K1: Ликвидация | L1: ОКВЭД | M1: ОКВЭД наименование | N1: Доп. ОКВЭД | O1: Руководитель | P1: ИНН руководителя | Q1: Должность | R1: Адрес | S1: Телефоны | T1: Web-сайты | U1: Email | V1: Уст. капитал | W1: Выручка (2025) | X1: Осн. средства (2025) | Y1: Запасы (2025) | Z1: Деб. задолженность (2025) | AA1: Кред. задолженность (2025) | AB1: Чистая прибыль (2025) | AC1: Прибыль от продаж (2025) | AD1: прибыль до налогообложения (2025) | AE1: РМСП | AF1: кол-во сотрудников | AG1: Налоговый режим
A2: 1027700092661 | B2: 7712040126 | C2: ПАО "АЭРОФЛОТ" | D2: ПУБЛИЧНОЕ АКЦИОНЕРНОЕ ОБЩЕСТВО "АЭРОФЛОТ-РОССИЙСКИЕ АВИАЛИНИИ" | E2: 29063984 | F2: 45286552000 | G2: 41 | H2: 12247 | I2: 770401001 | J2: 1994-06-21 | L2: 51.10.1 | M2: Перевозка воздушным пассажирским транспортом, подчиняющимся расписанию | N2: 49.39.39,51.21.1,52.23.19,52.29,61.90.9,68.20.29,85.42.9,86.21,18.12,33.16,41.20,46.14,51.10.1,51.21.3,52.29,55.10,56.10.1,58.19,62.01,62.02,62.09,64.99,68.32.2,70.22,73.20,79.11,85.22,85.42.9,86.21 | O2: АЛЕКСАНДРОВСКИЙ СЕРГЕЙ ВЛАДИМИРОВИЧ | P2: 770177090572 | Q2: ГЕНЕРАЛЬНЫЙ ДИРЕКТОР | R2: 119019, Г.МОСКВА, УЛ. АРБАТ, Д. 1 | S2: +74956641319,+74955781384,+74995006762,+74995007624,+74995007258,+79091647126,+74957538163,+74995006765,+74957551500,+78432009585,+74212783456,+74952584082,+74957529016,+74242788555,+74152300722,+79091994636,+74955443312,+74995006868,+74952235555,+79039310032,+74956640001,+74957538188,+71278345684,+72300722842,+72901684995,+70068688415,+78288432009,+75858903931,+78584952584,+70032849575,+70828903931,+73849525840,+73884320095,+72427885558,+78495753816,+74957538004,+74957538063,+74952580684,+74995006867,+74955443329,+74992463049,+74995006700,+74991556648,+74995006800,+74957529031,+74992235555,+74956641201,+74995006481,+73833196860,+74995507624 | T2: emitent@aeroflot.ru,,www.aeroflot.ru | U2: info@aeroflot.ru,ostepanov@aeroflot.ru,trade@aeroflot.ru,obodrova@aeroflot.ru,vgnikolaev@aeroflot.ru,saveliev@aeroflot.ru,info-afl@aeroflot.ru,imoskovaya@aeroflot.ru,yusannikov@aeroflot.ru,vminaev@aeroflot.ru,aableeva@aeroflot.ru,dbalakina@aeroflot.ru,ookorolev@aeroflot.ru,grkkp@aeroflot.ru,vakuzmin@aeroflot.ru,ankuznetsov3@aeroflot.ru,uussales@aeroflot.ru,arbat1@aeroflot.ru,inikolaenko@aeroflot.ru,rtwapsu@aeroflot.ru,krrapsu@aeroflot.ru,oshulga@aeroflot.ru,rtwapsuч@aeroflot.ru,ledtosu@aeroflot.ru,skorolev@aeroflot.ru,obadrova@aeroflot.ru,dsotnichenko@aeroflot.ru,yumelnik@aeroflot.ru,akhaliulin@aeroflot.ru,eakurochkin@aeroflot.ru,vvankevich@aeroflot.ru,asftosu@aeroflot.ru,vogtosu@aeroflot.ru,atarakanova@aeroflot.ru,yakhalaev@aeroflot.ru,kuftosu@aeroflot.net,khvsu@aeroflot.ru,rkashaev@aeroflot.ru,uusapsu@aeroflot.ru,aeroflot@atnet.ru,nsmolyannikova@aeroflot.ru,omssales@aeroflot.ru,peetosu@aeroflot.ru,dmalinov@aeroflot.ru,ovbtosu@aeroflot.ru,ikamaletdinov@aeroflot.ru,sspakhova@aeroflot.ru,omsapsu@aeroflot.ru,nplyasunova@aeroflot.ru,tjmtosu@aeroflot.ru | V2: 3975771215 | W2: 760401133000 | X2: 457204966000 | Y2: 78738975000 | Z2: 135207149000 | AA2: 240967255000 | AB2: 123037451000 | AC2: -14589929000 | AD2: 160180997000 | AG2: ОСН
A3: 1067746341024 | B3: 7708591995 | C3: ПАО "ТРАНСКОНТЕЙНЕР" | D3: ПУБЛИЧНОЕ АКЦИОНЕРНОЕ ОБЩЕСТВО "ТРАНСКОНТЕЙНЕР" | E3: 94421386 | F3: 46483000000 | G3: 41 | H3: 12247 | I3: 504701001 | J3: 2006-03-04 | L3: 52.29 | M3: Деятельность вспомогательная прочая, связанная с перевозками | N3: 35.30.14,46.90,49.41.1,52.24.2,68.20.29,16.23,29.20,30.2,33.11,33.12,33.17,35.30,41.2,43.11,43.12,45.11,45.19,45.20,46.69,46.77,46.90,47.99,49.20,49.41,52.10,52.2,52.21,52.24,52.29,68.1,68.2,69.20,69.20.2,70.22,73.20.1,77.12,77.3,77.39,82.20 | O3: МАРКОВ ВИКТОР НИКОЛАЕВИЧ КОНЦЕРЕВ МИХАИЛ РУДОЛЬФОВИЧ | P3: 772900803304 781400896256 | Q3: ДИРЕКТОР ПРЕЗИДЕНТ | R3: 141402, МОСКОВСКАЯ ОБЛАСТЬ, Г.О. ХИМКИ, Г ХИМКИ, УЛ ЛЕНИНГРАДСКАЯ, ВЛД. 39, СТР. 6, ОФИС 3 (ЭТАЖ 6) | S3: +74922486079,+79035505976,+74957881717,+74952627578,+74992626135,+74956379178,+74952661186,+74956096168,+74992625171,+74992628506,+74952628506,+74992627578,+74992627425,+79144837765,+73466467506,+79102522856,+73022220029,+73912480036,+74992627700,+73912480031,+73022225925,+78124589115,+74852230257,+74852205072,+73912480045,+78312484253,+73022225469,+78632594676,+73832222100,+74991548202,+74212385472,+74852230120,+78124589118,+78124586800,+74732653508,+73433801245,+74212384752,+78452390054,+78452390048,+73952645948,+78632590898,+78632699228,+78463032468,+73952645950,+73832294757,+74732558323,+73022325211,+78124586804,+74732652874,+78124586815 | T3: www.e-disclosure.ru/portal/company.aspx?id=11194,,www.trcont.ru | U3: trcont@trcont.ru,zykinaes@trcont.ru,davidovatn@trcont.ru,zszd@trcont.ru,popyvanovaag@trcont.ru,secretar_dvgd@trcont.ru,ikonnikovaev@trcont.ru,medvedevamp@trcont.ru,kotygavg@trcont.ru,beliakovail@trcont.ru,burkutovaks@trcont.ru,mishinayu@trcont.ru,belyakovail@trcont.ru,obukhovichtv@trcont.ru,shorenkovaa@trcont.ru,demidovaon@trcont.ru,volozhaninmiu@trcont.ru,uskovanm@trcont.ru,konoplevdv@trcont.ru,smirnovagaa@trcont.ru,natalyp@pvrr.ru,svzd@trcont.ru,dvzd@tcont.ru,gzd@trcont.ru,uvzd@trkont.ru,vszd@trcont.ru,kiselevanv@trcont.ru,tripeletcmv@trcont.ru,kruglovaa@trcont.ru,bochkarevpi@trcont.ru,izvekovaen@trcont.ru,kozlovmib@trcont.ru,elenskiyam@trcont.ru,stankevskiysa@trcont.ru,didykmp@trcont.ru,liapinskoviv@trcont.ru,zlydnevani@trcont.ru,tokarevvn@trcont.ru,iasinskiyss@trcont.ru,omelchenkoan@trcont.ru,andreevio@trcont.ru,vasinav@trcont.ru,kuleshovea@trcont.ru,boldorzhievaviu@trcont.ru,golenevai@trcont.ru,erbiaginamv@trcont.ru,kulkovrs@trcont.ru,belosheykinaov@trcont.ru,korneeviuv@trcont.ru,titkovsn@trcont.ru | V3: 13894778000 | W3: 159888098000 | X3: 122577344000 | Y3: 1550744000 | Z3: 24634580000 | AA3: 13611376000 | AB3: -9221825000 | AC3: 9769387000 | AD3: -12214316000 | AG3: ОСН
A4: 1097746772738 | B4: 7708709686 | C4: АО "ФПК" | D4: АКЦИОНЕРНОЕ ОБЩЕСТВО "ФЕДЕРАЛЬНАЯ ПАССАЖИРСКАЯ КОМПАНИЯ" | E4: 94154560 | F4: 45286565000 | G4: 41 | H4: 12267 | I4: 770801001 | J4: 2009-12-03 | L4: 49.10.1 | M4: Перевозка пассажиров железнодорожным транспортом в междугородном сообщении | N4: 26.5,35.30.14,36.00,45.20,47.11,47.19,47.73,47.74,47.75,47.9,49.10,49.20,49.20,49.3,49.4,52.10,52.21,52.24,52.29,55.90,56.10,56.10.1,56.10.3,56.29,58,59.1,63.11.1,68.20,73.11,74.90.31,77.2,77.3,77.39,79.11,85.30,85.42,85.42.9,90.04,91.01,91.02,91.03,93.11,93.19,96.04 | O4: ПЯСТОЛОВ ВЛАДИМИР ГЕННАДЬЕВИЧ | P4: 740404334042 | Q4: ГЕНЕРАЛЬНЫЙ ДИРЕКТОР | R4: 107078, Г.МОСКВА, УЛ МАШИ ПОРЫВАЕВОЙ, Д. 34 | S4: +78512323240,+78512324212,+74992608474,+74992623349,+78312482346,+73952450950,+78463391044,+78124574173,+73472291767,+74992662278,+74212310765,+74992661276,+74992604398,+78312488352,+73433582758,+74992601356,+78452521214,+78463390441,+78463038654,+73433582463,+74992625192,+78463034679,+74992606634,+78312486414,+78632382844,+78124367178,+73832293306,+78312488911,+74955393886,+78124045084,+74992608602,+78632590648,+73433583957,+78463038468,+74959881000,+73832294124,+73952637405,+73952643266,+78463034244,+78463037390,+71242310765,+78312486737,+78452983061,+78632596918,+78312486491,+78312486242,+78312486069,+74212384692,+78452983065,+73472291004 | T4: disclosure.skrin.ru/disclosure/7708709686,,fpc.rzd.ru/static/public/ru?structure_id=14,fpc54.ru | U4: delo@fpc.ru,vasilkovsv@fpc.ru,kravchukyv-kuyb@fpc.ru,chernyavinadu-priv@fpc.ru,lapshinaey-gork@fpc.ru,debunovav@fpc.ru,kaplinamv@fpc.ru,popovaoa-szap@fpc.ru,korolevasn-szap@fpc.ru,klimovaia-vsib@fpc.ru,korotkovang-msk@fpc.ru,rcoz_ovchinnikovve@grw.ru,artemevaya-ural@fpc.ru,sadykovnn@center.rzd.ru,miniakhmetovdh-kuyb@fpc.ru,shprungve@center.rzd.ru,rkz_vlasovvo@msk.rzd.ru,khalatovasa-daln@fpc.ru,chernovvv-ural@fpc.ru,kochevav@fpc.ru,behuv-skav@fpc.ru,voevodinayo-kuyb@fpc.ru,yatcichenkoia-kuyb@fpc.ru,pashkovau@fpc.ru,lynovadv@fpc.ru,ckz_mashinskaya@orw.ru,bochkarevaav-gork@fpc.ru,Аlekseevatv-zsib@fpc.ru,rcoz_skopinamv@grw.ru,koreginaas-szap@fpc.ru,chernoskutovann@fpc.ru,rcoz_artemovka@grw.ru,bariomi@center.rzd.ru,alekseevatv-zsib@fpc.ru,barskayaeg-daln@fpc.ru,sgpetrova@svrw.ru,skzd-iruban@skzd.rzd.ru,trubilinalv-vsib@fpc.ru,korolevaav-kuyb@fpc.ru,ryabykhai-kuyb@fpc.ru,tagilcevaeb@wsr.ru,ivanovanv-priv@fpc.org.rzd,yashinala@fpc.ru,zuevanv-priv@fpc.ru,rсоz_makarovpv@esrr.ru,kuznecovsa-kuyb@fpc.ru,rcoz_makarovpv@esrr.ru,slynkoas-kuyb@fpc.ru,rkz-terentevan@kbsh.rzd.ru,rckz_medvedevav@dvgd.ru | V4: 263588838994 | W4: 427758435000 | X4: 437693243000 | Y4: 11603320000 | Z4: 24030311000 | AA4: 60554694000 | AB4: 19596889000 | AC4: 45942576000 | AD4: 27506070000 | AG4: ОСН
A5: 1067746082546 | B5: 7708587205 | C5: АО "РЖДСТРОЙ" | D5: АКЦИОНЕРНОЕ ОБЩЕСТВО "РЖДСТРОЙ" | E5: 93287520 | F5: 45286555000 | G5: 41 | H5: 12267 | I5: 770901001 | J5: 2006-01-19 | L5: 43.12 | M5: Подготовка строительной площадки | N5: 23.32,23.51,23.61,25.11,37.00,41.10,41.2,41.20,42.11,42.12,42.13,42.91,42.99,43.11,43.12.3,43.2,43.21,43.22,43.29,43.3,43.39,43.91,43.99,43.99.1,46.73,47.52.7,49.20,68.20,71.12.1,71.12.2,71.12.45,77.32 | O5: МАЛЬЦЕВ ЮРИЙ СЕРГЕЕВИЧ | P5: 150405977663 | Q5: ГЕНЕРАЛЬНЫЙ ДИРЕКТОР | R5: 105005, Г.МОСКВА, ПЕР. ЕЛИЗАВЕТИНСКИЙ, Д. 12, СТР. 1 | S5: +78512322996,+78512323866,+74992668800,+74992613337,+74997530634,+74952680051,+79035380745,+74012601160,+79108813414,+73952644331,+74992603432,+79281279352,+74991873614,+78452412083,+79241007607,+78452744077,+79093913913,+74212911361,+79106662575,+73912482439,+78124364734,+73022225771,+78632590467,+74992662869,+78632594104,+78632638256,+79807400829,+74212911374,+73952643377,+79243099638,+74991873616,+74212911365,+74212382712,+74992604398,+78312483552,+74955005018,+74992662726,+74732655443,+74992662681,+74952668800,+74955434000,+78632035784,+74212911366,+78421911366,+74232249417,+74630349808,+79171092027,+74012587230,+74955005019,+78632638254 | T5: www.rzdstroy.ru,,www.rzdstroy.ru | U5: info@rzdstroy.ru,boroninav@rzdstroy.ru,chuvankinab@rzdstroy.ru,sevostyanovrs@rzdstroy.ru,tokarevaaa@rzdstroy.ru,avetisyanis@rzdstroy.ru,parfulindg@rzdstroy.ru,zheleznovaei@rzdstroy.ru,myagkovaev@rzdstroy.ru,nikolaevds@rzdstroy.ru,shepchugovaap@rzdstroy.ru,moskovkinaes@rzdstroy.ru,lugovskayatv@rzdstroy.ru,pomeshikovals@rzdstroy.ru,shirokovav@rzdstroy.ru,pilipenkoem@rzdstroy.ru,ilinata@rzdstroy.ru,bizyaevaov@rzdstroy.ru,ratkinamn@rzdstroy.ru,kopylovaim@rzdstroy.ru,goncharovaoi@rzdstroy.ru,leonovaev@rzdstroy.ru,milovds@rzdstroy.ru,kosheevaka@rzdstroy.ru,uspenskayant@rzdstroy.ru,filkinaeo@rzdstroy.ru,korolevaey@rzdstroy.ru,odintsovas@rzdstroy.ru,ocheredkooe@rzdstroy.ru,stadnichenkoei@rzdstroy.ru,dyakonovaas@rzdstroy.ru,lesnovng@rzdstroy.ru,vasukovsn@rzdstroy.ru,hizhnyakovayv@rzdstroy.ru,kravetson@rzdstroy.ru,andreikouv@rzdstroy.ru,bogdanovana@rzdstroy.ru,somikey@rzdstroy.ru,shlemchenkoep@rzdstroy.ru,maximovda@rzdstroy.ru,solovevatv@rzdstroy.ru,sadykovnn@center.rzd.ru,garikhinoe@rzdstroy.ru,karelinsv@rzdstroy.ru,kozlovev@rzdstroy.ru,elfimovaev@rzdstroy.ru,andreykouv@rzdstroy.ru,bobylevaap@rzdstroy.ru,udalcovama@rzdstroy.ru,slonkinsg@rzdstroy.ru | V5: 14176805000 | W5: 117762144000 | X5: 5389211000 | Y5: 8385986000 | Z5: 41310670000 | AA5: 73734110000 | AB5: -17820406000 | AC5: -3882051000 | AD5: -11097891000 | AG5: ОСН
A6: 1117746460358 | B6: 7704784450 | C6: АО "ИНТЕР РАО-ЭЛЕКТРОГЕНЕРАЦИЯ" | D6: АКЦИОНЕРНОЕ ОБЩЕСТВО "ИНТЕР РАО-ЭЛЕКТРОГЕНЕРАЦИЯ" | E6: 92516444 | F6: 45286590000 | G6: 16 | H6: 12267 | I6: 770401001 | J6: 2011-06-15 | L6: 35.11.1 | M6: Производство электроэнергии тепловыми электростанциями, в том числе деятельность по обеспечению работоспособности электростанций | N6: 25.62,33.12,33.14,35.11.2,35.14,35.23,35.30.11,35.30.14,35.30.4,36.00.1,36.00.2,37.00,46.90,49.42,49.50.21,52.10.21,52.10.9,52.21.11,61.10.1,68.20.1,68.20.29,69.20.2,71.20.4,77.39.11,77.39.23,77.39.29,82.99,93.11,96.09.9,03.21.4,03.22.5,20.11,23.61,33.13,33.14,33.14,33.20,35.11,35.11.1,35.11.1,35.11.2,35.11.2,35.12,35.12,35.13,35.14,35.14,35.22,35.30.1,35.30.11,35.30.14,35.30.2,35.30.3,35.30.4,35.30.5,36.00.1,36.00.2,37.00,37.00,41.2,41.20,42.21,42.22.1,42.22.3,43.21,46.71,46.90,49.20,49.3,49.4,49.41.1,49.41.2,49.50.21,49.50.22,52.10,52.10.21,52.10.23,52.21.1,52.21.2,52.24,56.29,61.10.1,68.10,68.20,68.20.1,68.20.2,68.32,70.10.1,70.10.2,70.22,71.12.1,71.12.6,71.12.62,71.20.1,72.19,73.20,77.39,85.23,85.42,86.21,86.23,86.90.4,91.01,93.11,96.09 | O6: ОБЩЕСТВО С ОГРАНИЧЕННОЙ ОТВЕТСТВЕННОСТЬЮ "ИНТЕР РАО - УПРАВЛЕНИЕ ЭЛЕКТРОГЕНЕРАЦИЕЙ" | P6: 7704775342 | Q6: — | R6: 119435, Г.МОСКВА, УЛ. БОЛЬШАЯ ПИРОГОВСКАЯ, Д.27, СТР.1 | S6: +73014595437,+74945372855,+74945372863,+74956647680,+73426593950,+74945372062,+73426593234,+73426595002,+74945372246,+73014595367,+73426593000,+73014595327,+73014595572,+74945372860,+74012690449,+74012690448,+74945372708,+74945372648,+74945372834,+73426593306,+79632929980,+74012690453,+73014595326,+79632973711,+74016140610,+73014595651,+74945372818,+74945372822,+74945372253,+73014595344,+74012690263,+73014595491,+79044975203,+74014336160,+73536351207,+73513492396,+74012690423,+73516672531,+73536351247,+73426593260,+73435722308,+73014595349,+73494246713,+79243936695,+73494246723,+73494246671,+79245501153,+79245501152,+74012690367,+79245501154 | T6: www.e-disclosure.ru/portal/company.aspx?id=29767,,www.interrao.ru/activity/generation/disclosure,pechgres.ru | U6: titova_eo@interrao.ru,surzhikova_ys@interrao.ru,alekseeva_aa@interrao.ru,tyurnikova_mb@interrao.ru,nazarova_va@interrao.ru,merkusheva_ta@interrao.ru,dmitrieva_ap@interrao.ru,golubeva_ly@interrao.ru,loskutnikov_am@interrao.ru,lebusova_on@interrao.ru,baldina_en@interrao.ru,prikhodko_ey@interrao.ru,nechaeva_tv@interrao.ru,likhacheva_ev@interrao.ru,suranov_av@interrao.ru,bulatova_avl@interrao.ru,moroz_tr@interrao.ru,ivanova_iv@interrao.ru,gavrilyuk_db@interrao.ru,shubin_rv@interrao.ru,brusnikina_in@interrao.ru,smotrichenko_ee@interrao.ru,shushpanova_ne@interrao.ru,svarin_es@interrao.ru,kabakova_iv@interrao.ru,gorokhova_aa@interrao.ru,kanashina_iv@interrao.ru,korenkova_ts@interrao.ru,frolov_svl@interrao.ru,efimova_tp@interrao.ru,dubova_ma@interrao.ru,kravchenko_ko@interrao.ru,pakush_av@interrao.ru,mokhova_nn@interrao.ru,karyakina_ym@interrao.ru,gosuslugi_eg@interrao.ru,nikiforova_yv@interrao.ru,naumkina_ms@interrao.ru,kutlaeva_er@interrao.ru,frolova_ty@interrao.ru,abramova_nan@interrao.ru,nosova_ns@interrao.ru,balbatunova_ey@interrao.ru,sd@vtgres.ogk1.ru,batalova_ea@interrao.ru,wwwinter-rao@mail.ru,lytkina_ya@interrao.ru,kazunina_dv@interrao.ru,chistyakova_ov@interrao.ru,shishkova_iv@interrao.ru | V6: 172491169361 | W6: 293934892000 | X6: 240926685000 | Y6: 14660876000 | Z6: 34992223000 | AA6: 19752065000 | AB6: 67561454000 | AC6: 54744900000 | AD6: 90248644000 | AG6: ОСН
A7: 5087746119951 | B7: 7721632827 | C7: АО "КОНЦЕРН РОСЭНЕРГОАТОМ" | D7: АКЦИОНЕРНОЕ ОБЩЕСТВО "РОССИЙСКИЙ КОНЦЕРН ПО ПРОИЗВОДСТВУ ЭЛЕКТРИЧЕСКОЙ И ТЕПЛОВОЙ ЭНЕРГИИ НА АТОМНЫХ СТАНЦИЯХ" | E7: 8844275 | F7: 45290554000 | G7: 61 | H7: 12267 | I7: 772101001 | J7: 2008-09-17 | L7: 35.11.3 | M7: Производство электроэнергии атомными электростанциями, в том числе деятельность по обеспечению работоспособности электростанций | N7: 35.11.3,35.12,35.12,35.13,35.30.12,35.30.2,35.30.3,35.30.5,36.00.1,37.00,38.1,38.2,42.22.3,42.99,43.21,51.10,55.10,55.90,61.10,63.11,70.22,71.11.1,71.12,71.12.1,71.12.45,71.20,72.19,84.24,85.30,85.42,86.90.4 | O7: ШУТИКОВ АЛЕКСАНДР ВИКТОРОВИЧ | P7: 643909165462 | Q7: ГЕНЕРАЛЬНЫЙ ДИРЕКТОР | R7: 109507, Г.МОСКВА, УЛ. ФЕРГАНСКАЯ, Д.25 | S7: +74953770213,+78136922518,+74956474354,+74956605001,+74956609070,+74956434754,+74957106363,+74999494740,+74957830143,+73437736940,+79859703601,+74956474370,+74957106546,+74815370611,+78639219872,+78153243798,+78153244787,+78153243627,+78136954317,+78136954328,+78136954329,+78453497141,+74815330440,+78136954315,+74825569048,+74273825759,+74736473472,+78453497294,+78453497180,+74713156371,+78136954316,+78136954313,+78153243957,+78136954311,+74736473671,+78639297022,+78453497823,+74713157277,+78639297757,+78453497810,+74713153783,+78153242140,+74736473302,+73437738105,+74825569159,+78453499818,+78639298724,+74815330441,+74825569251,+78639223739 | T7: sanatorij-balaes.ru,www.rosenergoatom.ru/stations_projects/sayt-novovoronezhskoy-aes/,www.salma-ski.ru,www.e-disclosure.ru/portal/company.aspx?id=18936,,www.rosenergoatom.ru | U7: kev@belnpp-auto.ru,post@belnpp.ru,sokolov@balaes.ru,profk@kolatom.murmansk.ru,panitskiyae@kolnpp.rosenergoatom.ru,salma-ski@yandex.ru,surkova@balaes.ru,beketova-sa@vdnpp.rosenergoatom.ru,kolanpp@kolatom.murmansk.ru,spf@belnpp.ru,reception@knpp.local,nvnpp1@nvnpp1.rosenergoatom.ru,kopan.laes@yandex.ru,voropaevaap@saes.ru,nechatvys@yandex.ru,info@rosenergoatom.ru,info@atomkomplekt.org,abramova-eka@rosenergoatom.ru,rakov-vv@rosenergoatom.ru,cz19@belnpp.ru,anvlprikhodko@rosatom.ru,gajdukova-ii@btaes.ru,savina-ys@rosenergoatom.ru,baibenkova-mn@rosenergoatom.ru,medvedeva22@rosenergoatom.ru,cz3@belnpp.ru,tabunshchikyv@odic.rosenergoatom.ru,cz-sov@ln.rosenergoatom.ru,turutina@balaes.ru,bekmambetov@saes.ru,lapkin_ou@kunpp.ru,anisimovav@kolnpp.rosenergoatom.ru,melnikova_ti@kunpp.ru,turganova@balaes.ru,rybakova-iv@bilnpp.ru,cz9@belnpp.ru,npp@balaes.ru,matveev_en@kunpp.ru,cz-reu@ln.rosenergoatom.ru,safronovav@nvnpp1.rosenergoatom.ru,frkp_zakupki@rosenergoatom.ru,borodina@kunpp.ru,evgrafova_as@knpp.ru,soboleva_tn@kunpp.ru,od-cpv@ln.rosenergoatom.ru,avdeeva@knpp.ru,bogdanov-ia@bilnpp.ru,shakurova-og@knpp.ru,cz-lav@ln.rosenergoatom.ru,sambulovrv@odic.rosenergoatom.ru | V7: 830313906474 | W7: 689530314000 | X7: 1990136600000 | Y7: 82659832000 | Z7: 96167823000 | AA7: 108998064000 | AB7: 133373947000 | AC7: 242569601000 | AD7: 201913926000 | AG7: ОСН
A8: 5087746570830 | B8: 7715729877 | C8: АО "ЖЕЛДОРРЕММАШ" | D8: АКЦИОНЕРНОЕ ОБЩЕСТВО "ЖЕЛДОРРЕММАШ" | E8: 94138851 | F8: 45280569000 | G8: 41 | H8: 12267 | I8: 771501001 | J8: 2008-12-09 | L8: 30.20.9 | M8: Предоставление услуг по восстановлению и оснащению (завершению) железнодорожных локомотивов, трамвайных моторных вагонов и прочего подвижного состава | N8: 16.24,16.29.11,18.12,22.19.7,23.61,25.50.1,25.61,25.62,25.73,28.15.2,30.20.1,30.20.4,33.12,33.14,33.17,33.20,35.12,35.13,35.22,35.30.14,35.30.2,35.30.3,35.30.4,36.00.2,38.32.5,41.20,43.11,43.12.1,43.12.3,43.29,46.69.1,46.69.2,46.77,46.90,47.9,49.10,49.20,49.3,49.31,49.4,49.41.2,52.21.1,55.10,55.90,56.10,56.10.1,56.10.3,56.29,61.10.1,62.01,62.02,62.09,63.11.1,68.20.1,68.20.2,68.32.1,71.1,71.11,71.11.1,71.12.12,71.12.45,71.12.5,71.12.6,71.20,72.1,72.19,73.20.1,74.20,74.30,82.92,82.99,85.42,85.42.9,86.21,91.01 | O8: МАВРИН АЛЕКСАНДР НИКОЛАЕВИЧ | P8: 616206292791 | Q8: ГЕНЕРАЛЬНЫЙ ДИРЕКТОР | R8: 127018, Г.МОСКВА, УЛ. ОКТЯБРЬСКАЯ, Д.5, СТР.8 | S8: +79092859495,+74992621737,+74992620106,+74234263081,+74996382298,+78006000669,+74234232385,+74234232331,+78512210112,+73012444340,+73517914731,+70006698851,+78184992620,+71068499262,+72210112830,+71737849963,+78229888006,+72342323318,+71842342630,+71244434084,+78351791473,+74992627117,+74732008213,+78632409130,+74234260070,+74852406749,+74234232435,+74234252525,+73012446626,+73012371756,+74234360594,+78632406134,+73517914333,+78512210152,+73517914165,+74732653831,+74732531560,+78622528320,+73433312627,+78632402044,+78512301812,+74852773000,+73833376448,+73833377142,+78512301465,+74852406761,+73532566183,+73433119702,+73833375486,+74234367507 | T8: e-disclosure.azipi.ru/organization/800330/,,www.olrz.ru,www.ao-zdrm.ru | U8: urlz@mail.ussuriisk.ru,matveevala@locotech.ru,lapinaea@ulrz.ru,energi-rerz@ao-zdrm.ru,omto@r56.fssprus.ru,ulrz@ml.ussuriisk.ru,lapinaea@locotech.ru,ulrz@uirz.ru,уссуржелдоррем@mail.ru,ulrz@ulrz.ru,urlz@ml.ussuriisk.ru,u.kalmikova@cherz.ru,info@yarz.ru,olgakalashnikova0371@gmail.com,energi-rerz@ао-zdm.ru,atrz@locotech.ru,mail@ing.center.ru,erz@erz.ru,atrz@astranet.ru,olrz@olrz.ru,nerz@nerz.ru,rerz@lokotech.ru,vrntrz@ttk-uv.ru,oge-ulrz@yandex.ru,vtrz@locotech.ru,uss_ds101@mail.ru,savvateevaov-oge@uirz.ru,pavel@lvrz.ru,00000@mail.ru,bely@loco.ru,detsadik106@mail.ru,ulrz@ao-zdrm.ru,savvateevaov-oge@ulrz.ru,ooo_teplo@mail.ru,0@mail.ru,omto@r56.fsshrus.ru,geidorrem@mail.ru,lvrz@lvrz.ru,dboroda73@mail.ru,kirichenkovo-ogmeh@ulrz.ru,birukovael-oopz@ulrz.ru,auction@locotech.ru,1@mail.ru,energy-rerz@ao-zdrm.ru,oozp-ulrz@ao-zdrm.ru,kuzyakinva@locotech.ru,geldorrem@mail.ru,cherz-odc@mail.ru,otv-zdrm@css-rzd.ru,rem@mail.ru | V8: 15162764668 | W8: 89893496000 | X8: 13262416000 | Y8: 17597199000 | Z8: 37509656000 | AA8: 26363392000 | AB8: 4067863000 | AC8: 9445655000 | AD8: 5465281000 | AG8: ОСН
A9: 1057747320278 | B9: 7728551528 | C9: ООО "СПОРТМАСТЕР" | D9: ОБЩЕСТВО С ОГРАНИЧЕННОЙ ОТВЕТСТВЕННОСТЬЮ "СПОРТМАСТЕР" | E9: 77522772 | F9: 45293566000 | G9: 23 | H9: 12300 | I9: 772801001 | J9: 2005-06-27 | L9: 47.71 | M9: Торговля розничная одеждой в специализированных магазинах | N9: 46.49,47.91,53.20.39,95.29,37.00,46.42.11,46.42.12,46.42.13,46.42.14,46.42.2,47.25,47.64,47.71.1,47.71.2,47.71.3,47.71.4,47.71.5,47.71.6,47.71.7,47.71.8,47.72.1,47.72.2,47.74,47.78,47.91.2,52.10,53.20.3,62.01,62.02,68.31.12,73.11,85.42,85.42.9,95.11,95.29 | O9: СТРАХОВ ЛЕОНИД БОРИСОВИЧ | P9: 772728563630 | Q9: ГЕНЕРАЛЬНЫЙ ДИРЕКТОР | R9: 117437, Г.МОСКВА, УЛ. МИКЛУХО-МАКЛАЯ, Д.18, К.2, КОМН. 102 | S9: +74922323940,+73512634142,+74957558143,+74957558194,+74957777771,+73522600625,+74957558190,+74957558184,+74957558197,+74959747522,+74959747890,+74959747934,+74957558179,+73472912151,+73472922151,+73432165154,+73432165151,+73473290843,+78123200002,+78452201864,+73022282244,+73812325174,+73722533106,+78612775522,+79282611111,+73832300844,+78632559555,+79138005302,+73822900715,+79039170663,+79517237800,+74954116923,+74954116922,+73843910644,+73012297691,+74967545747,+78463722532,+79034000675,+74993502071,+78632559454,+73812321574,+78452207720,+78632870140,+78792252680,+74242708620,+73953560003,+73822283367,+73412916916,+73412903838,+73843390358 | T9: www.sportmaster.ru | U9: legal@sportmaster.ru,asergienko@sportmaster.ru,okorotaeva@sportmaster.ru,sportmaster@mail.ru,ovlaskina@sportmaster.ru,nfilippova@sportmaster.ru,tmazurova@sportmaster.ru,skonovalova@sportmaster.ru,director5886@sportmaster.ru,info@grrus.ru,okarelina@sportmaster.ru,rostov@czn-rostov.ru,vaeremeeva@sportmaster.ru,emakanova@sportmaster.ru,megadirector763@sportmaster.ru,adminshop5198@sportmaster.ru,direktor5581@sportmaster.ru,null@null.ru,account852@sportmaster.ru | V9: 261642499 | W9: 165625072000 | X9: 33077804000 | Y9: 44904585000 | Z9: 12075061000 | AA9: 26105333000 | AB9: 4963645000 | AC9: 14067088000 | AD9: 7112593000 | AG9: ОСН
A10: 1027717003467 | B10: 7717133960 | C10: ПАО НК "РУССНЕФТЬ" | D10: ПУБЛИЧНОЕ АКЦИОНЕРНОЕ ОБЩЕСТВО НЕФТЕГАЗОВАЯ КОМПАНИЯ "РУССНЕФТЬ" | E10: 59107064 | F10: 45286560000 | G10: 34 | H10: 12247 | I10: 770501001 | J10: 2002-09-17 | L10: 06.10.1 | M10: Добыча нефти | N10: 06.10,08.12.1,09.10.1,09.10.9,23.51,28.13,33.20,35.11,35.12,35.13,35.22,35.30.14,46.71,46.71.2,46.71.3,49.41,49.41.1,49.50.11,49.50.21,52.10,52.10.22,52.21.2,52.29,64.20,64.99,69.10,69.20,70.10,70.10.1,70.10.2,71.12,71.12.1,71.20,82.11,84.13 | O10: ТОЛОЧЕК ЕВГЕНИЙ ВИКТОРОВИЧ | P10: 637700276860 | Q10: ПРЕЗИДЕНТ | R10: 115054, Г.МОСКВА, УЛ. ПЯТНИЦКАЯ, Д.69 | S10: +79195300000,+74954116309,+74954116325,+74957805891,+78452393555,+78452393427,+74954116312 | T10: russneft.ru | U10: russneft@russneft.ru,srf@russneft.ru,russneft@mail.ru,vasilevaei@russneft.ru | V10: 196076000 | W10: 221621391000 | X10: 104110496000 | Y10: 12185993000 | Z10: 74520682000 | AA10: 124442818000 | AB10: 7752425000 | AC10: 27792742000 | AD10: 1059615000 | AG10: ОСН
A11: 1065009017920 | B11: 5009053687 | C11: ООО "ТАТНЕФТЬ-АЗС-ЗАПАД" | D11: ОБЩЕСТВО С ОГРАНИЧЕННОЙ ОТВЕТСТВЕННОСТЬЮ "ТАТНЕФТЬ-АЗС-ЗАПАД" | E11: 96277539 | F11: 45268569000 | G11: 16 | H11: 12300 | I11: 773101001 | J11: 2006-07-17 | L11: 47.30 | M11: Торговля розничная моторным топливом в специализированных магазинах | N11: 10.71.1,10.85,68.20.21,10.13.4,10.32,10.71,10.72,10.72.4,10.82,10.82.2,10.85,10.89,11.07.2,19.20,42.21,45.2,45.20.5,46.12.1,46.71,46.71.1,46.71.2,46.90,47.11,47.2,47.24,47.25,47.26,47.30,47.30.2,47.73,47.74,47.75,47.78.9,47.91,47.91.1,47.91.2,47.91.29,49.31,49.50.1,52.10.21,52.29,56.10,56.10.21,56.10.22,56.10.24,56.29,56.30,66.19,73.11,74.20,74.30,77.40,82.92,85.30,85.42.9 | O11: НИЖАМЕТДИНОВ ШАМИЛЬ РАШИДОВИЧ | P11: 771800020650 | Q11: ДИРЕКТОР | R11: 121205, Г.МОСКВА, ВН.ТЕР.Г. МУНИЦИПАЛЬНЫЙ ОКРУГ МОЖАЙСКИЙ, ТЕР ИННОВАЦИОННОГО ЦЕНТРА СКОЛКОВО, Б-Р БОЛЬШОЙ, Д. 62 | S11: +79857731191,+74952801347,+74852726044,+79150274207,+74922421317,+78125503510,+74952801124,+78182462914,+74922420546,+78125500180,+74922421096,+74952211603,+74952211639,+74956441611,+74952211726,+78495280137,+78442984256,+74952211640,+74952211611,+74953339560,+78442984253,+78443589884,+78443586884,+74952271725,+78182622220,+78182622020,+74952211725,+74952801348,+78443580091,+74852726014,+78125503666,+78125500170,+78182652109,+74957899049,+74452211603,+74952211775,+78957661850,+74957775707,+74952211620,+74956455306,+74965553698,+74942211725,+78182602020,+74956441610,+79106625601,+78182621777,+78282622020,+74922726044,+78818622020,+78182621277 | T11: www.azs-tatneft.ru,,www.tatneft.ru | U11: tender@msk.tatneft.ru,tatneft@msk.tatneft.ru,5009053687_772901001@eo.tensor.ru,tatneft34@msk.tatneft.ru,bogomolova@tnvl.ru,bakhtin@azszapad.ru,vyalkin_au@msk.tatneft.ru,artem@azszapad.ru,npvega@mail.ru,нет@mail.ru,tender@msk.tatneft.tu,sekr@tnvl.ru,kubkina_os@msk.tatneft.ru,tat@mail.ru,goricheva@tnvl.ru,mail@azszapad.ru,shikunova_ad@msk.tatneft.ru,tender@vsk.tatneft.ru,1@mail.ru,net@mail.ru,bogomolov_as@msk.tatneft.ru,bahtin@azszapad.ru,tender@msk.tatntft.ru,tnw@yandex.ru,bogomolova@tnvl.ru;,tender@msk.tatneft.ru;,bogomolova@ntvl.ru,tn@mail.ru,ivanova.n@spb.tatneft.ru,info@zenit.ru,fokin_da@msk.tatneft.ru,tatneft@mail.ru,samigullin_kv@msk.tatneft.ru,vrublevskaya_oi@msk.tatneft.ru,famullina_er@msk.tatneft.ru,tender_bi@tatneft.ru,granovskiy_bi@msk.tatneft.ru,polushkina@spb.tatneft.ru,delo@spb.tatneft.ru,info@msk.tataneft.ru,phykj@mail.ru,sekr@tnvt.ru,tender_bi@msk.tatneft.ru,deli@msk.tatneft.ru,pleshkan@tatneft.ru,delo@msk.tatneft.ru,,info@tatneftm.ru,tihonova@spb.tatneft.ru,boqomolova@tnvl.ru,bogomolova@tnv.ru | V11: 3646969080 | W11: 148369814000 | X11: 15480622000 | Y11: 7046460000 | Z11: 13143887000 | AA11: 9103676000 | AB11: 5522836000 | AC11: 5370557000 | AD11: 6870674000 | AG11: ОСН
A12: 1077763638578 | B12: 7704670879 | C12: АО "ИКАО" | D12: АКЦИОНЕРНОЕ ОБЩЕСТВО "ИПОТЕЧНАЯ КОМПАНИЯ АТОМНОЙ ОТРАСЛИ" | E12: 84095282 | F12: 45296559000 | G12: 16 | H12: 12267 | I12: 772501001 | J12: 2007-12-10 | L12: 71.12.2 | M12: Деятельность заказчика-застройщика, генерального подрядчика | N12: 41.2,55.90,64.92.3,68.1,68.2,68.3,70.22,71.11.1 | O12: КИСЕЛЕВ ЮРИЙ МИХАЙЛОВИЧ | P12: 772783125074 | Q12: ВРЕМЕННЫЙ ЕДИНОЛИЧНЫЙ ИСПОЛНИТЕЛЬНЫЙ ОРГАН | R12: 115432, Г.МОСКВА, ВН.ТЕР.Г. МУНИЦИПАЛЬНЫЙ ОКРУГ ДАНИЛОВСКИЙ, ПРОЕЗД ПРОЕКТИРУЕМЫЙ 4062-Й, Д. 6, СТР. 25, ПОМЕЩ. 11 | S12: +74957953799,+74957953967,+79156301777,+79166478963,+74959602086,+74713153488,+74815332977,+78153272184,+74957953767,+74959602085,+74736428506,+78136949393,+74825558022,+78453396140,+79202200600,+78639244771 | U12: ao-ikao@yandex.ru,vyukuzmichev@rosatom.ru,eysavina@rosatom.ru,ao-ikao@rosatom.ru,zaoikao@gmail.com,dmekrylov@rosatom.ru,zaoika@gmail.com,zao.ikao@gmail.com,dedova.2013@list.ru79606939798,krylov.ikao@gmail.com,krylov.ikao@gmai.com | V12: 4427000000 | W12: 445141000 | X12: 286911000 | Y12: 103947000 | Z12: 171202000 | AA12: 37444000 | AB12: 217104000 | AC12: 124168000 | AD12: 293173000 | AF12: 34 | AG12: ОСН
A13: 1117746491500 | B13: 7702764909 | C13: ООО "КАРИ" | D13: ОБЩЕСТВО С ОГРАНИЧЕННОЙ ОТВЕТСТВЕННОСТЬЮ "КАРИ" | E13: 92543151 | F13: 45286565000 | G13: 23 | H13: 12300 | I13: 770801001 | J13: 2011-06-22 | L13: 47.72 | M13: Торговля розничная обувью и изделиями из кожи в специализированных магазинах | N13: 46.42,16.29.13,23.19.9,24.10.2,32.12.1,32.12.2,32.12.3,32.12.4,32.12.5,32.13,38.32.2,38.32.59,46.12.22,46.18.2,46.18.2,46.41,46.41.2,46.42,46.43,46.44,46.45,46.46,46.48.2,46.49,46.72.23,46.76.4,47.19,47.43,47.51,47.54,47.7,47.71,47.72,47.75,47.77.2,47.91,47.91.1,47.91.2,47.91.4,63.99.1,66.19.5,69.10,69.20,70.22,78.10,95.25 | O13: ОБЩЕСТВО С ОГРАНИЧЕННОЙ ОТВЕТСТВЕННОСТЬЮ УПРАВЛЯЮЩАЯ КОМПАНИЯ "КАРИ" | P13: 9729299145 | Q13: — | R13: 107140, Г.МОСКВА, УЛ. РУСАКОВСКАЯ, Д.13 | S13: +79140708917,+74956697002,+79607612362,+74956677002,+74959874807,+74959874806,+79659191692 | T13: www.kari.ru | U13: 10575@kari.com,karu@mail.ru,10387@kari.com | V13: 2000000000 | W13: 98818597000 | X13: 24008361000 | Y13: 58953882000 | Z13: 16406908000 | AA13: 39005199000 | AB13: 2265676000 | AC13: 2784404000 | AD13: 3048046000 | AG13: ОСН
A14: 1037702027670 | B14: 7702354081 | C14: ООО "ЛАР" | D14: ОБЩЕСТВО С ОГРАНИЧЕННОЙ ОТВЕТСТВЕННОСТЬЮ "ЛУКОЙЛ-АЭРО" | E14: 14666926 | F14: 45286555000 | G14: 16 | H14: 12300 | I14: 770901001 | J14: 2003-06-10 | L14: 46.71.2 | M14: Торговля оптовая моторным топливом, включая авиационный бензин | N14: 46.18,70.10,77.39.11,46.71,46.75.2,49.41.1,52.10.21,52.23.1,52.23.12,52.23.19,68.20.2,77.39 | O14: БРАУН ВЛАДИМИР АЛЕКСАНДРОВИЧ | P14: 590201689550 | Q14: ГЕНЕРАЛЬНЫЙ ДИРЕКТОР | R14: 109028, Г.МОСКВА, Б-Р ПОКРОВСКИЙ, Д. 3, СТР. 1 | S14: +79688022610,+74959803113,+74959817087,+74959803114,+78442317101,+78312565226,+78312759650,+74959803938,+70959803113,+73422947711,+70959803114,+73517783274,+74959803100 | U14: aero@lukoil.com,aero@lukoil.ru | V14: 1437325691 | W14: 196514024000 | X14: 2594810000 | Y14: 5171455000 | Z14: 21207903000 | AA14: 20026368000 | AB14: 9927275000 | AC14: 8704071000 | AD14: 12115031000 | AG14: ОСН
A15: 1027700050278 | B15: 7704228075 | C15: АО "РОСАТОМ ЭНЕРГОСБЫТ" | D15: АКЦИОНЕРНОЕ ОБЩЕСТВО "РОСАТОМ ЭНЕРГОСБЫТ" | E15: 57082325 | F15: 45296559000 | G15: 61 | H15: 12267 | I15: 772501001 | J15: 2001-07-13 | L15: 35.14 | M15: Торговля электроэнергией | N15: 47.19,82.99,33.12,35.11,35.13,35.14,45.20.1,47.19,47.91.2,47.91.3,47.91.4,49.39,62.01,62.02,62.02.1,62.02.4,62.03.13,62.09,63.11,63.11.1,66.2,66.22,73.11,74.90.31,77.29,80.10,80.20,80.30,82.99,84.21 | O15: ГОРЧАКОВ АЛЕКСЕЙ НИКОЛАЕВИЧ | P15: 511002181700 | Q15: ГЕНЕРАЛЬНЫЙ ДИРЕКТОР | R15: 115432, Г.МОСКВА, ПР-Д ПРОЕКТИРУЕМЫЙ 4062-Й, Д. 6, СТР. 25 | S15: +74957847701,+78152692359,+78152692421,+74812687500,+74957899921,+74823358716,+74812687555,+74812687533,+78152692323,+78152692633,+78152692318,+74712324072,+74822483019,+74712390301,+74822483015,+74712390303,+74712390312,+74812687586,+74712323995,+74712506196,+74712324502,+74712390321,+78152692627,+74823622897,+74812687575,+74712390310,+74812687550,+74712324102,+74712320312,+74812687571,+74712320301,+74812687526,+74712227018,+74826922135,+74712390315,+74712324302,+74712324010,+74712390317,+74712390324,+74824224301,+74713421466,+74712227021,+74825555498,+74823352873,+74822379367,+74712227014,+74813247160,+74823622144,+74824224300,+74822483016 | T15: atomsbt.ru,www.atomsbt.ru | U15: info@atomsbt.ru,info@murmansk.atomsbt.ru,secretare@tver.atomsbt.ru,secretar@smolensk.atomsbt.ru,atomsbt@mail.ru,pershinans@tver.atomsbt.ru,shleitanovani@tver.atomsbt.ru,korotkikhyg@smolensk.atomsbt.ru,antonyukaa@murmansk.atomsbt.ru,kuzmenkonv@murmansk.atomsbt.ru,arkhipovna@atomsbt.ru,maslennikovaaa@murmansk.atomsbt.ru,usachyovag@smolensk.atomsbt.ru,strelkovaen@kursk.atomsbt.ru,mitchenkosv@tver.atomsbt.ru,halinda@kursk.atomsbt.ru,hintbatg@atomsbt.ru,petrovain@kursk.atomsbt.ru,loktionovaos@kursk.atomsbt.ru,malykhinaaa@kursk.atomsbt.ru,rebaneaa@tver.atomsbt.ru,medvedevale@smolensk.atomsbt.ru,alekseevain@smolensk.atomsbt.ru,baryshnikovaiv@tver.atomsbt.ru,penkovamv@tver.atomsbt.ru,teleginmy@kursk.atomsbt.ru,parhomenkmv@smolensk.atomsbt.ru,molchanovms@kursk.atomsbt.ru,kamenevdg@kursk.atomsbt.ru,kondratevaav@murmansk.atomsbt.ru,alexeevain@smolensk.atomsbt.ru,4ekmareva77@mail.ru,korobeynikovaoa@tver.atomsbt.ru,voroninev@kursk.atomsbt.ru,arcybashevaa@kursk.atomsbt.ru,shubinami@tver.atomsbt.ru,dementevanv@kursk.atomsbt.ru,stepanovaim@smolensk.atomsbt.ru,davydenkovaes@smolensk.atomsbt.ru,volobuevdn@kursk.atomsbt.ru,matrosovda@tver.atomsbt.ru,suharevna@tver.atomsbt.ru,chuvashovdv@tver.atomsbt.ru,remezkp@smolensk.atomsbt.ru,kukovenkovalm@smolensk.atomsbt.ru,timashukse@atomsbt.ru,ovchinnikovang@kursk.atomsbt.ru,uzhekinmv@smolensk.atomsbt.ru,smerdinaka@tver.atomsbt.ru,zhukovro@tver.atomsbt.ru | V15: 3720000000 | W15: 91525482000 | X15: 3440924000 | Y15: 41834000 | Z15: 7311650000 | AA15: 9600061000 | AB15: 2769557000 | AC15: 3651692000 | AD15: 3654059000 | AG15: ОСН
A16: 1057746557329 | B16: 7736520080 | C16: АО "МОСЭНЕРГОСБЫТ" | D16: АКЦИОНЕРНОЕ ОБЩЕСТВО "МОСЭНЕРГОСБЫТ" | E16: 76469930 | F16: 45293554000 | G16: 16 | H16: 12267 | I16: 773601001 | J16: 2005-04-01 | L16: 35.14 | M16: Торговля электроэнергией | N16: 26.51,33.13,35.13,35.30.3,36.00.2,37.00,46.18.2,47.11,52.10.21,56.29,64.19,66.22,70.22,73.20.1,81.21,81.22,81.29,81.29.1,82.99,84.24,85.23,86.21,95.11,95.12,95.22 | O16: КОВАЛЕВ АНДРЕЙ ВИКТОРОВИЧ | P16: 344402643468 | Q16: ГЕНЕРАЛЬНЫЙ ДИРЕКТОР | R16: 117312, Г.МОСКВА, УЛ. ВАВИЛОВА, Д.9 | S16: +74962241666,+74959819819,+74991329933,+74957106022,+74986959533,+74964523852,+74955125694,+74995500333,+74967556287,+74999819819,+74995509716,+74995500318,+74995500319,+74991328401,+74965193854,+74995509721,+74964618942,+74967699922,+74965513211,+74957185822,+74965192800,+74991328544,+74995504110,+74952211867,+74995500494,+74965393200,+74995509819,+74995509550,+74995500303,+74995504135,+74955500333,+74955508929,+74959571359,+74955508324,+74955615429,+74955815429,+74953271396,+74951328640,+74952874491,+74953060707,+74953270035,+74956618403,+74951328440,+74952874490,+74951327956,+74953271904,+74952591779,+74959573814,+74952598160,+74951328400 | T16: nimanovbi@mosenergosbyt.ru,,www.e-disclosure.ru/portal/company.aspx?id=6980,,www.mosenergosbyt.ru | U16: dmitrovto@yandex.ru,parshinz_vv@mosenergosbyt.ru,info@mosenergosbyt.ru,lopatina_mg@interrao.ru,svo@mosenergosbyt.ru,kuzmicheva_es@mosenergosbyt.ru,nimanovbi@mosenergosbyt.ru,belova_ek@interrao.ru,cto@mosenergosbyt.ru,zhigovskaya_eg@mosenergosbyt.ru,viklenko@mosenergosbyt.ru,forosna@mosenergosbyt.ru,kuzmicheva@mosenergosbyt.ru,forostyan_na@mosenergosbyt.ru,00@jj.ru,okr-ogrdolg@mosenergosbyt.ru,info@mocenergosbyt.ru,chaykina_ev@mosenergosbyt.ru,sukhova_ose@mosenergosbyt.ru,null@null.ru,,sedova_sv@mosenergosbyt.ru,litvinova_aaa@mosenergosbyt.ru,g.lekovada@mosenergosbyt.ru,alekseeva_my@mosenergosbyt.ru,szo@mosenergosbyt.ru,chizhikovaeyu@mosenergosbyt.ru,kurmaevadf@mosenergosbyt.ru,mosenergo@mail.ru,titovaela@mosenergosbyt.ru,polyanskaya_en@mosenergosbyt.ru,skitaevatv@mosenergosbyt.ru,uspenskayaov@mosenergosbyt.ru,mejinen@mosenergosbyt.ru,fsvch6898@mail.ru,moesk@msk.ru,churushkin_av@mosenergosbyt.ru,chernyavskaya_ee@mosenergosbyt.ru,info@mosenergo.ru,andr.a.gorbunov@mail.ru,info@dantamedic.ru,pushkino@mosenеrgosbyt.ru,buh_uii@mail.ru,tender@puppet.ru,mosenergosbyt@mail.ru,zubkova_mv@mosenergosbyt.ru,emelyanova_nv@mosenergosbyt.ru,ingo@mosenergosbyt.ru,foreostyan_na@mosenergosbyt.ru,2061331@mail.ru,dfghsdrf@mail.ru | V16: 383004818 | W16: 629184846000 | X16: 25768124000 | Y16: 854380000 | Z16: 41285827000 | AA16: 79481382000 | AB16: 13839669000 | AC16: 21836396000 | AD16: 20883685000 | AG16: ОСН
A17: 1123444007070 | B17: 3444197347 | C17: ООО "ЛИКАРД" | D17: ОБЩЕСТВО С ОГРАНИЧЕННОЙ ОТВЕТСТВЕННОСТЬЮ "ЛУКОЙЛ-ИНТЕР-КАРД" | E17: 50513259 | F17: 45286560000 | G17: 16 | H17: 12300 | I17: 770501001 | J17: 2012-10-01 | L17: 46.71 | M17: Торговля оптовая твердым, жидким и газообразным топливом и подобными продуктами | N17: 22.29.2,33.12,46.12.1,46.90,47.19,47.21,47.22,47.23,47.24,47.25,47.26,47.29,47.30,47.78,47.99.2,56.10,62.09,63.11,63.11.1,66.11.2,66.19,66.19.6,68.10.22,70.22,73.11,73.20.1 | O17: ФИЛИППОВ АЛЕКСЕЙ ВИКТОРОВИЧ | P17: 774306802813 | Q17: ГЕНЕРАЛЬНЫЙ ДИРЕКТОР | R17: 115035, Г.МОСКВА, ВН.ТЕР.Г. МУНИЦИПАЛЬНЫЙ ОКРУГ ЗАМОСКВОРЕЧЬЕ, УЛ БОЛЬШАЯ ОРДЫНКА, Д. 3 | S17: +78442235767,+73422336156,+78442785261,+78212302614,+78442963373,+73422336147,+78312789821,+78442558003,+78172726010,+78844255800,+78001000911,+78442558005,+78842558003,+78612388932,+74966731232,+78312789877,+79226061077,+78124591989,+78315021746,+78221000911,+78124951987,+78124591897,+78124591987,+73422336145,+78612388938,+78312789801,+74955870770,+78172734180,+78312789803,+78132789821,+74959817033,+74957775977,+78182302619,+78442550803,+78172720610,+78312789819,+74955870711,+78314265245,+74959271677,+78312782512,+78612350515,+78212232526,+78800100091,+78442963376,+78314350101,+79994554550,+78612533418,+73422236145,+78612388936,+78172786010 | T17: www.licard.ru | U17: kmaksimova@licard.com,likard@mail.r,eis@licard.com,lk@mail.ru,ssychev@likard.com,contract@licard.com,ivasenina@licard.com,ekashintseva@licard.com,info@licard.ru,ytn@rambler.ru,erusova@likard.com,abochkareva@licard.com,rfotina@licard.com,iplakunova@licard.com,mborisova@licard.com,erusova@licard.ru,likar@yandex.ru,mtimoshinina@licard.com,mbeshanova@licard.com,erusova@licard.com,ssychev@licard.com,ndudko@licard.com,equest@licard.com,arezvanova@licard.com,robot@licard.ru,afomin@licard.com,info@licord.ru,ltimofeeva@licard.com,ecashintseva@likard.ru,spbsales@licard.com,ndevaeva@licard.com,pbsales@licard.com,contrakt@licard.com,myasyuk@licard.com,kanclend@mail.ru,ltimofeeva@likard.com,request@licard.com,0@0.ru,lantonova@licard.com,abochkateva@licard.com,areznikov@licard.com,info@likard.com,eefremova@licard.ru,no@mail.ru,timofeeva@likard.ru,svsmirnova@licard.com,ikard@mail.ru,licard@licard.com,abochkareva@likard.ru,ashevchenko@licard.com | V17: 697000000 | W17: 856318766000 | X17: 4669695000 | Y17: 23974288000 | Z17: 67553200000 | AA17: 80674971000 | AB17: 10505699000 | AC17: 14367566000 | AD17: 13964255000 | AG17: ОСН
A18: 1027700000679 | B18: 7701285928 | C18: ООО "ЛУКОЙЛ-ЦЕНТРНЕФТЕПРОДУКТ" | D18: ОБЩЕСТВО С ОГРАНИЧЕННОЙ ОТВЕТСТВЕННОСТЬЮ "ЛУКОЙЛ-ЦЕНТРНЕФТЕПРОДУКТ" | E18: 58388374 | F18: 45286570000 | G18: 16 | H18: 12300 | I18: 770201001 | J18: 2002-01-28 | L18: 47.30 | M18: Торговля розничная моторным топливом в специализированных магазинах | N18: 56.10.1,41.20,45.1,45.20,46.12,46.71,46.90,47.11,47.25,47.30,47.73,47.74,47.75,47.8,52.10.21,66.19,68.20.21,68.20.29,70.22,71.11,71.12.2,71.20,85.30 | O18: НЕСТЕРЕНКО АЛЕКСАНДР НИКОЛАЕВИЧ | P18: 27411637338 | Q18: ГЕНЕРАЛЬНЫЙ ДИРЕКТОР | R18: 129110, Г.МОСКВА, ВН.ТЕР.Г. МУНИЦИПАЛЬНЫЙ ОКРУГ МЕЩАНСКИЙ, ПР-КТ ОЛИМПИЙСКИЙ, Д. 5, СТР. 1 | S18: +79191478316,+74959817450,+74957717232,+74956278888,+74959817472,+74956232902,+79163287387,+74956278229,+74959817679,+79168094424,+79067893050,+79266287671,+79261468949,+74832744840,+74862434551,+74832666360,+74742222524,+74956278018,+74956272823,+74959803131,+74956278223,+74956271278,+74959817481,+74959817672,+78002002425,+70959339450,+74812322567,+74812322368,+74872347078,+74872345593,+74742223803,+74742223804,+78314623074,+70959817672,+74957806022,+74959817596,+74955040529,+70009817596,+74959817594,+74956278277,+74959339450 | T18: www.luknef.lukoil.ru | U18: luknef@lukoil.com,ekaterina.desyatkova@lukoil.com,alexander.chubenko@lukoil.com,luknef@luknef.ru,hotline@luknef.ru,,marina.ruchko@lukoil.com,kolosova@lukoil.com,nadejda.plyonkina@lukoil.com | V18: 2379785955 | W18: 267315840000 | X18: 32283127000 | Y18: 4055671000 | Z18: 5727253000 | AA18: 15703400000 | AB18: 17636607000 | AC18: 24890074000 | AD18: 23450204000 | AG18: ОСН
A19: 1107746744038 | B19: 7743792870 | C19: ООО "ТЕБОЙЛ РУС" | D19: ОБЩЕСТВО С ОГРАНИЧЕННОЙ ОТВЕТСТВЕННОСТЬЮ "ТЕБОЙЛ РУС" | E19: 17216218 | F19: 45286585000 | G19: 16 | H19: 12300 | I19: 771001001 | J19: 2010-09-13 | L19: 47.30 | M19: Торговля розничная моторным топливом в специализированных магазинах | N19: 19.20,43.99,46.71,47.11,52.10.21,56.10.2,56.10.21,62.09,63.11,68.10,68.20,71.12,77.39 | O19: МАСЛОВ ВИТАЛИЙ ГЕННАДИЕВИЧ | P19: 773423718948 | Q19: ГЕНЕРАЛЬНЫЙ ДИРЕКТОР | R19: 125196, Г.МОСКВА, УЛ. ЛЕСНАЯ, Д. 9, ЭТАЖ 3 | S19: +74952585900,+74952586920,+74825193005,+74999232101,+74952586900,+74952586924,+78123801212,+74825193000,+78123801011,+78137825418,+78137825417 | T19: www.shell.com.ru | U19: zakaz-b2c-ru@shell.com,maria.suslenkova@shell.com,techinfo@shell.com,s.botev@shell.com | V19: 2964177663 | W19: 110040896000 | X19: 30805627000 | Y19: 4359064000 | Z19: 7983458000 | AA19: 10698386000 | AB19: 1599414000 | AC19: 2941281000 | AD19: 2161469000 | AG19: ОСН
A20: 1047796118182 | B20: 7706525041 | C20: ООО "РН-ЭНЕРГО" | D20: ОБЩЕСТВО С ОГРАНИЧЕННОЙ ОТВЕТСТВЕННОСТЬЮ "РН-ЭНЕРГО" | E20: 72147789 | F20: 46439566000 | G20: 16 | H20: 12300 | I20: 502401001 | J20: 2004-02-26 | L20: 35.14 | M20: Торговля электроэнергией | N20: 33.13,33.14,33.20,35.11,35.14,43.21,43.29,45.20.5 | O20: КУЛЫГИН НИКОЛАЙ ВЛАДИМИРОВИЧ | P20: 590405256690 | Q20: ГЕНЕРАЛЬНЫЙ ДИРЕКТОР | R20: 143440, МОСКОВСКАЯ ОБЛАСТЬ, Г.О. КРАСНОГОРСК, ПГТ. ПУТИЛКОВО, ТЕР. ГРИНВУД, СТР. 23, ЭТАЖ 2, ПОМЕЩ. 129 | S20: +74952313182,+74957774724,+74954284096,+74995766596,+74957774477,+74992313182,+74957774742,+78126111905,+79181200809,+73463332217,+79657546297,+74955766596,+73493654743,+73463313445,+73493653214,+79277362627,+73955403752,+78655822169,+73955572940,+73412606865,+73463253548,+74957777742,+74953214568,+78861464426,+73825966034,+78412550820,+73463253549,+73463253508,+78466120447,+74995766595,+78466141209,+73825963395,+74956648840 | T20: www.rosneft.ru/about | U20: e_mochalova@rosneft.ru,rn-energo.ru@rn-energo.ru,kann@pesc.ru,v_sokirka@mail.ru,rn-energo@rn-enerao.ru,m-energo@m-energo.ru,zsg@pesc.ru,energ@mail.ru,rn-energo@energo.ru,rn-energo@rn_energo.ru,rn-energo@rn-energo.eu,rn-energo@rn-energo.ru,kochneva@belkam.com,fff@ffff.ff,gatinim@yungjsc.com,s_chistyakova@rn-energo.ru,chistyakova_no-reply@rn-energo.ru,rn@rn.ru,e_mochalova@rosneft.ru,,info@rnenergo.ru,d_savchuk86@mail.ru,d.rumyantseva@in-tex.ru,pr@rosneft.ru,alyautdinova@mroads.ru,gatinim@energy.yugjsc.com,-@mail.ru,antoshukli@energoneft-t.ru,rn-energo@rn-energo.com,1@1.ru,svfdogovor@bk.ru,raysihea@energy.yungjsc.com,tek@energosales.ru,n_kannabikh@rn-energo.ru,zatulivetrov_mv@interrao.ru,o_titaeva@rn-enegro.ru,o_titaeva@rn-energo.ru,o_titaeva@rn-enrgo.ru | V20: 5010000 | W20: 155711309000 | X20: 279773000 | Y20: 177000 | Z20: 9509601000 | AA20: 16070179000 | AB20: 10457635000 | AC20: 5836302000 | AD20: 14031060000 | AG20: ОСН
A21: 1117746105400 | B21: 7707743204 | C21: АО "ФОРТЕИНВЕСТ" | D21: АКЦИОНЕРНОЕ ОБЩЕСТВО "ФОРТЕИНВЕСТ" | E21: 90531706 | F21: 45286585000 | G21: 34 | H21: 12267 | I21: 770701001 | J21: 2011-02-16 | L21: 46.71.2 | M21: Торговля оптовая моторным топливом, включая авиационный бензин | N21: 06.10,06.10.1,06.20,19.20,46.12.1,52.29,64.99,66.19.4,70.22,84.11.4 | O21: КОЗЛОВ ВИТАЛИЙ ВЛАДИМИРОВИЧ | P21: 623002845248 | Q21: ГЕНЕРАЛЬНЫЙ ДИРЕКТОР | R21: 127055, Г.МОСКВА, УЛ. НОВОСЛОБОДСКАЯ, Д. 41, ЭТАЖ 6 ПОМЕЩЕНИЕ I | S21: +74956415900,+79857667887,+71417487170,+71417487171,+74956415908,+74956415909 | T21: forteinvest.ru | U21: info@forteinvest.ru,info@forteinvest.ru,,sokolovasa@forteinvest.ru,,kuleshovsi@forteinvest.ru | V21: 20000000 | W21: 297264349000 | X21: 393142000 | Y21: 6866107000 | Z21: 46405227000 | AA21: 28374720000 | AB21: 9346312000 | AC21: 23413924000 | AD21: 12217038000 | AG21: ОСН
A22: 1087746480348 | B22: 7704685184 | C22: АО "НК "НЕФТИСА" | D22: АКЦИОНЕРНОЕ ОБЩЕСТВО "НЕФТЯНАЯ КОМПАНИЯ "НЕФТИСА" | E22: 85741809 | F22: 45286585000 | G22: 16 | H22: 12267 | I22: 771001001 | J22: 2008-04-07 | L22: 46.71.3 | M22: Торговля оптовая нефтью | N22: 06.10.1,06.10.3,08.12.1,09.1,09.10.9,19.20,46.12.1,46.71.2,47.30,52.10.21,52.10.22,52.29,62.02,62.02.1,62.02.2,62.02.3,62.02.4,62.02.9,62.03,62.03.1,62.03.11,62.03.12,62.03.13,62.03.19,62.09,63.11,63.11.1,63.11.9,63.12,66.12.2,69.20.2,70.22,71.12.3,72.19,73.11,73.20.1,74.90.3,74.90.9,74.90.92,74.90.93,74.90.94,74.90.99,82.99 | O22: Зарубин Андрей Леонидович | P22: 860301402225 | Q22: ГЕНЕРАЛЬНЫЙ ДИРЕКТОР | R22: 125375, Г.МОСКВА, ВН.ТЕР.Г. МУНИЦИПАЛЬНЫЙ ОКРУГ ТВЕРСКОЙ, УЛ ТВЕРСКАЯ, Д. 22/2, К. 1, ЭТАЖ 5, КОМ. 5-34 | S22: +74956275585 | T22: www.e-disclosure.ru/portal/company.aspx?id=14687,neftisa.ru | V22: 55000000 | W22: 89133427000 | X22: 976182000 | Y22: 193000 | Z22: 54767601000 | AA22: 109184387000 | AB22: -4678875000 | AC22: 3355955000 | AD22: -5727520000 | AG22: ОСН
A23: 1157746958830 | B23: 7724338125 | C23: ООО "НОВЫЙ АЙ ТИ ПРОЕКТ" | D23: ОБЩЕСТВО С ОГРАНИЧЕННОЙ ОТВЕТСТВЕННОСТЬЮ "НОВЫЙ АЙ ТИ ПРОЕКТ" | E23: 51207582 | F23: 45296571000 | G23: 16 | H23: 12300 | I23: 772401001 | J23: 2015-10-20 | L23: 46.51 | M23: Торговля оптовая компьютерами, периферийными устройствами к компьютерам и программным обеспечением | N23: 26.20.1,26.20.2,26.20.3,26.20.4,26.20.9,43.21,43.22,43.29,46.15.3,46.15.4,46.19,46.43.1,46.43.2,46.43.3,46.49.42,46.66,46.69.7,46.90,47.91.1,47.91.2,52.10,52.10.9,52.21.2,52.24,52.24.1,52.24.2,52.29,61.10,61.10.1,61.10.4,61.10.9,61.20,61.30,61.90,62.01,62.02,62.03,62.09,63.11,63.11.1,63.12,63.91,63.99,63.99.1,73.11,73.12,73.20,73.20.1,79.90,95.11,95.12,95.21 | O23: ТКАЧЕВ СТАНИСЛАВ ИГОРЕВИЧ | P23: 232307152273 | Q23: ГЕНЕРАЛЬНЫЙ ДИРЕКТОР | R23: 115487, Г.МОСКВА, УЛ. НАГАТИНСКАЯ, Д. 16, СТР. 9, ПОМЕЩ. VII КОМ.15 ОФ.5 | S23: +74952077586,+74952077557,+74959266632,+74959269136,+79031090589,+79252412639,+79197276307,+74742220555 | U23: tender@3l.ru,e.karabanova28@gmail.com,info@3l.ru,e.karabanova28@gmai.ru,kazartsev@3l.ru,tender@regard.lipetsk.ru,info@3l.mail.ru,e.karabanova28@gmail.ru,vsevolod@3l.ru,hgjfnnnhh@mail.ru,mshapovalov@31.ru | V23: 100000000 | W23: 102474602000 | X23: 4378373000 | Y23: 27018478000 | Z23: 31901047000 | AA23: 24670520000 | AB23: 2048524000 | AC23: 7417390000 | AD23: 2814624000 | AG23: ОСН
A24: 1147746128694 | B24: 7725819008 | C24: ООО "МЕДСКАН" | D24: ОБЩЕСТВО С ОГРАНИЧЕННОЙ ОТВЕТСТВЕННОСТЬЮ "МЕДСКАН" | E24: 28946948 | F24: 45293578000 | G24: 16 | H24: 12300 | I24: 772801001 | J24: 2014-02-14 | L24: 86.10 | M24: Деятельность больничных организаций | N24: 33.13,46.18.1,46.46,47.73,47.74,47.75,73.11,77.39.26 | O24: ПОДТЕТЕНЕВ ДМИТРИЙ СЕРГЕЕВИЧ | P24: 770470783064 | Q24: ГЕНЕРАЛЬНЫЙ ДИРЕКТОР | R24: 119421, Г.МОСКВА, УЛ. ОБРУЧЕВА, Д. 21А | S24: +74951220303,+74951261620,+74956688181,+79031060530,+79161409478 | V24: 2198902242 | W24: 707049000 | X24: 516551000 | Y24: 25207000 | Z24: 42561000 | AA24: 158705000 | AB24: -109939000 | AC24: -43974000 | AD24: -132610000 | AF24: 98 | AG24: ОСН
A25: 1117746708078 | B25: 7705961278 | C25: АО "ВО "ТЯЖПРОМЭКСПОРТ" | D25: АКЦИОНЕРНОЕ ОБЩЕСТВО "ВНЕШНЕЭКОНОМИЧЕСКОЕ ОБЪЕДИНЕНИЕ "ТЯЖПРОМЭКСПОРТ" | E25: 2839020 | F25: 45277598000 | G25: 12 | H25: 12267 | I25: 771401001 | J25: 2011-09-08 | L25: 41.20 | M25: Строительство жилых и нежилых зданий | N25: 41.2,46.14,46.90,68.2,71.1,71.12.5,71.12.6,73.11,73.20.1,78.1,82.99 | O25: ЕГОРОВ СЕРГЕЙ АНАТОЛЬЕВИЧ | P25: 773128953616 | Q25: ГЕНЕРАЛЬНЫЙ ДИРЕКТОР | R25: 125284, Г.МОСКВА, ПР-Д 1-Й ХОРОШЁВСКИЙ, Д. 3А, СТР. 2 | S25: +74996480000,+74959415100,+74959412552,+74959412060,+74959412694,+74959412072,+74959416020,+74959410433,+74959415101,+74959413617,+74959413716,+79104635472,+74959412090,+74959412555,+74959413955,+74959501610,+79035097146,+74959415022,+79459412072,+79039412694 | T25: tyazh.ru | U25: i.kostina@tyazh.ru,e.duyunova@tyazh.ru,info@tyazh.ru,eduynova@tyazh.ru,e.duynova@mail.ru,e.dyunova@tyazh.ru,v.melnikova@tyazh.ru,a.mikhailov@tyazh.ru,,tyazh@dol.ru,,g.volkenshtein@tyazh.ru,,e.duynova@tyazh.ru,i.stenichkov.@tyazh.ru,i.stenichkov@tyazh.ru,g.volkenshtein@tyazh.ru,a.mikhailov@tyazh.ru,d.dzhambulat@tyazh.ru,a/mikhailov@tyazh.ru | V25: 1739643000 | W25: 1720796000 | X25: 66038000 | Y25: 64711000 | Z25: 1481485000 | AA25: 3190715000 | AB25: 1927000 | AC25: -9441000 | AD25: 12225000 | AF25: 62 | AG25: ОСН
A26: 1037739941227 | B26: 7705568878 | C26: АО "СОГАЗ ТАУЭР" | D26: АКЦИОНЕРНОЕ ОБЩЕСТВО "СОГАЗ ТАУЭР" | E26: 71593328 | F26: 45286565000 | G26: 16 | H26: 12267 | I26: 770801001 | J26: 2003-11-03 | L26: 68.20.29 | M26: Аренда и управление собственным или арендованным прочим нежилым недвижимым имуществом | N26: 41.20,64.99.3,68.10,68.20,68.31,68.32,68.32.2,70.22,71.11,73.11,73.20.1 | O26: НЕЧАЕВ ГЕОРГИЙ ВИКТОРОВИЧ | P26: 772700728603 | Q26: ГЕНЕРАЛЬНЫЙ ДИРЕКТОР | R26: 107078, Г.МОСКВА, ПР-КТ АКАДЕМИКА САХАРОВА, Д. 10 | S26: +74956606015,+74956431315,+74956431316 | U26: wave@wavetower.ru | V26: 5446257100 | W26: 261246000 | X26: 23684000 | Y26: 0 | Z26: 585380000 | AA26: 6547028000 | AB26: 3935822000 | AC26: -5151000 | AD26: 3981045000 | AF26: 0 | AG26: ОСН
A27: 1035001602570 | B27: 5007032441 | C27: АО "АГРОФИРМА "ОРУДЬЕВСКОЕ" | D27: АКЦИОНЕРНОЕ ОБЩЕСТВО "АГРОФИРМА "ОРУДЬЕВСКОЕ" | E27: 3509402 | F27: 46415000499 | G27: 16 | H27: 12267 | I27: 500701001 | J27: 2002-06-21 | L27: 68.1 | M27: Покупка и продажа собственного недвижимого имущества | N27: 01.42,52.24.2,52.29,64.92,68.2 | O27: КОМАРОВ ОЛЕГ ВАЛЕНТИНОВИЧ | P27: 772580524669 | Q27: ГЕНЕРАЛЬНЫЙ ДИРЕКТОР | R27: 141825, МОСКОВСКАЯ ОБЛАСТЬ, М.О. ДМИТРОВСКИЙ, С ОРУДЬЕВО, УЛ ЦЕНТРАЛЬНАЯ, Д. 87А, ПОМЕЩ. 28 | S27: +74959939868,+74969939868 | V27: 1649943000 | W27: 264331000 | X27: 0 | Y27: 567858000 | Z27: 1274240000 | AA27: 6061000 | AB27: -431443000 | AC27: -205576000 | AD27: -431443000 | AE27: Микропредприятие | AF27: 3 | AG27: УСН
A28: 1035001610808 | B28: 5007041559 | C28: ООО "МДК" | D28: ОБЩЕСТВО С ОГРАНИЧЕННОЙ ОТВЕТСТВЕННОСТЬЮ "МДК" | E28: 13369267 | F28: 46415000329 | G28: 16 | H28: 12300 | I28: 500701001 | J28: 2003-04-02 | L28: 55.10 | M28: Деятельность гостиниц и прочих мест для временного проживания | N28: 41.2,43.12,43.12.3,43.2,43.3,43.33,43.99.1,43.99.4,43.99.6,43.99.7,45.20.1,45.20.2,47.11.2,47.30,52.29,55.30,55.90,56.10,56.10.1,56.10.3,56.30,68.2,77.21,79.11,86.90.4,88.10,93.11,93.19,96.02,96.04 | O28: ЮДЕНКОВ НИКОЛАЙ ЕВГЕНЬЕВИЧ | P28: 771526598212 | Q28: ГЕНЕРАЛЬНЫЙ ДИРЕКТОР | R28: 141840, МОСКОВСКАЯ ОБЛАСТЬ, М.О. ДМИТРОВСКИЙ, Д КУРОВО, Д. 69 | S28: +74957967504,+74957888512,+74952680243 | T28: www.dmitrov.golf,sorochany-mdk.ru | U28: info@dmitrov.golf,corp@dmitrov.golf,secretaru@sorochany-mdk.ru,secretary@sorochany-mdk.ru | V28: 240000000 | W28: 160710000 | X28: 38291000 | Y28: 8661000 | Z28: 66395000 | AA28: 141278000 | AB28: -742000 | AC28: -27854000 | AD28: -127000 | AE28: Малое предприятие | AF28: 51 | AG28: ОСН
A29: 1037789058900 | B29: 7702511168 | C29: АО "ЭКСР" | D29: АКЦИОНЕРНОЕ ОБЩЕСТВО "ЭБЕРСПЕХЕР КЛИМАТИЧЕСКИЕ СИСТЕМЫ РУС" | E29: 72081725 | F29: 45286575000 | G29: 23 | H29: 12267 | I29: 770301001 | J29: 2003-12-17 | L29: 45.31.1 | M29: Торговля оптовая автомобильными деталями, узлами и принадлежностями, кроме деятельности агентов | N29: 28.25.1,28.25.12,28.25.13,28.25.2,29.31,29.32,29.32.3,45.20,45.31.1,45.31.2,45.32,52.10,52.24,52.29,74.20,74.30,82.19,82.92,82.99 | O29: ВОСТРОПЯТОВА МАРИНА ВЛАДИМИРОВНА | P29: 504704660886 | Q29: Генеральный директор | R29: 123104, Г.МОСКВА, ВН.ТЕР.Г. МУНИЦИПАЛЬНЫЙ ОКРУГ ПРЕСНЕНСКИЙ, Б-Р ТВЕРСКОЙ, Д. 13, СТР. 1 | S29: +74956471324,+78002003237,+74956455979,+74952120590,+70957558127,+70959248551,+74957558127 | T29: www.otem.ru | U29: info-ru@eberspacher.com,info-ru@eberspaecher.com | V29: 302870000 | W29: 505550000 | X29: 1319000 | Y29: 284787000 | Z29: 125703000 | AA29: 220027000 | AB29: 24012000 | AC29: -11445000 | AD29: 40861000 | AF29: 27 | AG29: ОСН
A30: 1037789057305 | B30: 7714528631 | C30: ООО "СЕВЕРНЫЙ АВТОВОКЗАЛ" | D30: ОБЩЕСТВО С ОГРАНИЧЕННОЙ ОТВЕТСТВЕННОСТЬЮ "СЕВЕРНЫЙ АВТОВОКЗАЛ" | E30: 71678361 | F30: 45277598000 | G30: 23 | H30: 12300 | I30: 771401001 | J30: 2003-12-17 | L30: 55.10 | M30: Деятельность гостиниц и прочих мест для временного проживания | N30: 41.20,43.11,43.12.3,43.91,43.99,43.99,55.10,56.10.1,68.10,68.10.1,68.20,68.32,70.22,71.1,71.11,71.12.5,71.12.6 | O30: БАЛТАОГЛУ ДЖЮНЕЙТ | P30: 770871662067 | Q30: ГЕНЕРАЛЬНЫЙ ДИРЕКТОР | R30: 125167, Г.МОСКВА, ПР-КТ ЛЕНИНГРАДСКИЙ, Д.37, К.8 | S30: +74996540320,+70954824592,+74954824592 | V30: 136709700 | W30: 257602000 | X30: 26703000 | Y30: 446000 | Z30: 84042000 | AA30: 19114000 | AB30: 82861000 | AC30: 167883000 | AD30: 111871000 | AF30: 4 | AG30: ОСН
A31: 1035005002361 | B31: 5027023420 | C31: ООО "ЛИДЕР" | D31: ОБЩЕСТВО С ОГРАНИЧЕННОЙ ОТВЕТСТВЕННОСТЬЮ "ЛИДЕР" | E31: 18192537 | F31: 46448561000 | G31: 16 | H31: 12300 | I31: 502701001 | J31: 1992-09-22 | L31: 49.4 | M31: Деятельность автомобильного грузового транспорта и услуги по перевозкам | N31: 10.32,11.07,11.07.2,29.20,29.20.5,45.20,45.20.1,46.16.2,46.17.1,52.10,68.20,68.20.1,70.10.2,77.11,77.12 | O31: МИРОШКИН АЛЕКСАНДР АЛЕКСЕЕВИЧ | P31: 500510664429 | Q31: ДИРЕКТОР | R31: 140032, МОСКОВСКАЯ ОБЛАСТЬ, Г ЛЮБЕРЦЫ, ПГТ. МАЛАХОВКА, УЛ ГАРАЖНАЯ, Д. 3 | S31: +74955012311,+74955013572,+74955019754,+74985013572,+74985012311,+79035964869,+74955011218 | U31: kazakova@liderco.ru | V31: 580621789 | W31: 285141000 | X31: 49009000 | Y31: 1338000 | Z31: 180751000 | AA31: 21063000 | AB31: 328715000 | AC31: 47337000 | AD31: 342196000 | AE31: Малое предприятие | AF31: 73 | AG31: ОСН
A32: 1035006452711 | B32: 5032014816 | C32: ООО ДСЭ " ОСЕНЬ " | D32: ОБЩЕСТВО С ОГРАНИЧЕННОЙ ОТВЕТСТВЕННОСТЬЮ ДИРЕКЦИЯ ПО СТРОИТЕЛЬСТВУ И ЭКСПЛУАТАЦИИ " ОСЕНЬ " | E32: 31322522 | F32: 46455000513 | G32: 23 | H32: 12300 | I32: 503201001 | J32: 1991-09-20 | L32: 68.32.1 | M32: Управление эксплуатацией жилого фонда за вознаграждение или на договорной основе | N32: 01.61,43.99,66.12,68.2,68.32.1,73.20.1,93.19 | O32: ЧЕПРАСОВА ЕЛЕНА ВИКТОРОВНА | P32: 771502261562 | Q32: ГЕНЕРАЛЬНЫЙ ДИРЕКТОР | R32: 143026, МОСКОВСКАЯ ОБЛАСТЬ, Г ОДИНЦОВО, УЛ ОСЕННЯЯ (НЕМЧИНОВО ТЕР.), Д. 1 | S32: +74952335476,+74954149675,+74957481006,+74957480088,+79166216584 | V32: 231250250 | W32: 121105000 | X32: 172255000 | Y32: 1684000 | Z32: 68216000 | AA32: 7322000 | AB32: 17000 | AC32: 100000 | AD32: 24000 | AF32: 38 | AG32: ОСН
A33: 1127746400759 | B33: 7726697521 | C33: ООО "НИЦЭВТ-ЭНЕРГО" | D33: ОБЩЕСТВО С ОГРАНИЧЕННОЙ ОТВЕТСТВЕННОСТЬЮ "НИЦЭВТ-ЭНЕРГО" | E33: 9814313 | F33: 45296593000 | G33: 16 | H33: 12300 | I33: 772601001 | J33: 2012-05-24 | L33: 35.11.1 | M33: Производство электроэнергии тепловыми электростанциями, в том числе деятельность по обеспечению работоспособности электростанций | N33: 33.12,33.12,33.12,33.12,33.12,33.12,33.14,33.14,33.14,33.20,35.11,35.11.4,35.30,35.30.1,35.30.11,35.30.13,35.30.14,35.30.15,35.30.2,35.30.3,35.30.4,35.30.5,36.00,36.00.1,36.00.2,41.20,41.20,42.21,42.21,42.22.2,42.22.3,42.99,43.11,43.11,43.12.1,43.12.3,43.21,43.22,43.29,43.31,43.32,43.33,43.34,43.34.1,43.34.2,43.39,43.91,43.99,43.99,43.99.1,43.99.2,43.99.3,43.99.4,43.99.5,43.99.6,43.99.7,43.99.9,46.12.1,46.71.2,47.52.73,47.78.6,49.50,49.50.2,49.50.21,52.10,52.10.2,52.10.22,52.10.23,52.21,52.21.2,68.10,68.10.1,68.10.12,68.20,68.20.2,68.31.1,68.31.12,68.31.2,68.31.22,68.31.3,68.31.32,68.31.4,68.31.42,68.31.5,68.32,68.32,68.32.2,70.22,71.11.1,71.12,71.12.1,71.12.12,71.12.13,71.12.45,71.20.6,71.20.9,73.20,73.20.1,73.20.2,77.39.23,81.22,81.29.9 | O33: СУКОВАТИКОВ РОМАН ПАВЛОВИЧ | P33: 503002547849 | Q33: ГЕНЕРАЛЬНЫЙ ДИРЕКТОР | R33: 117587, Г.МОСКВА, ВН.ТЕР.Г. МУНИЦИПАЛЬНЫЙ ОКРУГ ЧЕРТАНОВО СЕВЕРНОЕ, Ш ВАРШАВСКОЕ, Д. 125, СТР. 1, СЕКЦИЯ/ЭТАЖ/ПОМЕЩ. 3/5/IX, КОМ. 2 | S33: +79032582997,+79255068451,+74953196067 | T33: nicevt-energo.ru | V33: 393990122 | W33: 408872000 | X33: 679870000 | Y33: 0 | Z33: 114218000 | AA33: 126359000 | AB33: 61141000 | AC33: 132120000 | AD33: 81520000 | AF33: 12 | AG33: ОСН
A34: 1127746460434 | B34: 7733805552 | C34: ООО "МПС СОФТ" | D34: ОБЩЕСТВО С ОГРАНИЧЕННОЙ ОТВЕТСТВЕННОСТЬЮ "МАСТЕР ПРОДАКШН СОФТ ЭНД СИСТЕМЗ" | E34: 9875243 | F34: 45286555000 | G34: 16 | H34: 12300 | I34: 770101001 | J34: 2012-06-13 | L34: 62.0 | M34: Разработка компьютерного программного обеспечения, консультационные услуги в данной области и другие сопутствующие услуги | N34: 18.2,18.20,26.51,26.51.7,33.20,43.2,43.21,46.43.3,46.51,46.69.5,62.02,62.09,63.11.1,71.1,71.12.5,71.12.6,95.1 | O34: ОЛЬХОВ ВЛАДИМИР ПЕТРОВИЧ | P34: 644922752422 | Q34: ГЕНЕРАЛЬНЫЙ ДИРЕКТОР | R34: 105066, Г.МОСКВА, ВН.ТЕР.Г. МУНИЦИПАЛЬНЫЙ ОКРУГ БАСМАННЫЙ, УЛ НИЖНЯЯ КРАСНОСЕЛЬСКАЯ, Д. 40/12, К. 2, ПОМЕЩ. 1Н/3 | S34: +79266295688 | T34: rs485.ru | V34: 203381000 | W34: 662903000 | X34: 8123000 | Y34: 5918000 | Z34: 124493000 | AA34: 27779000 | AB34: 258905000 | AC34: 237791000 | AD34: 258905000 | AE34: Малое предприятие | AF34: 129 | AG34: ОСН
A35: 1125001005997 | B35: 5001091698 | C35: ООО "ТАРУСОВО-ДЕВЕЛОПМЕНТ" | D35: ОБЩЕСТВО С ОГРАНИЧЕННОЙ ОТВЕТСТВЕННОСТЬЮ "ТАРУСОВО-ДЕВЕЛОПМЕНТ" | E35: 18186531 | F35: 46478000771 | G35: 16 | H35: 12300 | I35: 507801001 | J35: 2012-12-13 | L35: 55.10 | M35: Деятельность гостиниц и прочих мест для временного проживания | N35: 56.10.1,64.99.11,64.99.3,68.1,68.2,68.3,68.31.1,68.31.2,68.31.3,68.31.4,77.32 | O35: ПОНОМАРЕНКО ЮЛИЯ АНАТОЛЬЕВНА | P35: 251101083838 | Q35: ГЕНЕРАЛЬНЫЙ ДИРЕКТОР | R35: 141932, МОСКОВСКАЯ ОБЛАСТЬ, Г.О. ТАЛДОМСКИЙ, Д ТАРУСОВО, ТЕР. ЛЕПОТА, Д. 1, ЭТАЖ 1, ПОМЕЩ. 15 | S35: +79057133446,+74952044091,+79858128507,+79653050174,+74956600644 | U35: notary@notarys.ru | V35: 168720737 | W35: 107202000 | X35: 146912000 | Y35: 399000 | Z35: 13414000 | AA35: 311675000 | AB35: 312000 | AC35: 19057000 | AD35: 577000 | AE35: Микропредприятие | AF35: 0 | AG35: ОСН
A36: 1167746525726 | B36: 7714391183 | C36: ООО "МЕДИА ЭКСТЕНШНС" | D36: ОБЩЕСТВО С ОГРАНИЧЕННОЙ ОТВЕТСТВЕННОСТЬЮ "МЕДИА ЭКСТЕНШНС" | E36: 2837541 | F36: 45277598000 | G36: 16 | H36: 12300 | I36: 771401001 | J36: 2016-06-02 | L36: 68.20 | M36: Аренда и управление собственным или арендованным недвижимым имуществом | N36: 18.12,43.21,58.11,58.14,59.11,60.10,60.20,61.10,62.01,62.02,62.09,63.11.1,64.99,68.31.1,68.31.2,68.31.3,68.31.4,68.32,70.22,71.11.1,72.20,73.11,74.30,77.11,77.33,78.30,80.10,80.20,80.30,81.22,81.29.9,82.19,82.99,90.0,91.01,93.11,93.29,95.11 | O36: ЛОБАШОВ ИЛЬЯ АНДРЕЕВИЧ | P36: 772826566206 | Q36: ГЕНЕРАЛЬНЫЙ ДИРЕКТОР | R36: 125284, Г.МОСКВА, Ш. ХОРОШЁВСКОЕ, Д. 32А, ПОМЕЩ. VII КОМН 46 | S36: +74959402025 | V36: 100100000 | W36: 144543000 | X36: 141907000 | Y36: 2000 | Z36: 4927000 | AA36: 9593000 | AB36: 79375000 | AC36: 0 | AD36: 0 | AE36: Микропредприятие | AF36: 2 | AG36: ОСН
A37: 1127747086367 | B37: 7708773522 | C37: ООО "ДЕЛЬТАХОЛДИНГ" | D37: ОБЩЕСТВО С ОГРАНИЧЕННОЙ ОТВЕТСТВЕННОСТЬЮ "ДЕЛЬТАХОЛДИНГ" | E37: 13238714 | F37: 45296559000 | G37: 16 | H37: 12300 | I37: 772501001 | J37: 2012-10-26 | L37: 77.39.12 | M37: Аренда и лизинг железнодорожного транспорта и оборудования | N37: 30.2,30.20.4,30.20.9,33.17,46.69.1,46.72,49.10,49.20,52.21.1,70.22 | O37: СОЛОВЬЁВА ИРИНА АЛЕКСАНДРОВНА | P37: 772584155116 | Q37: ГЕНЕРАЛЬНЫЙ ДИРЕКТОР | R37: 115114, Г.МОСКВА, ВН.ТЕР.Г. МУНИЦИПАЛЬНЫЙ ОКРУГ ДАНИЛОВСКИЙ, ПЕР 1-Й КОЖЕВНИЧЕСКИЙ, Д. 6, СТР. 1, ПОМЕЩ. 8/4 | S37: +79852273175 | U37: info@delta-holding.ru,aleksandrakareva@mail.ru | V37: 200000000 | W37: 194446000 | X37: 618032000 | Y37: 16000 | Z37: 133531000 | AA37: 14871000 | AB37: -26682000 | AC37: 33022000 | AD37: -35486000 | AE37: Микропредприятие | AF37: 1 | AG37: ОСН
A38: 1135042007539 | B38: 5042129460 | C38: ООО "ПСБ БИЗНЕС" | D38: ОБЩЕСТВО С ОГРАНИЧЕННОЙ ОТВЕТСТВЕННОСТЬЮ "ПСБ БИЗНЕС" | E38: 18098784 | F38: 45286590000 | G38: 16 | H38: 12300 | I38: 770401001 | J38: 2013-09-23 | L38: 55.10 | M38: Деятельность гостиниц и прочих мест для временного проживания | N38: 41.20,43.21,43.22,43.29,43.31,43.32,43.33,43.91,43.99,52.10,68.10,68.10.1,68.10.11,68.10.12,68.20,68.31,68.31.1,68.31.2,68.31.3,68.31.4,68.31.5,68.32,68.32.1,68.32.2,69.10,69.20,71.11,71.12,71.12.2,74.10,82.30,93.11,93.19 | O38: Доступ к сведениям ограничен | P38: — | Q38: — | R38: 119021, Г.МОСКВА, ВН.ТЕР.Г. МУНИЦИПАЛЬНЫЙ ОКРУГ ХАМОВНИКИ, УЛ ЛЬВА ТОЛСТОГО, Д. 23, СТР. 3, ПОМЕЩ. II, КОМ. 1К, 1Л, 1М, 1Н, 1О, 1П | S38: +74957771020,+79032754278 | U38: dzo.procurement@psbank.ru,korotkovatv@psbank.ru,piladzisoa@psbank.ru | V38: 1716624000 | W38: 656240000 | X38: 24556000 | Y38: 22592000 | Z38: 1209608000 | AA38: 2005416000 | AB38: -1662061000 | AC38: -422492000 | AD38: -1623384000 | AF38: 74 | AG38: ОСН
A39: 1024001175516 | B39: 4027055893 | C39: ООО "ЭНЕРГОАТОМИНВЕСТ" | D39: ОБЩЕСТВО С ОГРАНИЧЕННОЙ ОТВЕТСТВЕННОСТЬЮ "ЭНЕРГОАТОМИНВЕСТ" | E39: 25922386 | F39: 45296561000 | G39: 16 | H39: 12300 | I39: 772501001 | J39: 2002-07-10 | L39: 64.99 | M39: Предоставление прочих финансовых услуг, кроме услуг по страхованию и пенсионному обеспечению, не включенных в другие группировки | N39: 33.20,35.11.3,41.20,42.11,42.21,42.22.2,43.11,43.12.1,43.12.3,43.21,43.22,43.29,43.31,43.32,43.33,43.34,43.91,43.99,43.99.1,43.99.5,45.1,45.11.1,45.11.2,45.11.3,45.11.4,45.19.1,45.19.2,45.19.3,45.19.4,45.20,45.3,49.39,49.4,55.10,55.90,56.10,56.10.1,56.10.3,56.29,63.99.1,64.91,66.22,68.20,68.20.2,70.22,71.12,71.12.1,71.12.12,77.39.1,79.11,79.12,79.90,85.41.9,86.90.4 | O39: БУДЬКО ИГОРЬ ВИТАЛЬЕВИЧ | P39: 772781534480 | Q39: ГЕНЕРАЛЬНЫЙ ДИРЕКТОР | R39: 115419, Г.МОСКВА, ВН.ТЕР.Г. МУНИЦИПАЛЬНЫЙ ОКРУГ ДОНСКОЙ, ПРОЕЗД 2-Й РОЩИНСКИЙ, Д. 8, СТР. 4, ЭТ./ПОМЕЩ. 5/I, КОМ. 1-35, 72-85 | S39: +74951079514,+74951079515,+74956207032,+74956207037,+74956207033,+74957305394,+74956207036,+74946207032,+74956207035,+74956207034,+74959670131,+74953664495,+74992701726,+74956203270,+74957305395,+74957305393,+78495735394,+74957305396,+74959671272,+74959613456,+74959671271,+78453499314 | U39: info@atominvest.com,senizhaleyko@rosatom.ru,kuznetsovatv@atominvest.com,nnivyalkina@rosatom.ru,koryagin@atominvest.com,arvkoryagin@rosatom.ru,vyalkina@atominvest.com,zhaleiko@atominvest.com,brodecki@atominvest.com,rusakov@atominvest.com,info@atominvest.ru,tulaev@atominvest.com,tulaev@atominest.com,info@atoninvest.com,muhanov@atominvest.com,brodecki@atominvestt.com,7622393@gmail.com,brodecki@atominvect.com,brodetcki@atominvest.com | V39: 8876790289 | W39: 553540000 | X39: 19488000 | Y39: 869000 | Z39: 67833000 | AA39: 530537000 | AB39: -82064000 | AC39: 58458000 | AD39: -88896000 | AF39: 82 | AG39: ОСН
A40: 5077746824436 | B40: 7703634853 | C40: ООО "ТВК "ТИШИНКА" | D40: ОБЩЕСТВО С ОГРАНИЧЕННОЙ ОТВЕТСТВЕННОСТЬЮ "ТОРГОВО-ВЫСТАВОЧНЫЙ КОМПЛЕКС "ТИШИНКА" | E40: 77306436 | F40: 45286575000 | G40: 16 | H40: 12300 | I40: 770301001 | J40: 2007-05-24 | L40: 68.20.2 | M40: Аренда и управление собственным или арендованным нежилым недвижимым имуществом | N40: 18.1,41.2,43.2,43.3,45.11.1,45.11.2,45.11.3,45.11.4,45.19.1,45.19.2,45.19.3,45.19.4,45.20.1,45.20.2,45.3,45.40,46.1,46.2,46.3,46.6,46.7,46.9,47.1,47.2,47.5,47.73,47.74,47.75,47.9,49.32,49.4,52.10,52.21.24,52.29,55.1,55.2,56.10,56.10.1,56.10.3,56.29,56.30,68.10.11,68.10.12,68.10.21,68.10.22,68.10.23,68.20.1,68.31.11,68.31.12,68.31.21,68.31.22,68.31.31,68.31.32,68.31.41,68.31.42,68.32.2,69.10,69.20,70.22,73.11,77.11,77.33,77.39,77.39.11,82.99,86,87,88,93.1,93.2,95.2 | O40: ОБЩЕСТВО С ОГРАНИЧЕННОЙ ОТВЕТСТВЕННОСТЬЮ "КАПИТАЛ ГРУП РАЗВИТИЕ" | P40: 9703173758 | Q40: — | R40: 123056, Г.МОСКВА, ПЛ. ТИШИНСКАЯ, Д.1, СТР.1 | S40: +74957390500,+74957390513,+74957390540 | T40: www.tishinka.com | U40: v.mitin@tishinka.com,v.ilchenko@tishinka.com,szd@tishinka.com,info@tishinka.com | V40: 161000000 | W40: 215361000 | X40: 2795000 | Y40: 5000 | Z40: 60760000 | AA40: 27484000 | AB40: -177480000 | AC40: -19863000 | AD40: -177480000 | AE40: Малое предприятие | AF40: 24 | AG40: ОСН
A41: 1027739292954 | B41: 7704017726 | C41: ОАО "ТВЕРСКАЯ, 16" | D41: ОТКРЫТОЕ АКЦИОНЕРНОЕ ОБЩЕСТВО "ТВЕРСКАЯ, 16" | E41: 29007000 | F41: 45286585000 | G41: 16 | H41: 12247 | I41: 771001001 | J41: 1993-06-29 | L41: 68.20.29 | M41: Аренда и управление собственным или арендованным прочим нежилым недвижимым имуществом | N41: 41.20,43.2,43.3,46.90,68.20.2,71.11.1 | O41: ЛЕНЬШИНА МАРИНА ВЯЧЕСЛАВОВНА | P41: 771703236485 | Q41: ГЕНЕРАЛЬНЫЙ ДИРЕКТОР | R41: 125375, Г.МОСКВА, ВН.ТЕР.Г. МУНИЦИПАЛЬНЫЙ ОКРУГ ТВЕРСКОЙ, УЛ ТВЕРСКАЯ, Д. 16, СТР. 1, ОФИС Б802 | S41: +74959358299,+74959358370,+74959357055,+74959358374,+74959358376,+74959358367,+74959358372 | V41: 127840000 | W41: 454491000 | X41: 242000 | Y41: 1202000 | Z41: 116210000 | AA41: 140123000 | AB41: 161575000 | AC41: 174661000 | AD41: 215599000 | AF41: 7 | AG41: ОСН
A42: 1027739323248 | B42: 7704172866 | C42: АО "ГАЗЕТА МЕТРО" | D42: АКЦИОНЕРНОЕ ОБЩЕСТВО "ГАЗЕТА МЕТРО" | E42: 47302889 | F42: 45277556000 | G42: 42 | H42: 12267 | I42: 771401001 | J42: 1997-08-26 | L42: 58.13.1 | M42: Издание газет в печатном виде | N42: 18.11,18.12,58.13,58.14,58.19,58.29,59.11,59.12,62.01,62.09,63.11,63.12,63.91,73.11,73.12,73.20,74.10,74.20,82.30,90.01,93.19,93.29 | O42: КЛИМЕНЧЕВА НАТАЛЬЯ АЛЕКСАНДРОВНА | P42: 772774217681 | Q42: ГЕНЕРАЛЬНЫЙ ДИРЕКТОР | R42: 125124, Г.МОСКВА, ВН.ТЕР.Г. МУНИЦИПАЛЬНЫЙ ОКРУГ БЕГОВОЙ, УЛ ПРАВДЫ, Д. 24, СТР. 4, ПОМЕЩ. 1Н | S42: +74957871211,+79060819736 | T42: www.gazetametro.ru | U42: natalia.zlobenko@gazetametro.ru,ekaterina.burtseva@gazetametro.ru,eka_burceva@mail.ru,dmitry.zarubin@gazetametro.ru,info@gazetametro.ru | V42: 405263200 | W42: 177031000 | X42: 806000 | Y42: 0 | Z42: 34005000 | AA42: 23375000 | AB42: -163821000 | AC42: -359402000 | AD42: -217747000 | AF42: 69 | AG42: ОСН
A43: 1027739262770 | B43: 5024032064 | C43: ООО "ДАЕВ ПЛАЗА" | D43: ОБЩЕСТВО С ОГРАНИЧЕННОЙ ОТВЕТСТВЕННОСТЬЮ "ДАЕВ ПЛАЗА" | E43: 45739820 | F43: 45286565000 | G43: 16 | H43: 12300 | I43: 770801001 | J43: 2002-02-05 | L43: 68.20.1 | M43: Аренда и управление собственным или арендованным жилым недвижимым имуществом | N43: 61.10.9,68.20.2 | O43: АНУФРИЕВ ИВАН ЕВГЕНЬЕВИЧ | P43: 500108482716 | Q43: ГЕНЕРАЛЬНЫЙ ДИРЕКТОР | R43: 107045, Г.МОСКВА, ПЕР ДАЕВ, Д. 20 | S43: +74956048116,+74956048248,+74956048328,+74956048471,+74956048484,+74959562955,+74956048020,+74952048020,+74956048444 | T43: www.daev-plaza.ru | U43: info@deavnet.ru,info@daevnet.ru,-@-.-,daevplasa@mail.ru,daev@daev-plaza.ru | V43: 175000000 | W43: 183270000 | X43: 77448000 | Y43: 465000 | Z43: 9553000 | AA43: 29636000 | AB43: 4533000 | AC43: 8109000 | AD43: 5428000 | AF43: 42 | AG43: ОСН
A44: 1187746267400 | B44: 7704452567 | C44: ООО "ЭЛГАД ИНВЕСТ" | D44: ОБЩЕСТВО С ОГРАНИЧЕННОЙ ОТВЕТСТВЕННОСТЬЮ "ЭЛГАД ИНВЕСТ" | E44: 27233073 | F44: 45286555000 | G44: 34 | H44: 12300 | I44: 770901001 | J44: 2018-03-12 | L44: 68.20.2 | M44: Аренда и управление собственным или арендованным нежилым недвижимым имуществом | N44: 64.92,64.99,68.10,68.10.22,68.20 | O44: ГАДАЕВ ГАЙ НАТАНОВИЧ | P44: 771878729509 | Q44: ГЕНЕРАЛЬНЫЙ ДИРЕКТОР | R44: 105005, Г.МОСКВА, НАБ. АКАДЕМИКА ТУПОЛЕВА, Д. 15, ЭТ/ПОМ/КОМ 3/I/6 | S44: +74956287650 | V44: 1041751000 | W44: 249318000 | X44: 33107000 | Y44: 2324000 | Z44: 32279000 | AA44: 44862000 | AB44: 18037000 | AC44: 66674000 | AD44: 104517000 | AE44: Малое предприятие | AF44: 6 | AG44: ОСН
A45: 1115074015132 | B45: 5036118421 | C45: ООО "ФОРМА" | D45: ОБЩЕСТВО С ОГРАНИЧЕННОЙ ОТВЕТСТВЕННОСТЬЮ "ФОРМА" | E45: 92734738 | F45: 46460000000 | G45: 23 | H45: 12300 | I45: 503601001 | J45: 2011-10-20 | L45: 81.10 | M45: Деятельность по комплексному обслуживанию помещений | N45: 41.2,43.12,43.2,43.3,43.99,64.19,64.99,66.1,68.1,68.2,68.3,71.1,71.12.5,71.12.6 | O45: КОСЦОВ ЮРИЙ ВЛАДИМИРОВИЧ | P45: 773401716993 | Q45: ДИРЕКТОР | R45: 142100, МОСКОВСКАЯ ОБЛАСТЬ, Г. ПОДОЛЬСК, УЛ. КОМСОМОЛЬСКАЯ, Д. 1, СТР. 51А, ПОМЕЩ. 73 | S45: +74955803060 | U45: n.minaev@danhson.com | V45: 149314000 | W45: 219254000 | X45: 230037000 | Y45: 10000 | Z45: 13802000 | AA45: 12358000 | AB45: 182799000 | AC45: 184260000 | AD45: 245018000 | AF45: 1 | AG45: ОСН
A46: 1175053010274 | B46: 5012094725 | C46: ООО "МАСТЕР ДИСТРИБЬЮТОР" | D46: ОБЩЕСТВО С ОГРАНИЧЕННОЙ ОТВЕТСТВЕННОСТЬЮ "МАСТЕР ДИСТРИБЬЮТОР" | E46: 16009813 | F46: 45296571000 | G46: 16 | H46: 12300 | I46: 772401001 | J46: 2017-06-14 | L46: 68.20.2 | M46: Аренда и управление собственным или арендованным нежилым недвижимым имуществом | N46: 46.36,46.36.2,46.36.3,46.38.2,46.38.29,49.41,49.41.1,49.41.2,49.41.3,49.42,52.10,52.10.9,52.21.2,52.21.29,52.24,52.24.1,52.24.2,52.29,82.99 | O46: УРБАН АЛЕКСАНДР ГЕННАДЬЕВИЧ | P46: 771000788588 | Q46: ГЕНЕРАЛЬНЫЙ ДИРЕКТОР | R46: 115230, Г.МОСКВА, ВН.ТЕР.Г. МУНИЦИПАЛЬНЫЙ ОКРУГ НАГАТИНО-САДОВНИКИ, ПРОЕЗД ХЛЕБОЗАВОДСКИЙ, Д. 7, СТР. 9, КОМ. 23/Н | S46: +74995196451 | U46: master-distributor@master-distributor.ru | V46: 180000000 | W46: 1226316000 | X46: 15771000 | Y46: 11000 | Z46: 13549000 | AA46: 281976000 | AB46: 554551000 | AC46: 980668000 | AD46: 717771000 | AE46: Малое предприятие | AF46: 11 | AG46: ОСН
A47: 1177746006437 | B47: 7703421968 | C47: ООО "ПЛТ БЕКАСОВО" | D47: ОБЩЕСТВО С ОГРАНИЧЕННОЙ ОТВЕТСТВЕННОСТЬЮ "ПЛТ БЕКАСОВО" | E47: 6219952 | F47: 45286575000 | G47: 16 | H47: 12300 | I47: 770301001 | J47: 2017-01-09 | L47: 68.20.29 | M47: Аренда и управление собственным или арендованным прочим нежилым недвижимым имуществом | N47: 41.20,43.99,52.10,52.21,52.29,64.99.11,64.99.3,68.10,68.10.23,68.20.2 | O47: БЕСПАЛОВ ДМИТРИЙ РОБЕРТОВИЧ | P47: 711601915507 | Q47: ГЕНЕРАЛЬНЫЙ ДИРЕКТОР | R47: 123112, Г.МОСКВА, ВН.ТЕР.Г. МУНИЦИПАЛЬНЫЙ ОКРУГ ПРЕСНЕНСКИЙ, НАБ ПРЕСНЕНСКАЯ, Д. 12, ЭТАЖ 30, КОМ. 21 | S47: +74996438480 | V47: 587903873 | W47: 688857000 | X47: 67000 | Y47: 120000 | Z47: 10440000 | AA47: 105679000 | AB47: 325100000 | AC47: 439494000 | AD47: 433467000 | AF47: 1 | AG47: ОСН
A48: 1217700608729 | B48: 9704106828 | C48: ООО "СИГМА КОНСТРАКШЕН" | D48: ОБЩЕСТВО С ОГРАНИЧЕННОЙ ОТВЕТСТВЕННОСТЬЮ "СИГМА КОНСТРАКШЕН" | E48: 54633380 | F48: 45286552000 | G48: 16 | H48: 12300 | I48: 770401001 | J48: 2021-12-13 | L48: 46.73 | M48: Торговля оптовая лесоматериалами, строительными материалами и санитарно-техническим оборудованием | N48: 23.20,23.61,23.63,23.64,23.69,46.69,46.73.6,49.42,68.20,77.12 | O48: ПОЛЕНОВ АЛЕКСАНДР ЮРЬЕВИЧ | P48: 772106508916 | Q48: ГЕНЕРАЛЬНЫЙ ДИРЕКТОР | R48: 119019, Г.МОСКВА, ВН.ТЕР.Г. МУНИЦИПАЛЬНЫЙ ОКРУГ АРБАТ, УЛ АРБАТ, Д. 6/2, ПОМЕЩ. 1/1/4 | S48: +79059747555 | U48: sigma.tgy@gmail.com | V48: 111216374 | W48: 365907000 | X48: 68361000 | Y48: 113199000 | Z48: 451895000 | AA48: 447939000 | AB48: -5116000 | AC48: 0 | AD48: 0 | AE48: Малое предприятие | AF48: 10 | AG48: ОСН
A49: 1247700304268 | B49: 9701284011 | C49: АО "Л-КОНСАЛТ" | D49: АКЦИОНЕРНОЕ ОБЩЕСТВО "Л-КОНСАЛТ" | E49: 85921612 | F49: 45286555000 | G49: 16 | H49: 12267 | I49: 770101001 | J49: 2024-04-09 | L49: 68.20 | M49: Аренда и управление собственным или арендованным недвижимым имуществом | N49: 41.20,42.11,42.91,42.99,43.21,43.22,43.29,43.91,43.99,43.99.1,62.02,62.09,63.11.1,64.99.1,70.22,71.12.1,72.19,82.99,85.42.9,95.11 | O49: РОДИНА ЕКАТЕРИНА ВЯЧЕСЛАВОВНА | P49: 773607732822 | Q49: ГЕНЕРАЛЬНЫЙ ДИРЕКТОР | R49: 105066, Г.МОСКВА, ВН.ТЕР.Г. МУНИЦИПАЛЬНЫЙ ОКРУГ БАСМАННЫЙ, УЛ ДОБРОСЛОБОДСКАЯ, Д. 5 | S49: +74956356441,+79166944953 | V49: 290630000 | W49: 147473000 | X49: 282478000 | Y49: 54000 | Z49: 211003000 | AA49: 15635000 | AB49: 117344000 | AC49: 10922000 | AD49: 133085000 | AE49: Малое предприятие | AF49: 42 | AG49: ОСН
A50: 1217700481613 | B50: 7714477151 | C50: ООО "ГАЛС-ПРОЕКТ" | D50: ОБЩЕСТВО С ОГРАНИЧЕННОЙ ОТВЕТСТВЕННОСТЬЮ "ГАЛС-ПРОЕКТ" | E50: 53163653 | F50: 45277556000 | G50: 16 | H50: 12300 | I50: 771401001 | J50: 2021-10-11 | L50: 68.20.29 | M50: Аренда и управление собственным или арендованным прочим нежилым недвижимым имуществом | N50: 41.20,43.11,43.12.1,43.21,43.29,43.39,43.99.7,46.49,46.90,63.11.1,64.99,68.10,68.20,68.31.3,68.31.32,68.31.4,68.31.42,68.32.2,69.10,69.20,70.22,71.12.1,71.12.2,71.12.5,71.12.6,72.19,73.20.1 | O50: ЦЫГАНКОВ ДЕНИС АЛЕКСЕЕВИЧ | P50: 773127149530 | Q50: ГЕНЕРАЛЬНЫЙ ДИРЕКТОР | R50: 125284, Г.МОСКВА, ВН.ТЕР.Г. МУНИЦИПАЛЬНЫЙ ОКРУГ БЕГОВОЙ, ПР-КТ ЛЕНИНГРАДСКИЙ, Д. 35, СТР. 1, ЭТАЖ/ПОМЕЩ./КОМ. 5/I/19 | S50: +79263725626 | V50: 2051000000 | W50: 77895000 | X50: 812788000 | Y50: 68850000 | Z50: 24832000 | AA50: 108315000 | AB50: 16632000 | AC50: -82196000 | AD50: 46448000 | AF50: 22 | AG50: ОСН
A51: 1257700039805 | B51: 7743464703 | C51: ООО "СЗ "ГАЛС-СТАРОПЕТРОВСКИЙ" | D51: ОБЩЕСТВО С ОГРАНИЧЕННОЙ ОТВЕТСТВЕННОСТЬЮ "СПЕЦИАЛИЗИРОВАННЫЙ ЗАСТРОЙЩИК "ГАЛС-СТАРОПЕТРОВСКИЙ" | E51: 63671758 | F51: 45277565000 | G51: 16 | H51: 12300 | I51: 774301001 | J51: 2025-01-31 | L51: 68.20.29 | M51: Аренда и управление собственным или арендованным прочим нежилым недвижимым имуществом | N51: 46.19,46.90,52.10.9,68.10.21,68.10.22,68.20.2,69.20.1,70.22,73.20.1,82.99 | O51: КИБИШЕВ МАКСИМ ВЯЧЕСЛАВОВИЧ | P51: 507601258762 | Q51: ГЕНЕРАЛЬНЫЙ ДИРЕКТОР | R51: 125130, Г.МОСКВА, ВН.ТЕР.Г. МУНИЦИПАЛЬНЫЙ ОКРУГ ВОЙКОВСКИЙ, ПРОЕЗД СТАРОПЕТРОВСКИЙ, Д. 11, К. 1, ПОМЕЩ. 1 | S51: +79852247504 | V51: 103492900 | W51: 277591000 | X51: 176505000 | Y51: 176426000 | Z51: 40438000 | AA51: 41716000 | AB51: 146081000 | AC51: 128826000 | AD51: 198830000 | AF51: 1 | AG51: ОСН
A52: 5167746180135 | B52: 7725335021 | C52: ООО "ЛЭНДМАРК ГРУП" | D52: ОБЩЕСТВО С ОГРАНИЧЕННОЙ ОТВЕТСТВЕННОСТЬЮ "ЛЭНДМАРК ГРУП" | E52: 4952513 | F52: 45296561000 | G52: 23 | H52: 12300 | I52: 772501001 | J52: 2016-10-07 | L52: 68.20 | M52: Аренда и управление собственным или арендованным недвижимым имуществом | N52: 64.20,64.99.11,64.99.12,64.99.3,64.99.4,66.19,68.10,68.31,68.32,77.29,77.33,77.39 | O52: МАРКОВ АРКАДИЙ ОЛЕГОВИЧ | P52: 502700448290 | Q52: ГЕНЕРАЛЬНЫЙ ДИРЕКТОР | R52: 115419, Г.МОСКВА, ПР-Д 5-Й ДОНСКОЙ, Д. 4, ПОМЕЩ. 1 КОМ. 4 | S52: +79851132368 | V52: 862116748 | W52: 127936000 | X52: 818262000 | Y52: 1000 | Z52: 290252000 | AA52: 354039000 | AB52: 322100000 | AC52: -12997000 | AD52: 321375000 | AF52: 12 | AG52: ОСН
A53: 1227700484076 | B53: 9717118570 | C53: ООО "МЕДСКАН ЛАБ" | D53: ОБЩЕСТВО С ОГРАНИЧЕННОЙ ОТВЕТСТВЕННОСТЬЮ "МЕДСКАН ЛАБ" | E53: 98385807 | F53: 45280552000 | G53: 16 | H53: 12300 | I53: 771701001 | J53: 2022-08-10 | L53: 64.20 | M53: Деятельность холдинговых компаний | N53: 70.22 | O53: АКЦИОНЕРНОЕ ОБЩЕСТВО "МЕДСКАН" | P53: 7736328675 | Q53: — | R53: 129626, Г.МОСКВА, ВН.ТЕР.Г. МУНИЦИПАЛЬНЫЙ ОКРУГ АЛЕКСЕЕВСКИЙ, ПР-КТ МИРА, Д. 102, К. 1, ПОМЕЩ. 3/7 | S53: +79035492065 | V53: 6382610417 | W53: 310779000 | X53: 0 | Y53: 0 | Z53: 93855000 | AA53: 1606000 | AB53: 166464000 | AC53: 306093000 | AD53: 165295000 | AF53: 0 | AG53: ОСН
A54: 1237700699257 | B54: 9725137376 | C54: ООО "РТС" | D54: ОБЩЕСТВО С ОГРАНИЧЕННОЙ ОТВЕТСТВЕННОСТЬЮ "РОСАТОМ ТЕХНОЛОГИИ СООРУЖЕНИЯ" | E54: 79839527 | F54: 45296559000 | G54: 16 | H54: 12300 | I54: 772501001 | J54: 2023-10-17 | L54: 70.10 | M54: Деятельность головных офисов | N54: 28.99,33.12,33.20,46.69,66.19.4,69.10,70.10,70.22,71.12,71.12.14,73.20.1,74.90.1,74.90.6 | O54: ВЕРГИЗАЕВ ИЛЬЯ АЛЕКСАНДРОВИЧ | P54: 772729379680 | Q54: ГЕНЕРАЛЬНЫЙ ДИРЕКТОР | R54: 115280, Г.МОСКВА, ВН.ТЕР.Г. МУНИЦИПАЛЬНЫЙ ОКРУГ ДАНИЛОВСКИЙ, УЛ ЛЕНИНСКАЯ СЛОБОДА, Д. 26, ПОМЕЩ. 4Н/1 | S54: +74952800014,+79857276675 | U54: dvabelova@roatom.ru,dvabelova@rosatom.ru,vskurakina@rosatom.ru,rkip@rosatom.ru,oamusaelyan@rosatom.ru,salberezhnoy@rosatom.ru | V54: 250000000 | W54: 273984000 | X54: 0 | Y54: 6090000 | Z54: 200791000 | AA54: 58602000 | AB54: -993972000 | AC54: -885920000 | AD54: -1004173000 | AF54: 113 | AG54: ОСН
A55: 1227700616626 | B55: 9723169975 | C55: ООО "ПРОМСТРОЙ" | D55: ОБЩЕСТВО С ОГРАНИЧЕННОЙ ОТВЕТСТВЕННОСТЬЮ "ПРОМЫШЛЕННОЕ СТРОИТЕЛЬСТВО" | E55: 70374475 | F55: 45290582000 | G55: 16 | H55: 12300 | I55: 772301001 | J55: 2022-09-28 | L55: 71.12.2 | M55: Деятельность заказчика-застройщика, генерального подрядчика | N55: 41.10,41.20,42.22,42.99,43.11,43.12,43.21,43.22,43.29,43.31,43.32,43.33,43.34,43.39,62.02,63.11,64.99,66.19,68.10,68.20,69.10,70.22,71.12.1,71.12.2,82.99 | O55: СУЛТАНОВ ВЛАДИСЛАВ НАЗИПОВИЧ | P55: 666301898376 | Q55: ГЕНЕРАЛЬНЫЙ ДИРЕКТОР | R55: 109316, Г.МОСКВА, ВН.ТЕР.Г. МУНИЦИПАЛЬНЫЙ ОКРУГ ПЕЧАТНИКИ, ПР-КТ ВОЛГОГРАДСКИЙ, Д. 42, К. 5, КОМ. 9 | S55: +74952801480,+79856464428 | U55: info@mos-promstroy.ru,arutyunyanas@mos-promstroy.ru | V55: 25283577400 | W55: 4137635000 | X55: 4419707000 | Y55: 20312000 | Z55: 50081711000 | AA55: 53556544000 | AB55: 1121165000 | AC55: 268314000 | AD55: 1510408000 | AF55: 133 | AG55: ОСН
A56: 1077746296550 | B56: 7717580421 | C56: АО "МПС-ГРАНД" | D56: АКЦИОНЕРНОЕ ОБЩЕСТВО "МПС-ГРАНД" | E56: 99058068 | F56: 45286570000 | G56: 16 | H56: 12267 | I56: 770201001 | J56: 2007-02-06 | L56: 68.20.1 | M56: Аренда и управление собственным или арендованным жилым недвижимым имуществом | N56: 46.39,55.10,56.10,56.21,56.30,68.10,68.20,68.31,68.32,70.22,79.11,79.12,79.90,82.30 | O56: ОБЩЕСТВО С ОГРАНИЧЕННОЙ ОТВЕТСТВЕННОСТЬЮ "САФМАР ПЛАЗА" | P56: 9710014685 | Q56: — | R56: 129272, Г.МОСКВА, УЛ. СУЩЁВСКИЙ ВАЛ, Д. 74, ЭТ 21 ПОМ I КОМ 1 | S56: +74956505145,+74956990379 | V56: 5308900000 | W56: 377661000 | X56: 73816000 | Y56: 0 | Z56: 11030000 | AA56: 3001023000 | AB56: 231764000 | AC56: 301247000 | AD56: 308933000 | AF56: 1 | AG56: ОСН
A57: 1077746381624 | B57: 7717582274 | C57: АО "МПС-ФОРЕСТ" | D57: АКЦИОНЕРНОЕ ОБЩЕСТВО "МПС-ФОРЕСТ" | E57: 99572859 | F57: 45286570000 | G57: 16 | H57: 12267 | I57: 770201001 | J57: 2007-02-22 | L57: 68.20 | M57: Аренда и управление собственным или арендованным недвижимым имуществом | N57: 46.39,55.10,56.10,56.21,56.30,68.10,68.31,68.32,70.22,79.11,79.12,79.90,82.30 | O57: ОБЩЕСТВО С ОГРАНИЧЕННОЙ ОТВЕТСТВЕННОСТЬЮ "САФМАР ПЛАЗА" | P57: 9710014685 | Q57: — | R57: 129272, Г.МОСКВА, УЛ. СУЩЁВСКИЙ ВАЛ, Д. 74, ЭТ 21 ПОМ I КОМ 1 | S57: +74956990379 | V57: 4307740000 | W57: 104714000 | X57: 57971000 | Y57: 0 | Z57: 1340000 | AA57: 1242409000 | AB57: 121315000 | AC57: 69733000 | AD57: 162421000 | AF57: 0 | AG57: ОСН
A58: 1077759685717 | B58: 7726575587 | C58: АО "ОСПОС" | D58: АКЦИОНЕРНОЕ ОБЩЕСТВО "ОПЕРАТОР СИСТЕМ ПЕНСИОННОГО ОБЕСПЕЧЕНИЯ И СТРАХОВАНИЯ" | E58: 82537942 | F58: 45296593000 | G58: 16 | H58: 12267 | I58: 772601001 | J58: 2007-09-03 | L58: 66.29.9 | M58: Деятельность вспомогательная прочая в сфере страхования, кроме обязательного социального страхования | N58: 62.01,62.02,62.09,63.11.1,63.99.1,66.2,70.22,73.20.1,82.99 | O58: МОЧАЛОВ ЕВГЕНИЙ ВЛАДИМИРОВИЧ | P58: 500113143395 | Q58: ГЕНЕРАЛЬНЫЙ ДИРЕКТОР | R58: 117556, Г.МОСКВА, Ш. ВАРШАВСКОЕ, Д.95, К.1 | S58: +74995800080,+74957820894 | T58: ospos.ru,,ospos.ru | V58: 150000000 | W58: 483101000 | X58: 8554000 | Y58: 0 | Z58: 35893000 | AA58: 70740000 | AB58: 14102000 | AC58: -63702000 | AD58: 26991000 | AF58: 107 | AG58: ОСН
A59: 1077760250974 | B59: 7708648850 | C59: ООО "ИНВЕСТКОНСАЛТИНГ" | D59: ОБЩЕСТВО С ОГРАНИЧЕННОЙ ОТВЕТСТВЕННОСТЬЮ "ИНВЕСТКОНСАЛТИНГ" | E59: 82563129 | F59: 45286560000 | G59: 16 | H59: 12300 | I59: 770501001 | J59: 2007-09-18 | L59: 50.20.29 | M59: Перевозка прочих грузов морскими судами каботажного плавания | N59: 50.10,50.20,50.20.3,52.22.1 | O59: ЧВЕРТКО НИКОЛАЙ НИКОЛАЕВИЧ | P59: 254002327775 | Q59: ГЕНЕРАЛЬНЫЙ ДИРЕКТОР | R59: 115184, Г.МОСКВА, ВН.ТЕР.Г. МУНИЦИПАЛЬНЫЙ ОКРУГ ЗАМОСКВОРЕЧЬЕ, УЛ НОВОКУЗНЕЦКАЯ, Д. 7/11, СТР. 1, ЭТАЖ 3, КАБ. 317 | S59: +74957391243,+74957391127 | V59: 145010000 | W59: 595618000 | X59: 716031000 | Y59: 47999000 | Z59: 172119000 | AA59: 151663000 | AB59: -1153000 | AC59: 107252000 | AD59: 7560000 | AF59: 113 | AG59: ОСН
A60: 1077764075399 | B60: 7721607323 | C60: АО "ТРАСТИНВЕСТНЕДВИЖИМОСТЬ" | D60: АКЦИОНЕРНОЕ ОБЩЕСТВО "ТРАСТИНВЕСТНЕДВИЖИМОСТЬ" | E60: 84153950 | F60: 45290586000 | G60: 16 | H60: 12267 | I60: 772101001 | J60: 2007-12-19 | L60: 68.10.22 | M60: Покупка и продажа собственных нежилых зданий и помещений | N60: 14.12,46.11.35,46.12.31,46.15,46.42.14,46.49,64.20,64.92.2,64.92.3,64.99.3,66.1,66.12.1,66.19,66.19.4,66.19.5,68.10.12,68.10.23,68.20.2,68.31.1,68.31.2,68.31.3,68.31.4,68.31.52,68.32,68.32.1,68.32.2,69.10,69.20,70.10.1,70.10.2,70.22,73.1,73.20 | O60: КОЗЛОВ НИКОЛАЙ ГЕННАДЬЕВИЧ | P60: 772157795465 | Q60: ГЕНЕРАЛЬНЫЙ ДИРЕКТОР | R60: 109518, Г.МОСКВА, ПР-Д ГРАЙВОРОНОВСКИЙ 2-Й, Д.34А, СТР.1 | S60: +74954247771 | V60: 416240800 | W60: 205834000 | X60: 1080619000 | Y60: 564000 | Z60: 35635000 | AA60: 25189000 | AB60: -3949000 | AC60: 2555000 | AD60: -4590000 | AE60: Малое предприятие | AF60: 69 | AG60: ОСН
A61: 1077762607450 | B61: 7703649183 | C61: ОАО "МОСКОВСКАЯ ГАЗЕТНАЯ ТИПОГРАФИЯ" | D61: ОТКРЫТОЕ АКЦИОНЕРНОЕ ОБЩЕСТВО "МОСКОВСКАЯ ГАЗЕТНАЯ ТИПОГРАФИЯ" | E61: 84011894 | F61: 45286575000 | G61: 42 | H61: 12267 | I61: 770301001 | J61: 2007-11-19 | L61: 18.12.9 | M61: Прочие виды полиграфической деятельности, не включенные в другие группировки | N61: 18.11,46.90,68.20.29,81.10,18.11,18.12,18.13,18.14,52.29,53.20.3,58.11.1,58.11.3,58.14,58.19,59.20,59.20.3,61.1,68.20.1 | O61: ВЕРХНЯЦКАЯ ОЛЬГА АНАТОЛЬЕВНА | P61: 500401846919 | Q61: ГЕНЕРАЛЬНЫЙ ДИРЕКТОР | R61: 123022, Г.МОСКВА, УЛ. 1905 ГОДА, Д.7, СТР.1 | S61: +74992598110,+74995581508,+74951358466,+74957814737,+74992560424,+74992561528,+74992598374,+79255060641,+79852227542,+74992589110,+74992561527,+74992598111,+74952598110,+74952594700,+74992595354,+74992594700,+74992596013 | T61: www.disclosure.ru/issuer/7703649183/,,www.mosgt.ru | U61: info@mosgt.ru,verhn@mosgt.ru,info@mosgr.ru,vantsova.ev@mosgt.ru,boss@orion-pr.ru,pochta@poichta.ru,yakovlev@mosgt.ru,info@mosgt.ru.ru,maypasha@rambler.ru,lazareva@mosgt.ru,spantyukhova@mosgt.ru,info@mosgt.ru,,purchase@mosgt.ru,sender@mosgt.ru,null@null.ru | V61: 1404846275 | W61: 812407000 | X61: 650832000 | Y61: 177438000 | Z61: 32609000 | AA61: 72901000 | AB61: 110070000 | AC61: -18917000 | AD61: 147076000 | AF61: 222 | AG61: ОСН
A62: 1067746734318 | B62: 7701666049 | C62: ООО "ББ МЕДИА" | D62: ОБЩЕСТВО С ОГРАНИЧЕННОЙ ОТВЕТСТВЕННОСТЬЮ "ББ МЕДИА" | E62: 96024519 | F62: 45286555000 | G62: 16 | H62: 12300 | I62: 770101001 | J62: 2006-06-23 | L62: 46.19 | M62: Деятельность агентов по оптовой торговле универсальным ассортиментом товаров | N62: 46.73.6,45.11,45.19,46.12,46.13,46.14,46.63,46.69,46.72,46.73,46.74,46.75,46.90,49.10,49.20,52.10,52.21,52.24,52.29,64.92,77.11,77.12,77.32 | O62: ШИЯНОВ ЕВГЕНИЙ НИКОЛАЕВИЧ | P62: 524701756783 | Q62: ПРЕЗИДЕНТ | R62: 101000, Г.МОСКВА, УЛ. МЯСНИЦКАЯ, Д. 46, СТР. 7, ПОМ/КОМН I/18 | S62: +74957802080,+74952235631,+74957892542 | U62: info@etk.com,s.levandovskii@kstg.ru,s.levandovskii@kstg.ru,,e.shiyanov@kstg.ru | V62: 15010000100 | W62: 108449000 | X62: 2000 | Y62: 49719289000 | Z62: 5189071000 | AA62: 22338277000 | AB62: 13546000 | AC62: 20347000 | AD62: 18062000 | AF62: 3 | AG62: ОСН
A63: 1117746349324 | B63: 7701917479 | C63: АО "ЭКОПЛАСТ" | D63: АКЦИОНЕРНОЕ ОБЩЕСТВО "ЭКОПЛАСТ" | E63: 91530502 | F63: 45286555000 | G63: 16 | H63: 12267 | I63: 770101001 | J63: 2011-05-03 | L63: 64.99.11 | M63: Вложения в ценные бумаги | N63: 64.20,64.92.2,64.99,64.99.3,66.19.4,70.10.1,70.10.2,70.22,73.20.1 | O63: ГЛАДКОВ АНДРЕЙ ЮВИНАЛИЕВИЧ | P63: 773604239545 | Q63: ГЕНЕРАЛЬНЫЙ ДИРЕКТОР | R63: 105005, Г.МОСКВА, ВН.ТЕР.Г. МУНИЦИПАЛЬНЫЙ ОКРУГ БАСМАННЫЙ, ПЕР АПТЕКАРСКИЙ, Д. 4, СТР. 2 | S63: +74957753624 | V63: 316625000 | W63: 568891000 | X63: 375000 | Y63: 11765000 | Z63: 333292000 | AA63: 166000 | AB63: 253000 | AC63: -7514000 | AD63: 611000 | AE63: Малое предприятие | AF63: 3 | AG63: ОСН
A64: 1025006033040 | B64: 5046062009 | C64: ООО "ХАУСХОЛД ЛОДЖИК" | D64: ОБЩЕСТВО С ОГРАНИЧЕННОЙ ОТВЕТСТВЕННОСТЬЮ "ХАУСХОЛД ЛОДЖИК" | E64: 56844460 | F64: 46460000126 | G64: 16 | H64: 12300 | I64: 507401001 | J64: 2001-06-09 | L64: 68.20 | M64: Аренда и управление собственным или арендованным недвижимым имуществом | N64: 41.20,52.10,52.10.9,52.24,52.29,68.10,70.22 | O64: КУЛЬДЕНОВ ДЕНИС СЕРИКОВИЧ | P64: 561506906844 | Q64: ГЕНЕРАЛЬНЫЙ ДИРЕКТОР | R64: 142108, МОСКОВСКАЯ ОБЛАСТЬ, Г ПОДОЛЬСК, П ЖЕЛЕЗНОДОРОЖНЫЙ, УЛ БОЛЬШАЯ СЕРПУХОВСКАЯ, Д. 230, СТР. 1 | S64: +79104261439,+79168000386,+79154795160,+74952257800,+79852155000,+74952211847 | T64: hhlogic.ru | V64: 110594087 | W64: 324395000 | X64: 890768000 | Y64: 456000 | Z64: 247145000 | AA64: 91389000 | AB64: 86520000 | AC64: 107236000 | AD64: 115364000 | AE64: Малое предприятие | AF64: 14 | AG64: ОСН
A65: 1025007269583 | B65: 5056000964 | C65: АО "ЦАБ" | D65: АКЦИОНЕРНОЕ ОБЩЕСТВО "ЦАБ" | E65: 113052 | F65: 46411000000 | G65: 16 | H65: 12267 | I65: 502701001 | J65: 1999-03-10 | L65: 68.20.2 | M65: Аренда и управление собственным или арендованным нежилым недвижимым имуществом | N65: 43.22,46.12.22,46.47.1,46.49.49,46.49.5,46.69.5,46.69.9,46.73,46.90,49.31,49.4,52.10.9,52.24,52.29,68.31.22,68.31.32,68.31.42,77.39.29 | O65: КОЗЛОВ КОНСТАНТИН ПАВЛОВИЧ | P65: 860222999577 | Q65: ГЕНЕРАЛЬНЫЙ ДИРЕКТОР | R65: 140090, МОСКОВСКАЯ ОБЛАСТЬ, Г. ДЗЕРЖИНСКИЙ, Г ЛЮБЕРЦЫ, УЛ ЭНЕРГЕТИКОВ, Д. 1 | S65: +74955512763,+74955512777,+74955512790,+74955513100,+74965512777,+74957413303,+74965512763,+70955512763 | V65: 110011000 | W65: 266912000 | X65: 85020000 | Y65: 1008000 | Z65: 45867000 | AA65: 13655000 | AB65: 11036000 | AC65: 27150000 | AD65: 17803000 | AE65: Малое предприятие | AF65: 11 | AG65: ОСН
A66: 1047796071344 | B66: 7727504170 | C66: ООО "ТРАНСПОРТНАЯ ГРУППА ФЕСКО" | D66: ОБЩЕСТВО С ОГРАНИЧЕННОЙ ОТВЕТСТВЕННОСТЬЮ "УПРАВЛЯЮЩАЯ КОМПАНИЯ "ТРАНСПОРТНАЯ ГРУППА ФЕСКО" | E66: 72042263 | F66: 45286560000 | G66: 16 | H66: 12300 | I66: 770501001 | J66: 2004-02-09 | L66: 70.22 | M66: Консультирование по вопросам коммерческой деятельности и управления | N66: 50.20,50.40.2,53.20.3,68.1,69.10,69.20,70.10.1,70.10.2,70.22 | O66: РАДЧЕНКО ИВАН АЛЕКСАНДРОВИЧ ПАНЬКОВ ДМИТРИЙ АЛЕКСАНДРОВИЧ | P66: 253714027106 667206013402 | Q66: УПРАВЛЯЮЩИЙ ДИРЕКТОР ВМТП ГЕНЕРАЛЬНЫЙ ДИРЕКТОР | R66: 115184, Г.МОСКВА, ВН.ТЕР.Г. МУНИЦИПАЛЬНЫЙ ОКРУГ ЗАМОСКВОРЕЧЬЕ, УЛ НОВОКУЗНЕЦКАЯ, Д. 7/11, СТР. 1, ЭТАЖ 3, КАБ. 334 | S66: +74955408000,+74959268100 | V66: 480100000 | W66: 82911000 | X66: 755000 | Y66: 0 | Z66: 645251000 | AA66: 99370000 | AB66: -11807000 | AC66: -8041000 | AD66: -17825000 | AF66: 1 | AG66: ОСН
A67: 1095019001220 | B67: 5019021966 | C67: АО "НИЦ АЭС" | D67: АКЦИОНЕРНОЕ ОБЩЕСТВО "НАУЧНО-ИСПЫТАТЕЛЬНЫЙ ЦЕНТР ОБОРУДОВАНИЯ АТОМНЫХ ЭЛЕКТРОСТАНЦИЙ" | E67: 11749497 | F67: 46435000000 | G67: 61 | H67: 12267 | I67: 501901001 | J67: 2009-11-26 | L67: 71.20.9 | M67: Деятельность по техническому контролю, испытаниям и анализу прочая | N67: 25.61,25.62,26.5,46.9,71.20,72.19 | O67: ШОРСТОВ ДЕНИС АНАТОЛЬЕВИЧ | P67: 501903344103 | Q67: ДИРЕКТОР | R67: 142902, МОСКОВСКАЯ ОБЛАСТЬ, Г КАШИРА, УЛ СОВЕТСКИЙ ПРОСПЕКТ, Д. 2А | S67: +74966963253,+74966963304,+74966964550,+74966963207,+79030113938,+74966921396,+74956921818,+74966922988,+79851328750,+74966921818,+74966964512,+74956964550 | T67: niaes.ru | U67: omts@niaes.ru,info@niaes.ru,peo@niaes.ru,vera.vikulova@niaes.ru,rusinova_ea@niaes.ru,atom_kia@mail.ru,,atom_kia@mail.ru,aivanova_k@mail.ru | V67: 187022000 | W67: 165517000 | X67: 179727000 | Y67: 1091000 | Z67: 32204000 | AA67: 26511000 | AB67: 22001000 | AC67: 3870000 | AD67: 30376000 | AF67: 58 | AG67: ОСН
A68: 1087746628903 | B68: 7708671295 | C68: ООО "АРМЗ СЕРВИС" | D68: ОБЩЕСТВО С ОГРАНИЧЕННОЙ ОТВЕТСТВЕННОСТЬЮ "АРМЗ СЕРВИС" | E68: 86469806 | F68: 45286580000 | G68: 16 | H68: 12300 | I68: 770901001 | J68: 2008-05-13 | L68: 46.19 | M68: Деятельность агентов по оптовой торговле универсальным ассортиментом товаров | N68: 42.99,45.1,45.20,45.3,46.1,46.42,46.71,46.72,46.72.12,46.73.1,46.73.2,46.75,46.75.2,46.90,49.4,52.10,68.32,70.22,72.19,72.19.3,72.19.9,73.20 | O68: САВЧЕНКО ЭДУАРД ИВАНОВИЧ | P68: 770474483248 | Q68: ГЕНЕРАЛЬНЫЙ ДИРЕКТОР | R68: 109004, Г.МОСКВА, ПЕР. БОЛЬШОЙ ДРОВЯНОЙ, Д. 12, СТР. 3 | S68: +74995006026,+74995006027,+79057083219,+74999516058,+74999516057,+74999516078,+79516057223,+74955006026,+74996006026,+74959516057,+74952233078,+74952233076,+74959516058,+74999515057,+78499951657 | T68: esk-armz.ru | U68: elnivasilyeva@armz-service.ru,uslugi@armz-service.ru,tvivityuk@armz-service.ru,tovar@armz-service.ru,galyashnov@armz-service.ru,sedpotemkin@armz-service.ru,info@armz-service.ru,lelevkov@armz-service.ru,sskharlamov@armz-service.ru,idmlis@armz-service.ru,evymedvedeva@armz-service.ru,yssiplova@armz-service.ru,esizikova@armz-service.ru,aakapustkin@armz-service.ru,alpazaytsev@armz-service.ru,siplova.y.s@armz-service.ru,anbpetrazhitskaya@armz-service.ru,tvisimakova@armz-service.ru,ivaaleksandrov@armz-service.ru,romanova.t.v@armz-service.ru,sizikova.e.n@armz-service.ru,potemkin.s.d@armz-service.ru,zaytsev.a.p@armz-service.ru,info@armz.ru,nesvetaeva.k.y@armz-service.ru,shkabrova.e.a@armz-service.ru,nosova.t.v@armz-service.ru,tovari@armz-service.ru,mail@mail.ru,var@armz-service.ru,bogdanova.u.o@armz-service.ru,zakupki@armz-service.ru | V68: 176000000 | W68: 496487000 | X68: 71178000 | Y68: 375000 | Z68: 364283000 | AA68: 281932000 | AB68: -962000 | AC68: -14996000 | AD68: -436000 | AF68: 111 | AG68: ОСН
A69: 1057748725352 | B69: 7724558466 | C69: АО "МЗП" | D69: АКЦИОНЕРНОЕ ОБЩЕСТВО "МОСКОВСКИЙ ЗАВОД ПОЛИМЕТАЛЛОВ" | E69: 7622472 | F69: 45296569000 | G69: 16 | H69: 12267 | I69: 772401001 | J69: 2005-10-21 | L69: 68.20.21 | M69: Аренда и управление собственным или арендованным торговым объектом недвижимого имущества | N69: 25.30.2,25.40,25.61,25.62,25.99.29,26.30,26.51.7,28.29.12,35.11.3,35.30.2,35.30.3,35.30.4,68.20.2,68.32.2,72.19 | O69: БИРЮКОВ ВИКТОР ВИКТОРОВИЧ | P69: 220901290279 | Q69: ГЕНЕРАЛЬНЫЙ ДИРЕКТОР | R69: 115409, Г.МОСКВА, Ш. КАШИРСКОЕ, Д.49 | S69: +74993247234,+74957428298,+74959955515,+79259589602,+74959955513,+74953247234,+70953247234,+70957428298 | T69: www.mzp.ru | U69: mzp@mzp.ru,morozova@mzp.ru | V69: 1229926000 | W69: 588946000 | X69: 732836000 | Y69: 3744000 | Z69: 146540000 | AA69: 114756000 | AB69: 179070000 | AC69: 19275000 | AD69: 243149000 | AG69: ОСН
A70: 1125031002634 | B70: 5031101696 | C70: АО "ДЭП №19" | D70: АКЦИОНЕРНОЕ ОБЩЕСТВО "ДОРОЖНОЕ ЭКСПЛУАТАЦИОННОЕ ПРЕДПРИЯТИЕ №19" | E70: 3421972 | F70: 46451000000 | G70: 12 | H70: 12267 | I70: 503101001 | J70: 2012-06-29 | L70: 52.21.22 | M70: Деятельность по эксплуатации автомобильных дорог и автомагистралей | O70: ПОПОВ ОЛЕГ АЛЕКСАНДРОВИЧ | P70: 503211067701 | Q70: ГЕНЕРАЛЬНЫЙ ДИРЕКТОР | R70: 142410, МОСКОВСКАЯ ОБЛАСТЬ, Г. НОГИНСК, Ш. ЭЛЕКТРОСТАЛЬСКОЕ, Д.14 | S70: +74965145287,+74952545287,+74955114388,+74965195353,+74965195154,+74965142821,+74965114388,+74965195153,+74952512732 | T70: disclosure.ru/issuer/5031101696/ | U70: dep19n@,mail.ru,dep19n@mail.ru | V70: 103813000 | W70: 281930000 | X70: 120925000 | Y70: 49061000 | Z70: 40972000 | AA70: 18999000 | AB70: 3049000 | AC70: -3728000 | AD70: 4065000 | AE70: Среднее предприятие | AF70: 108 | AG70: ОСН
A71: 1057746552115 | B71: 7743555005 | C71: АО "СПЕЦИАЛИЗИРОВАННЫЙ ЗАСТРОЙЩИК "ИЖОРСКАЯ" | D71: АКЦИОНЕРНОЕ ОБЩЕСТВО "СПЕЦИАЛИЗИРОВАННЫЙ ЗАСТРОЙЩИК "ИЖОРСКАЯ" | E71: 4005951 | F71: 45277577000 | G71: 16 | H71: 12267 | I71: 771301001 | J71: 2005-04-01 | L71: 68.20.29 | M71: Аренда и управление собственным или арендованным прочим нежилым недвижимым имуществом | N71: 68.10.21,41.20,49.4,52.10.9,52.29,68.10,68.20.2,71.12.2 | O71: ШЕСТАКОВА ЕКАТЕРИНА АЛЕКСАНДРОВНА | P71: 502912958550 | Q71: ГЕНЕРАЛЬНЫЙ ДИРЕКТОР | R71: 125599, Г.МОСКВА, ВН.ТЕР.Г. МУНИЦИПАЛЬНЫЙ ОКРУГ ЗАПАДНОЕ ДЕГУНИНО, УЛ ИЖОРСКАЯ, Д. 8, СТР. 2 | S71: +70954860308,+74954860310,+74954861584,+74954861586,+74954861587,+74954860308,+74954860788,+74954867229,+79055474507,+74954861672 | T71: www.mostzk.ru | U71: mtzk@mostzk.ru,mtzk@bl.ru,mtzk@bk.ru,,mtzk@bk.eu,mtzk@bk.ri,mtzk@bk.ru | V71: 190831000 | W71: 63013000 | X71: 166144000 | Y71: 28696944000 | Z71: 1136061000 | AA71: 13844170000 | AB71: 306344000 | AC71: -412991000 | AD71: 414525000 | AF71: 9 | AG71: ОСН
A72: 1057747813837 | B72: 7705680245 | C72: ООО ПКО "ССК" | D72: ОБЩЕСТВО С ОГРАНИЧЕННОЙ ОТВЕТСТВЕННОСТЬЮ ПРОФЕССИОНАЛЬНАЯ КОЛЛЕКТОРСКАЯ ОРГАНИЗАЦИЯ "СТОЛИЧНАЯ СЕРВИСНАЯ КОМПАНИЯ" | E72: 78499986 | F72: 45268560000 | G72: 34 | H72: 12300 | I72: 773101001 | J72: 2005-08-15 | L72: 82.91 | M72: Деятельность агентств по сбору платежей и бюро кредитной информации | N72: 66.19,69.10,70.22 | O72: МОХНАЧЕВ ДМИТРИЙ ВЯЧЕСЛАВОВИЧ | P72: 332800597605 | Q72: ГЕНЕРАЛЬНЫЙ ДИРЕКТОР | R72: 121609, Г.МОСКВА, ВН.ТЕР.Г. МУНИЦИПАЛЬНЫЙ ОКРУГ КРЫЛАТСКОЕ, Б-Р ОСЕННИЙ, Д. 23 | S72: +74957772516,+79261773957 | T72: capitalca.ru,csc.msk.ru | U72: capitalca@svea-cca.ru | V72: 140942639 | W72: 594873000 | X72: 4755000 | Y72: 18000 | Z72: 162163000 | AA72: 86733000 | AB72: 431955000 | AC72: 448791000 | AD72: 587961000 | AG72: ОСН
A73: 1057748830644 | B73: 7727557887 | C73: ООО "ГПБ-ЭНЕРГОЭФФЕКТ" | D73: ОБЩЕСТВО С ОГРАНИЧЕННОЙ ОТВЕТСТВЕННОСТЬЮ "ГПБ-ЭНЕРГОЭФФЕКТ" | E73: 79442155 | F73: 45286596000 | G73: 16 | H73: 12300 | I73: 770601001 | J73: 2005-10-28 | L73: 71.12 | M73: Деятельность в области инженерных изысканий, инженерно-технического проектирования, управления проектами строительства, выполнения строительного контроля и авторского надзора, предоставление технических консультаций в этих областях | N73: 33.11,33.12,33.14,33.20,35.11,35.12,41.10,41.20,42.21,42.22,42.99,43.11,43.12,43.21,43.22,43.29,43.99,52.10,52.29,62.01,62.02,63.11.1,64.99,68.20,70.22,71.20,77.12,77.32,77.39,82.99 | O73: Доступ к сведениям ограничен | P73: — | Q73: — | R73: 119049, Г.МОСКВА, УЛ. БОЛЬШАЯ ЯКИМАНКА, Д. 39, КОМ. 17 | S73: +74956607141,+74956518989,+74957555951,+74952873771,+70959804115 | U73: gpb@mail.ru,79442155@mail.ru,sergey.barsukov@gpb-ee.ru,null@null.ru,info@gpb-ee.ru | V73: 762735740 | W73: 1242968000 | X73: 2315175000 | Y73: 4000 | Z73: 274975000 | AA73: 140156000 | AB73: 173226000 | AC73: 500355000 | AD73: 231070000 | AF73: 16 | AG73: ОСН
A74: 1057749422994 | B74: 7714629291 | C74: ООО "ПРОФ ИНВЕСТ" | D74: ОБЩЕСТВО С ОГРАНИЧЕННОЙ ОТВЕТСТВЕННОСТЬЮ "ПРОФ ИНВЕСТ" | E74: 79417981 | F74: 45277592000 | G74: 24 | H74: 12300 | I74: 771301001 | J74: 2005-12-07 | L74: 68.20 | M74: Аренда и управление собственным или арендованным недвижимым имуществом | N74: 64.91,64.92,64.99,68.10,68.31,73.11,73.20.1,82.99 | O74: ШЕЛАБАЕВ ВЯЧЕСЛАВ АЛЕКСАНДРОВИЧ | P74: 503210468348 | Q74: ГЕНЕРАЛЬНЫЙ ДИРЕКТОР | R74: 127422, Г.МОСКВА, УЛ ТИМИРЯЗЕВСКАЯ, Д. 1 | S74: +74957868760,+74957881716 | V74: 156181669 | W74: 286234000 | X74: 7496000 | Y74: 19953000 | Z74: 1370000 | AA74: 99426000 | AB74: 115008000 | AC74: 150473000 | AD74: 153515000 | AE74: Малое предприятие | AF74: 22 | AG74: ОСН
A75: 1115024004413 | B75: 5024121620 | C75: ООО "ЭТАЛОН-ИНВЕСТ" | D75: ОБЩЕСТВО С ОГРАНИЧЕННОЙ ОТВЕТСТВЕННОСТЬЮ "ЭТАЛОН-ИНВЕСТ" | E75: 92670228 | F75: 46439000000 | G75: 16 | H75: 12300 | I75: 502401001 | J75: 2011-06-23 | L75: 41.2 | M75: Строительство жилых и нежилых зданий | N75: 43.12,43.2,43.3,43.99,64.9,66.1,68.1,68.2,68.3,69,71.1,71.12.5,71.12.6,73.1,74.20,74.30,82.92 | O75: ОБЩЕСТВО С ОГРАНИЧЕННОЙ ОТВЕТСТВЕННОСТЬЮ "ГРУППА КОМПАНИЙ "ЭТАЛОН" | P75: 7814486174 | Q75: — | R75: 143409, МОСКОВСКАЯ ОБЛАСТЬ, Г. КРАСНОГОРСК, УЛ. СВЕТЛАЯ, Д. 3А, СТР. 2, ПОМЕЩ. 9 | S75: +74952230453,+74956859352,+74952230445,+74952230450,+74953788888 | V75: 186100000 | W75: 181246000 | X75: 24119000 | Y75: 5000000 | Z75: 107266000 | AA75: 2596000 | AB75: -69359000 | AC75: 6126000 | AD75: -117384000 | AF75: 71 | AG75: ОСН
A76: 1037704002588 | B76: 7704251349 | C76: ЗАО "ЛЕТНЫЕ ПРОВЕРКИ И СИСТЕМЫ" | D76: ЗАКРЫТОЕ АКЦИОНЕРНОЕ ОБЩЕСТВО "ЛЕТНЫЕ ПРОВЕРКИ И СИСТЕМЫ" | E76: 59847542 | F76: 45286552000 | G76: 12 | H76: 12267 | I76: 770401001 | J76: 2003-01-23 | L76: 52.23 | M76: Деятельность вспомогательная, связанная с воздушным и космическим транспортом | N76: 52.23.1,52.23.13,74.20 | O76: ЛЫНКИНА НАТАЛЬЯ ВЛАДИМИРОВНА | P76: 500405305420 | Q76: ГЕНЕРАЛЬНЫЙ ДИРЕКТОР | R76: 121069, Г.МОСКВА, Б-Р НОВИНСКИЙ, Д. 18СТР1, ПОМЕЩ. VIII | S76: +74956124384,+79162106259,+74752566982,+79165013073,+74956624607,+70957862323,+74752567196,+74957862323 | U76: nvl@lps-aero.com,info@lps-aero.com,info@lsp-aero.com,tslps@mail.ru,info@ps-aero.com,info@lhs-aero.com. | V76: 203130000 | W76: 691332000 | X76: 273769000 | Y76: 46100000 | Z76: 41100000 | AA76: 81929000 | AB76: -28385000 | AC76: -91088000 | AD76: -37401000 | AF76: 114 | AG76: ОСН
A77: 1037714012907 | B77: 7714299413 | C77: ООО "ДЕЛЬТА КОНСТРАКШН" | D77: ОБЩЕСТВО С ОГРАНИЧЕННОЙ ОТВЕТСТВЕННОСТЬЮ "ДЕЛЬТА КОНСТРАКШН" | E77: 59895601 | F77: 45290586000 | G77: 16 | H77: 12300 | I77: 772101001 | J77: 2003-02-14 | L77: 81.10 | M77: Деятельность по комплексному обслуживанию помещений | N77: 77.12,33.13,41.20,43.12.3,43.39,43.99.5,43.99.7,46.13,52.10.21,52.10.22,68.20,68.20.1,68.20.2,71.11,71.11.1,71.12,77.11,77.12,77.32,77.39,77.39.27,81.10,81.21,81.22,81.29,90.0,95.29 | O77: ДЕМИРАЛП ДЖЕЙХУН | P77: 772160102953 | Q77: ГЕНЕРАЛЬНЫЙ ДИРЕКТОР | R77: 109428, Г.МОСКВА, ПР-КТ РЯЗАНСКИЙ, Д. 8А, СТР. 1, ПОМЕЩ. VII, К.47 (ВН500) Т/Э | S77: +74995009182,+74952320767,+79161055537,+74992320767,+74995009128,+70953616201 | T77: www.deltaconstruction.ru | U77: info@deltaconstruction.ru | V77: 109010000 | W77: 172356000 | X77: 875632000 | Y77: 2196000 | Z77: 38954000 | AA77: 13729000 | AB77: 89258000 | AC77: 54436000 | AD77: 112972000 | AE77: Среднее предприятие | AF77: 89 | AG77: ОСН
A78: 1037700134823 | B78: 7704180070 | C78: АО "ОБНОВЛЕНИЕ АРБАТА" | D78: АКЦИОНЕРНОЕ ОБЩЕСТВО "ОБНОВЛЕНИЕ АРБАТА" | E78: 18310445 | F78: 45286552000 | G78: 16 | H78: 12267 | I78: 770401001 | J78: 1998-01-30 | L78: 68.20 | M78: Аренда и управление собственным или арендованным недвижимым имуществом | N78: 33.12,33.14,33.20,41.20,42.99,43.12,43.2,43.21,43.22,43.29,43.3,43.31,43.32,43.33,43.34,43.39,43.91,43.99,55.10,55.20,64.99,64.99.3,68.10,68.10.22,68.20.2,68.32.2,71.12 | O78: МИКУШКО АЛЕКСЕЙ ЕВГЕНЬЕВИЧ | P78: 772728497297 | Q78: ГЕНЕРАЛЬНЫЙ ДИРЕКТОР | R78: 119019, Г.МОСКВА, УЛ. НОВЫЙ АРБАТ, Д.21 | S78: +74953630979,+74953630990,+74956959425,+74956850562,+71482282247,+71482914260,+71489344000,+74953630956,+74953690979 | T78: newarbat.ru,,www.e-disclosure.ru/portal/company.aspx?id=25407,newarbat.ru | U78: null@null.ru,,arenda@newarbat.ru,areda@newarbat.ru,secretary@newarbat.ru,olegvl1@mail.ru,olegvl1@mail.ru,,urist@newarbat.ru,tuzova@newarbat.ru,,secretary@newarbat.ru,,guseva@newarbat.ru,sinitsin@newarbat.ru,,pokudona@newarbat.ru,sharafullina@newarbat.ru,tuzova@newarbat.ru,secretary@newarbar.ru,lolapost@mail.ru,sinitsin@newarbat.ru,secretary@newarbat.ru.,null@null.ru,pokudina@newarbat.ru | V78: 930497000 | W78: 473438000 | X78: 356146000 | Y78: 24115000 | Z78: 68211000 | AA78: 95133000 | AB78: -33454000 | AC78: 145489000 | AD78: -10221000 | AE78: Малое предприятие | AF78: 10 | AG78: ОСН
A79: 1037722007070 | B79: 7722281113 | C79: ООО "БАНСАНА" | D79: ОБЩЕСТВО С ОГРАНИЧЕННОЙ ОТВЕТСТВЕННОСТЬЮ "БАНСАНА" | E79: 59871233 | F79: 45290564000 | G79: 16 | H79: 12300 | I79: 772201001 | J79: 2003-02-12 | L79: 68.20.2 | M79: Аренда и управление собственным или арендованным нежилым недвижимым имуществом | O79: КОРОВИН СЕРГЕЙ НИКОЛАЕВИЧ | P79: 771525220555 | Q79: ГЕНЕРАЛЬНЫЙ ДИРЕКТОР | R79: 111033, Г.МОСКВА, УЛ. ЗОЛОТОРОЖСКИЙ ВАЛ, Д.11, СТР.26-27 | S79: +74957839444,+74953629426 | V79: 104173447 | W79: 177189000 | X79: 58998000 | Y79: 0 | Z79: 31752000 | AA79: 37653000 | AB79: 81719000 | AC79: 0 | AD79: 0 | AE79: Малое предприятие | AF79: 14 | AG79: УСН
A80: 1037722024262 | B80: 7722291263 | C80: АО "МШЗМ" | D80: АКЦИОНЕРНОЕ ОБЩЕСТВО "МОСКОВСКИЙ ШИННЫЙ ЗАВОД - М" | E80: 14235273 | F80: 45290594000 | G80: 23 | H80: 12267 | I80: 772201001 | J80: 2003-04-29 | L80: 68.20.1 | M80: Аренда и управление собственным или арендованным жилым недвижимым имуществом | N80: 68.20 | O80: АГАЕВ МАГОМЕД ИЛЬЯСОВИЧ | P80: 773166992165 | Q80: ГЕНЕРАЛЬНЫЙ ДИРЕКТОР | R80: 115088, Г.МОСКВА, УЛ 1-Я ДУБРОВСКАЯ, Д. 13А, СТР. 1 | S80: +74959812418,+74959816002 | T80: mshzm.ru | U80: ermakov@midland.com.ru | V80: 799105300 | W80: 448992000 | X80: 25267000 | Y80: 7000 | Z80: 50021000 | AA80: 50956000 | AB80: 394805000 | AC80: 301103000 | AD80: 302543000 | AF80: 18 | AG80: ОСН
A81: 1021101005870 | B81: 1112003019 | C81: ООО ЛЗК "ЛУНВОЖ" | D81: ОБЩЕСТВО С ОГРАНИЧЕННОЙ ОТВЕТСТВЕННОСТЬЮ ЛЕСОЗАГОТОВИТЕЛЬНАЯ КОНТОРА "ЛУНВОЖ" | E81: 44765850 | F81: 45268569000 | G81: 16 | H81: 12300 | I81: 773101001 | J81: 1996-11-18 | L81: 16.10.1 | M81: Производство пиломатериалов, кроме профилированных, толщиной более 6 мм; производство непропитанных железнодорожных и трамвайных шпал из древесины | N81: 02.20,02.40.2,16.21.21,02.20,02.40.2,16.1,16.10.1,16.10.9,16.23.1,16.23.2,46.1,46.13,46.73.1,46.73.2,47.1,47.52.71,49.41.3,52.10,52.24,68.10.22,68.20,77.11,77.39.1,77.39.21,77.39.23 | O81: ЧИРИЧ СЕРГЕЙ ИВАНОВИЧ | P81: 270302454441 | Q81: ГЕНЕРАЛЬНЫЙ ДИРЕКТОР | R81: 121354, Г.МОСКВА, УЛ. ДОРОГОБУЖСКАЯ, Д. 14, СТР. 16, ЭТАЖ 2 ПОМЕЩЕНИЕ 208 | S81: +78213347233,+78213321658,+78334821289,+78334822289,+78334822499 | V81: 125155000 | W81: 926360000 | X81: 197226000 | Y81: 126571000 | Z81: 62434000 | AA81: 408929000 | AB81: -227962000 | AC81: -265750000 | AD81: -300899000 | AF81: 183 | AG81: ОСН
A82: 1187746701493 | B82: 9709034542 | C82: ООО "ЗЕМЛЯНОЙ ВАЛ 36" | D82: ОБЩЕСТВО С ОГРАНИЧЕННОЙ ОТВЕТСТВЕННОСТЬЮ "ЗЕМЛЯНОЙ ВАЛ 36" | E82: 31842201 | F82: 45286555000 | G82: 16 | H82: 12300 | I82: 770901001 | J82: 2018-07-24 | L82: 68.20 | M82: Аренда и управление собственным или арендованным недвижимым имуществом | N82: 46.90,64.99,68.31.5,69.10,69.20,70.22,73.20.1,94.11 | O82: МОРОЗОВ АЛЕКСЕЙ ВЯЧЕСЛАВОВИЧ | P82: 772012461606 | Q82: ГЕНЕРАЛЬНЫЙ ДИРЕКТОР | R82: 105064, Г.МОСКВА, УЛ. ЗЕМЛЯНОЙ ВАЛ, Д. 36, ЭТ 2 КОМ 211 | S82: +78495256225 | U82: kjhgkjfkk@mail.ru | V82: 678099000 | W82: 183752000 | X82: 219837000 | Y82: 0 | Z82: 3737000 | AA82: 7931000 | AB82: 354000 | AC82: 46895000 | AD82: 472000 | AF82: 4 | AG82: ОСН
A83: 1027739031462 | B83: 7701229747 | C83: ООО "БЭЛ ДЕВЕЛОПМЕНТ" | D83: ОБЩЕСТВО С ОГРАНИЧЕННОЙ ОТВЕТСТВЕННОСТЬЮ "БЭЛ ДЕВЕЛОПМЕНТ" | E83: 52422851 | F83: 45286555000 | G83: 16 | H83: 12300 | I83: 770101001 | J83: 2000-01-17 | L83: 70.22 | M83: Консультирование по вопросам коммерческой деятельности и управления | N83: 41.2,43.12,43.2,43.3,43.99,64.9,68.2,68.3,69,73.20.1 | O83: КОМИССАРОВА ЕЛЕНА ИВАНОВНА | P83: 772634671912 | Q83: ГЕНЕРАЛЬНЫЙ ДИРЕКТОР | R83: 105064, Г.МОСКВА, ВН.ТЕР.Г. МУНИЦИПАЛЬНЫЙ ОКРУГ БАСМАННЫЙ, ПЕР ГОРОХОВСКИЙ, Д. 12, СТР. 5, ЭТАЖ/ПОМЕЩ. 1/I, КОМ. 22 | S83: +74957295086,+74957295088,+74957298088,+74959706446,+79859706446 | T83: beldevelopment.ru | V83: 3709110000 | W83: 636458000 | X83: 6204000 | Y83: 373240000 | Z83: 122516000 | AA83: 84391000 | AB83: 1036567000 | AC83: 183449000 | AD83: 1032030000 | AE83: Малое предприятие | AF83: 41 | AG83: ОСН
A84: 1027739225205 | B84: 7704235643 | C84: ООО "УСАДЬБА "ДАВЫДОВЫХ" | D84: ОБЩЕСТВО С ОГРАНИЧЕННОЙ ОТВЕТСТВЕННОСТЬЮ "УСАДЬБА "ДАВЫДОВЫХ" | E84: 58199905 | F84: 45286590000 | G84: 16 | H84: 12300 | I84: 770401001 | J84: 2002-01-04 | L84: 68.32.2 | M84: Управление эксплуатацией нежилого фонда за вознаграждение или на договорной основе | N84: 41.20,43.21,43.22,43.29,43.31,43.32,43.33,43.34,43.39,43.91,43.99,43.99.1,68.20.2,68.31.1,68.31.2,68.31.3,68.31.4,70.22,71.1,71.12.5,71.12.6,73.11,93.29.9 | O84: ДАНИЛОВА МАРИНА НИКОЛАЕВНА | P84: 890404392715 | Q84: ГЕНЕРАЛЬНЫЙ ДИРЕКТОР | R84: 119034, Г.МОСКВА, УЛ ПРЕЧИСТЕНКА, Д. 17/9 | S84: +74952281500 | U84: 6286178@mail.ru | V84: 287200000 | W84: 128198000 | X84: 2144000 | Y84: 0 | Z84: 6958000 | AA84: 6171000 | AB84: -216099000 | AC84: 59087000 | AD84: -285422000 | AE84: Микропредприятие | AF84: 9 | AG84: ОСН
A85: 1167746418707 | B85: 9701038827 | C85: ООО "МЭП" | D85: ОБЩЕСТВО С ОГРАНИЧЕННОЙ ОТВЕТСТВЕННОСТЬЮ "МОСЭНЕРГОПРОЕКТ" | E85: 2219027 | F85: 45286555000 | G85: 16 | H85: 12300 | I85: 770101001 | J85: 2016-04-26 | L85: 71.11 | M85: Деятельность в области архитектуры | N85: 42.22.3,68.20,71.11.1,71.11.2,71.11.3,71.12,71.12.1,71.12.11,71.12.12,71.12.15,71.12.2,71.12.3,71.12.41,71.12.45,71.12.6,71.12.8 | O85: ЛЕНЁВ СЕРГЕЙ НИКОЛАЕВИЧ | P85: 600400487441 | Q85: ГЕНЕРАЛЬНЫЙ ДИРЕКТОР | R85: 105066, Г.МОСКВА, УЛ. СПАРТАКОВСКАЯ, Д. 2А, СТР. 2 | S85: +74956171565,+74956171567,+74996171565,+74956171564,+74956151565,+74957211654 | U85: mail@mep.ru,panovskiyyn@mep.ru,tender@mep.ru,info@mep.ru,mep@mosenergoproject.ru,tender_mep@mosenergoproject.ru,mail@mosenergoproject.ru,karasevva@mosenergoproject.ru,ivanovas@mosenergoproject.ru,leonovav@mosenergoproject.ru,simonyanss@mosenergoproject.ru,mail@mosenergoprojecy.ru,batoffag@mosenergoproject.ru,mail@mosenergpproject.ru,reg.dei@yandex.ru | V85: 753621804 | W85: 1103133000 | X85: 387057000 | Y85: 14398000 | Z85: 437208000 | AA85: 195059000 | AB85: 146476000 | AC85: 189566000 | AD85: 206930000 | AF85: 278 | AG85: ОСН
A86: 1105032007761 | B86: 5032229441 | C86: ООО "СБЕРБАНК ИНВЕСТИЦИИ" | D86: ОБЩЕСТВО С ОГРАНИЧЕННОЙ ОТВЕТСТВЕННОСТЬЮ "СБЕРБАНК ИНВЕСТИЦИИ" | E86: 68176779 | F86: 46455000000 | G86: 16 | H86: 12300 | I86: 503201001 | J86: 2010-10-11 | L86: 64.9 | M86: Деятельность по предоставлению прочих финансовых услуг, кроме услуг по страхованию и пенсионному обеспечению | N86: 41.2,45.1,46.1,46.6,46.9,47.9,68.1,72.1,72.2,73.1 | O86: Доступ к сведениям ограничен | P86: — | Q86: — | R86: 143007, МОСКОВСКАЯ ОБЛАСТЬ, Г. ОДИНЦОВО, УЛ. МОЛОДЕЖНАЯ, Д. 46 | S86: +74957872997,+79998805304,+74956690999,+74952878978,+74956950775,+74952580500,+79067890358,+74956170241,+74956878978,+74956878979,+74952878979 | U86: amdatsenko@sberbank.ru,aiperevezentseva@sberbank.ru,ilvolokhovskiy@sberbank-ast.ru,olga_antonova@sberbank-cib.ru,christina_gokoeva@sberbank-cib.ru,christina_gokoeva@sberbank.ru,ivnemtsova@sbrf-invest.ru,dmitry_pirogov@sberbank-cib.ru,oivarshavskaya@sbf-invest.ru,oivarshavskaya@sbrf-invest.ru,kharitontsev@sbrf-invest.ru,evgeniy_malygin@sberbank-cib.ru,ttkhamraev@sbrf-invest.ru,oivarshavskaya@sbrf-inves.ru,yyvolkov@sbrf-invest.ru,tvzhukova@sbrf-invest.ru,pakhramtsova@sbrf-invest.ru,avkoptelov@sbrf-invest.ru,svkostin@sbrf-invest.ru,pkhramtsova@sbrf-invest.ru,rrbabayan@sbrf-invest.ru,oivarshavskay@sbrf-invest.ru,tatyana_goltseva@sberbank-cib.ru,oilevko@sbrf-invest.ru,rrbabyan@sbrf-invest.ru | V86: 8180946956 | W86: 234940000 | X86: 11820000 | Y86: 0 | Z86: 834213000 | AA86: 1343622000 | AB86: 16644499000 | AC86: -320193000 | AD86: 26916935000 | AF86: 19 | AG86: ОСН
A87: 1165045050312 | B87: 5045059204 | C87: ООО "АРВАЛУС" | D87: ОБЩЕСТВО С ОГРАНИЧЕННОЙ ОТВЕТСТВЕННОСТЬЮ "АРВАЛУС" | E87: 484498 | F87: 46476000682 | G87: 23 | H87: 12300 | I87: 504501001 | J87: 2016-03-09 | L87: 10.61.4 | M87: Производство мучных смесей и приготовление мучных смесей или теста для хлеба, тортов, бисквитов и блинов | N87: 10.71.1,10.71.2,10.71.3,10.72.3,10.72.4,10.89,10.89.9,46.36.3,46.36.4,46.38.23,46.38.29 | O87: КОЛЛЕР ЙОХЕН ХАРАЛЬД ДЕЛЛЕР | P87: 770972895283 504513497981 | Q87: ГЕНЕРАЛЬНЫЙ ДИРЕКТОР ГЕНЕРАЛЬНЫЙ ДИРЕКТОР | R87: 142821, МОСКОВСКАЯ ОБЛАСТЬ, Г. СТУПИНО, Д. ШМАТОВО, УЛ. ИНДУСТРИАЛЬНАЯ, ВЛД. 23, СТР. 1 | S87: +79264679106 | U87: hillion@mail.ru | V87: 667000000 | W87: 672887000 | X87: 456244000 | Y87: 154602000 | Z87: 63003000 | AA87: 67946000 | AB87: 34639000 | AC87: 21626000 | AD87: 30151000 | AF87: 43 | AG87: ОСН
A88: 1167746887835 | B88: 7708300340 | C88: ООО "СПЕЦПРОМКОМПАНИЯ" | D88: ОБЩЕСТВО С ОГРАНИЧЕННОЙ ОТВЕТСТВЕННОСТЬЮ "СПЕЦПРОМКОМПАНИЯ" | E88: 4678265 | F88: 46468000000 | G88: 16 | H88: 12300 | I88: 504001001 | J88: 2016-09-21 | L88: 01.19.21 | M88: Выращивание цветов в открытом и защищенном грунте | N88: 01.13,01.19,01.19.1,01.19.2,01.25,01.30,01.50,01.61,41.20,46.22,46.90,52.24.2,64.20,64.99.11,64.99.3,68.10,68.10.23,68.20.2,68.32,70.10,70.10.2,70.22,73.11,73.20 | O88: КОРСАКОВ РОМАН МИХАЙЛОВИЧ | P88: 500705115935 | Q88: ГЕНЕРАЛЬНЫЙ ДИРЕКТОР | R88: 140152, МОСКОВСКАЯ ОБЛАСТЬ, М.О. РАМЕНСКИЙ, Г РАМЕНСКОЕ, ТЕР. АВТОДОРОГА ММК-РАМЕНСКОЕ, КМ 10-Й, СТР. 7, ПОМЕЩ. 6 | S88: +74959876734,+74956621515,+74959876707 | U88: lebed@vebcapital.ru,seryshev@vebcapital.ru | V88: 734579000 | W88: 270413000 | X88: 85543000 | Y88: 59742000 | Z88: 89238000 | AA88: 4991000 | AB88: -3825000 | AC88: 10409000 | AD88: -4839000 | AF88: 0 | AG88: ОСН
A89: 1247700363525 | B89: 9706045458 | C89: ООО "СВЯЗЬ.ОН" | D89: ОБЩЕСТВО С ОГРАНИЧЕННОЙ ОТВЕТСТВЕННОСТЬЮ "СВЯЗЬ.ОН" | E89: 83305375 | F89: 45286596000 | G89: 16 | H89: 12300 | I89: 770601001 | J89: 2024-05-08 | L89: 47.42 | M89: Торговля розничная телекоммуникационным оборудованием, включая розничную торговлю мобильными телефонами, в специализированных магазинах | N89: 46.15.4,46.19,46.43,46.43.1,46.43.2,46.43.3,46.43.4,46.49,46.49.49,46.49.5,46.51,46.66,46.90,47.19.2,47.24.2,47.25.2,47.29.35,47.41,47.43,47.54,47.63.1,47.64,47.65,47.78,47.78.1,47.79,47.91,49.41.2,52.10,52.10.9,52.29,53.20.3,56.10.1,56.29,61.10.1,63.11,66.19.61,66.19.62,66.22,70.22,73.11,73.20.1,78.30,82.99,95.21 | O89: Доступ к сведениям ограничен | P89: — | Q89: — | R89: 119017, Г.МОСКВА, ВН.ТЕР.Г. МУНИЦИПАЛЬНЫЙ ОКРУГ ЯКИМАНКА, УЛ БОЛЬШАЯ ОРДЫНКА, Д. 44, СТР. 4 | S89: +79036213089 | V89: 433000000 | W89: 2259060000 | X89: 2612577000 | Y89: 436610000 | Z89: 176471000 | AA89: 218669000 | AB89: -3608774000 | AC89: -3006907000 | AD89: -4777158000 | AF89: 906 | AG89: ОСН
A90: 1137746396633 | B90: 7709928666 | C90: ООО "ТМК НТЦ" | D90: ОБЩЕСТВО С ОГРАНИЧЕННОЙ ОТВЕТСТВЕННОСТЬЮ "НАУЧНО-ТЕХНИЧЕСКИЙ ЦЕНТР ТМК" | E90: 17551000 | F90: 45268569000 | G90: 16 | H90: 12300 | I90: 773101001 | J90: 2013-05-06 | L90: 72.19 | M90: Научные исследования и разработки в области естественных и технических наук прочие | N90: 24.20,24.33,25.50,25.61,25.62,25.99,28.14,28.41,71.12,71.20,73.20,74.90,74.90.6 | O90: ПЫШМИНЦЕВ ИГОРЬ ЮРЬЕВИЧ | P90: 666200576943 | Q90: ГЕНЕРАЛЬНЫЙ ДИРЕКТОР | R90: 121205, Г.МОСКВА, ВН.ТЕР.Г. МУНИЦИПАЛЬНЫЙ ОКРУГ МОЖАЙСКИЙ, ТЕР ИННОВАЦИОННОГО ЦЕНТРА СКОЛКОВО, Б-Р БОЛЬШОЙ, Д. 5 | S90: +74957757600,+74957757601 | V90: 1110000000 | W90: 303514000 | X90: 571753000 | Y90: 237474000 | Z90: 68720000 | AA90: 143407000 | AB90: 17862000 | AC90: 16987000 | AD90: 27212000 | AF90: 41 | AG90: ОСН
A91: 1221600079205 | B91: 9705179378 | C91: АО "МСП ЛИЗИНГ" | D91: АКЦИОНЕРНОЕ ОБЩЕСТВО "ЛИЗИНГОВАЯ КОМПАНИЯ ПО РАЗВИТИЮ МАЛОГО И СРЕДНЕГО ПРЕДПРИНИМАТЕЛЬСТВА" | E91: 78367138 | F91: 45286560000 | G91: 16 | H91: 12267 | I91: 770501001 | J91: 2022-09-30 | L91: 64.91.2 | M91: Деятельность по финансовой аренде (лизингу/сублизингу) в прочих областях, кроме племенных животных | N91: 64.91,64.99,77.12,77.31,77.32,77.33,77.39 | O91: ДАДАЯН ИННА ВАЛЕРЬЕВНА | P91: 502807521224 | Q91: ГЕНЕРАЛЬНЫЙ ДИРЕКТОР | R91: 115054, Г.МОСКВА, ВН.ТЕР.Г. МУНИЦИПАЛЬНЫЙ ОКРУГ ЗАМОСКВОРЕЧЬЕ, НАБ КОСМОДАМИАНСКАЯ, Д. 52, СТР. 1 | S91: +78001001100,+79131130357,+79191443924 | U91: zakupki@msp-leasing.ru,sgrishanov@msp-leasing.ru,tgoncharova@corpmsp.ru | V91: 8394000000 | W91: 502364000 | X91: 62121000 | Y91: 4336000 | Z91: 1881281000 | AA91: 531662000 | AB91: 267657000 | AC91: 126410000 | AD91: 368110000 | AF91: 33 | AG91: ОСН
A92: 1195081029857 | B92: 5012099794 | C92: ООО "КОНФИТЮР" | D92: ОБЩЕСТВО С ОГРАНИЧЕННОЙ ОТВЕТСТВЕННОСТЬЮ "КОНФИТЮР" | E92: 39312141 | F92: 46404000000 | G92: 16 | H92: 12300 | I92: 501201001 | J92: 2019-04-25 | L92: 68.20.2 | M92: Аренда и управление собственным или арендованным нежилым недвижимым имуществом | N92: 68.10,68.10.1,68.31,68.32 | O92: БОРОДЯНСКИЙ ВЛАДИМИР АБРАМОВИЧ | P92: 773602815553 | Q92: ГЕНЕРАЛЬНЫЙ ДИРЕКТОР | R92: 143980, МОСКОВСКАЯ ОБЛАСТЬ, Г. БАЛАШИХА, УЛ Рождественская (Железнодорожный мкр.), Д. 3, ЭТ/ПОМ/КОМ 3/I/24 | S92: +74992130060 | V92: 550000000 | W92: 283439000 | X92: 29240000 | Y92: 0 | Z92: 17132000 | AA92: 52771000 | AB92: 127633000 | AC92: 165842000 | AD92: 170230000 | AE92: Малое предприятие | AF92: 14 | AG92: ОСН
A93: 1130280039922 | B93: 223005179 | C93: ООО "ХЕВЕЛ ЭНЕРГОСЕРВИС" | D93: ОБЩЕСТВО С ОГРАНИЧЕННОЙ ОТВЕТСТВЕННОСТЬЮ "ХЕВЕЛ ЭНЕРГОСЕРВИС" | E93: 16811427 | F93: 45293566000 | G93: 16 | H93: 12300 | I93: 772801001 | J93: 2013-06-28 | L93: 35.11.4 | M93: Производство электроэнергии, получаемой из возобновляемых источников энергии, включая выработанную солнечными, ветровыми, геотермальными электростанциями, в том числе деятельность по обеспечению их работоспособности | N93: 46.69.2,28.1,28.2,33.14,33.14,33.20,35.11,35.11,35.11.1,35.11.4,35.12,35.12,35.13,35.14,41.2,43.11,43.12,43.12.3,43.2,43.3,43.99,46.1,46.4,46.6,46.7,47.5,62.02,62.09,64.9,66.1,68.1,68.2,68.20.29,68.3,69,71.20.9,74.20,74.30,77.39,82.92 | O93: УСАЧЁВ АНТОН МИХАЙЛОВИЧ | P93: 501705774859 | Q93: ДИРЕКТОР | R93: 117342, Г.МОСКВА, ВН.ТЕР.Г. МУНИЦИПАЛЬНЫЙ ОКРУГ КОНЬКОВО, УЛ ПРОФСОЮЗНАЯ, Д. 65, К. 1, ЭТАЖ 12, ПОМЕЩ. XXXVIII, КОМНАТА №5.14 | S93: +74993228255,+74959330603 | V93: 1056450401 | W93: 211308000 | X93: 1462503000 | Y93: 582268000 | Z93: 422437000 | AA93: 708376000 | AB93: -200826000 | AC93: -19264000 | AD93: -253742000 | AF93: 21 | AG93: ОСН
A94: 1155020002059 | B94: 5020079505 | C94: МУП "КЛИНТЕПЛОСЕТЬ" | D94: МУНИЦИПАЛЬНОЕ УНИТАРНОЕ ПРЕДПРИЯТИЕ "КЛИНСКИЕ ТЕПЛОВЫЕ СЕТИ" | E94: 1547806 | F94: 46437000000 | G94: 14 | H94: 65243 | I94: 502001001 | J94: 2015-11-05 | L94: 35.30.11 | M94: Производство пара и горячей воды (тепловой энергии) тепловыми электростанциями | N94: 33.12,33.12,33.14,33.20,35.11.1,35.14,35.14,35.30,35.30.11,35.30.14,35.30.3,35.30.4,35.30.5,36.00.2,41.20,42.21,42.22.2,43.21,43.22,43.29,43.99.1,52.21.24,68.20.29,68.32.1,81.29.9 | O94: ВЕДЯШКИН ИГОРЬ ВЛАДИМИРОВИЧ | P94: 502004542900 | Q94: ДИРЕКТОР | R94: 141603, МОСКОВСКАЯ ОБЛАСТЬ, Г.О. КЛИН, Г КЛИН, ТЕР. ЛЕНИНГРАДСКОЕ ШОССЕ, КМ 88-Й, СТР. 18Б | S94: +79035234997,+74962477950,+79057219818,+74962421248,+74962458881,+74962458809,+79060715545,+74962411248,+74962427287,+74962453658,+74962458561,+79256242164,+74962420072,+74962458559,+79057219863 | U94: teploklin@mail.ru,klinteplo@list.ru,teploklin-abo@mail.ru,1@yandex.ru,tepliklin-abo@mail.ru,eploklin@mail.ru,teploklin-abo@maii.ru,eploklin-abo@mail.ru,info@klinteploset.ru,klin-jem@yandex.ru,mail@mail.ru,msk-grand@mail.ru,mgrt@list.ru,5624757@mail.ru,z_top@zhky.ru,klinmyp@mail.ru,111@qqq.com,ru@ru.ru,teplo@yandex.ru,klinsport@list.ru,klintepseti@mai.ru,klin-teplo@info.ru,klinseti@mail.ru,klinteploset@mail.ru,tepllo@yandex.ru,klinskayateploset@mail.ru,vim.zakupki@mail.ru,klin@rfg.ru,klinteplo@mail.ru | V94: 424959716 | W94: 119307000 | X94: 213447000 | Y94: 2174000 | Z94: 150873000 | AA94: 32017000 | AB94: -5543000 | AC94: -77900000 | AD94: -5039000 | AG94: ОСН
A95: 1067760772419 | B95: 7708621985 | C95: АО "ГК "ИНФОРМТЕХНИКА" | D95: АКЦИОНЕРНОЕ ОБЩЕСТВО "ГРУППА КОМПАНИЙ "ИНФОРМТЕХНИКА" | E95: 98911851 | F95: 45286565000 | G95: 16 | H95: 12267 | I95: 770801001 | J95: 2006-12-08 | L95: 66.12.2 | M95: Деятельность по управлению ценными бумагами | N95: 41.20,42.21,42.22.2,62.02,64.99.11,64.99.12,66.19,68.10.12,68.10.23,68.20.2,70.22,73.11,77.33,77.33.1 | O95: ГРЕЙСМАН КОНСТАНТИН АНАТОЛЬЕВИЧ | P95: 695005990026 | Q95: ГЕНЕРАЛЬНЫЙ ДИРЕКТОР | R95: 107140, Г.МОСКВА, УЛ. ВЕРХНЯЯ КРАСНОСЕЛЬСКАЯ, Д.2/1, СТР.1 | S95: +74956466731,+74957716734 | T95: www.minicom.ru | U95: sale@infotek.ru | V95: 253150000 | W95: 100100000 | X95: 170000 | Y95: 1000 | Z95: 42556000 | AA95: 43053000 | AB95: 104321000 | AC95: 87586000 | AD95: 107030000 | AE95: Малое предприятие | AF95: 1 | AG95: ОСН
A96: 1045001302367 | B96: 5005038631 | C96: ГУП МО "БЕЛООЗЕРСКОЕ ЖКХ" | D96: ГОСУДАРСТВЕННОЕ УНИТАРНОЕ ПРЕДПРИЯТИЕ МОСКОВСКОЙ ОБЛАСТИ "БЕЛООЗЕРСКОЕ ЖИЛИЩНО-КОММУНАЛЬНОЕ ХОЗЯЙСТВО" | E96: 73017712 | F96: 46410000000 | G96: 14 | H96: 65243 | I96: 500501001 | J96: 2004-05-19 | L96: 36.00.1 | M96: Забор и очистка воды для питьевых и промышленных нужд | N96: 37.00,49.41.3,68.32.1,33.14,36.00,36.00.1,36.00.2,37.00,38.11,42.21,43.12.3,43.21,43.22,43.29,43.31,43.32,43.91,43.99,43.99.1,43.99.5,45.20,49.4,49.41,61.10,81.22 | O96: ШЕВЦОВ КИРИЛЛ АЛЕКСАНДРОВИЧ | P96: 773008312829 | Q96: ДИРЕКТОР | R96: 140202, МОСКОВСКАЯ ОБЛАСТЬ, Г.О. ВОСКРЕСЕНСК, Г ВОСКРЕСЕНСК, УЛ НЕКРАСОВА, Д. 17 | S96: +74964475236,+74964455282,+74964425282,+74954455282,+74964448732,+74964455258,+74951234567,+74991553040,+74964451244,+74964424570,+72444455282,+79265425241,+74961155282,+74964456365,+74964432654,+74964455828,+74964431762,+74964475070,+74964475050,+74964425700,+74966158336,+78496445236,+79104910761,+74962275236,+74964475326,+74964455252,+79162455434,+77964455282,+78244475236,+74964475430,+74964475282 | T96: НЕТ,bgkh.ru | U96: bgkh@bgkh.ru,beloozgkh@mail.ru,gadi83@mail.ru,bgkh@wlc-net.ru,dzar@bk.ru,bghk@bghk.ru,mzkp@mail.ru,ptobgkh@mail.ru,mail@mail.ru,dshi3@mail.ru,bjkh@wls-net.ru,cibino37@mail.ru,cibibno37@mail.ru,infojkh@mail.ru,a.ivushkin@bgkh.ru,voskresensk@mail.ru,bqkh@wlc-net.ru,ovowoskresensk@mail.ru,gal.maltzeva@yandex.ru,bdkh@wlc-net.ru,mup@mail.ru,123@mail.ru,132w@mail.ru,bgkh@wlc-nrt.ru,gk-lp@mail.ru,jgk@mail.ru,bgkh@wlknet.ru,bgkx@wlc-net.ru,bgkh@wlcnet.ru,111@mail.ru,0000@mail.ru,spartabel@mail.ru,bgkh@wlс-net.ru,bgkx@wlc-mail.ru,ogkh@wlc-net.ru,bgkg@mail.ru,plobogrh@mail.ru,plobogkh@mail.ru,adm-beloozerskiy@mail.ru,bzkh@mail.ru,bgkh@wls-net.ru,000@000.ru,00000@00.ru,jkyg@mail.ru,mail@bgkx.ru,bgkh@wl-net.ru,dgkh@wic-net.ru,dgkh@wlc-net.ru,bghk@mail.ru,bgkh@mail.ru | V96: 347164042 | W96: 823167000 | X96: 248357000 | Y96: 20515000 | Z96: 425760000 | AA96: 230085000 | AB96: -135039000 | AC96: -110061000 | AD96: -163963000 | AG96: ОСН
A97: 1155032010825 | B97: 5032217904 | C97: ООО "БАЗИС-МОСКВА" | D97: ОБЩЕСТВО С ОГРАНИЧЕННОЙ ОТВЕТСТВЕННОСТЬЮ "БАЗИС-МОСКВА" | E97: 11738045 | F97: 45286552000 | G97: 16 | H97: 12300 | I97: 770401001 | J97: 2015-10-12 | L97: 46.33 | M97: Торговля оптовая молочными продуктами, яйцами и пищевыми маслами и жирами | N97: 10.42,10.51,10.51.1,10.51.3,10.51.9,10.89,10.89.1,10.89.5,10.89.6,10.89.7,10.89.8,10.89.9,46.21,46.21.11,46.21.12,46.21.13,46.21.19,46.33.1,46.33.3,46.38,46.38.29,46.39,47.11,47.19,47.29,47.29.11,47.29.2,47.29.39,47.8,47.9,49.4,49.41.1,49.41.2,49.41.3,52.10,52.21,52.21.2,64.91,64.99,68.20,68.20.2,77.11,77.31,77.32,77.33,77.33.1,77.39.1,77.39.11,77.39.2,77.39.23,82.99 | O97: ЗАЛЕССКИЙ ГЕННАДИЙ ПЕТРОВИЧ | P97: 773395181779 | Q97: ДИРЕКТОР | R97: 121069, Г.МОСКВА, Б-Р НОВИНСКИЙ, Д. 20А, СТР 3-6, ПОМЕЩ. I КОМНАТА 115 | S97: +79180297755 | V97: 123894000 | W97: 292613000 | X97: 10641000 | Y97: 383000 | Z97: 3715000 | AA97: 56269000 | AB97: 1037000 | AC97: 23802000 | AD97: 6385000 | AE97: Малое предприятие | AF97: 2 | AG97: ОСН
A98: 1045011805244 | B98: 5039008071 | C98: МУП "ТВК Г. ПУЩИНО" | D98: МУНИЦИПАЛЬНОЕ УНИТАРНОЕ ПРЕДПРИЯТИЕ "ТЕПЛОВОДОКАНАЛ ГОРОДА ПУЩИНО" ГОРОДСКОГО ОКРУГА СЕРПУХОВ МОСКОВСКОЙ ОБЛАСТИ | E98: 4783967 | F98: 46470000506 | G98: 14 | H98: 65243 | I98: 503901001 | J98: 2004-10-29 | L98: 35.30.3 | M98: Распределение пара и горячей воды (тепловой энергии) | N98: 35.30.5,36.00.2,37.00,35.30.3,35.30.5,36.00.2,37.00 | O98: ДЕМИН СТАНИСЛАВ АЛЕКСЕЕВИЧ | P98: 331602813080 | Q98: ДИРЕКТОР | R98: 142290, МОСКОВСКАЯ ОБЛАСТЬ, Г.О. СЕРПУХОВ, Г ПУЩИНО, УЛ СТРОИТЕЛЕЙ, Д. 4 | S98: +74967732759,+79037091479,+74967732605,+74967731630,+74967733633,+74955422183,+79653670903,+74967732753,+74967732750,+74967732501,+74967351075,+79164779266,+74967732506,+71234567890,+79467732759,+74992507998,+74967732993,+74967731825,+74967731111,+74967733630,+74967735201,+74957274494,+74968732759,+74967733643,+74967123456,+70000732729,+70000732759 | T98: pushchino-tvk.ru | U98: mup-tvk@yandex.ru,directortvk@yandex.ru,zakupki-muptvk@yandex.ru,pshn_muptvk@mosreg.ru,ku@pushchino-tvk.ru,mup@vodokanalpodolsk.ru,mup@mail.ru,mup-tvr@yandex.ru,gumchs-mo@mail.ru,mail@mail.ru,clyucherowa@yandex.ru,os@orionhim.ru,myp-tvk@yandex.ru,myp.tvk@yandex.ru,mup-tnk@yandex.ru,mup_tvk@yandex.ru,none@none.ru,mup-tvl@yandex.ru,serpuhovbuh@yandex.ru,up-tvk@yandex.ru,tvk@yandex.ru,info@info.ru,123@mail.ru,mup-tvk@mail.ru,muptvk@yandex.ru,okts@flexuser.ru,bs-nrf@mail.ru,mup-tvk@yndeks.ru,koshman.tvk@yandex.ru,,avmak@keldysh.ru,tvkpo@mail.ru,ghghg@mail.ru,jkjkjkj@mail.ru,lk@rambler.ru,mup@rambler.ru,teplo@mail.ru,otvisimanina@yandex.ru,nn@qip.ru,nn@mail.ru,teplovod@mail.ru,info@k-agent.ru,tvbuh@yandex.ru,veronfr@gmail.com,buchissppushino@rambler.ru,koshman.tvk@yandex.ru,koshman/tvk@yandex.ru | V98: 218786000 | W98: 459586000 | X98: 148077000 | Y98: 32684000 | Z98: 180526000 | AA98: 135041000 | AB98: -42572000 | AC98: -75038000 | AD98: -49156000 | AG98: ОСН
A99: 1045010215623 | B99: 5050050180 | C99: ООО "ПРИНЦ" | D99: ОБЩЕСТВО С ОГРАНИЧЕННОЙ ОТВЕТСТВЕННОСТЬЮ "ПРИНЦ" | E99: 75211815 | F99: 46488000000 | G99: 16 | H99: 12300 | I99: 505001001 | J99: 2004-11-30 | L99: 68.20 | M99: Аренда и управление собственным или арендованным недвижимым имуществом | O99: ШАКЛОВА МАРИЯ ВЛАДИМИРОВНА | P99: 344810272701 | Q99: ДИРЕКТОР | R99: 141100, МОСКОВСКАЯ ОБЛАСТЬ, Г. ЩЁЛКОВО, Ш. ФРЯНОВСКОЕ, Д. 1, ОФИС 182 | S99: +74959955906,+74959955907 | V99: 120000000 | W99: 117392000 | X99: 52940000 | Y99: 6823000 | Z99: 227495000 | AA99: 12399000 | AB99: 60399000 | AC99: 0 | AD99: 0 | AE99: Микропредприятие | AF99: 7 | AG99: УСН
A100: 1157746606445 | B100: 7707345330 | C100: ООО "МОСЭНКА" | D100: ОБЩЕСТВО С ОГРАНИЧЕННОЙ ОТВЕТСТВЕННОСТЬЮ "МОСЭНКА" | E100: 11422833 | F100: 45286585000 | G100: 23 | H100: 12300 | I100: 770701001 | J100: 2015-07-07 | L100: 68.20.2 | M100: Аренда и управление собственным или арендованным нежилым недвижимым имуществом | N100: 41.20,43.11,43.12.3,43.21,43.22,43.31,43.32,43.33,43.34,68.10.22 | O100: ДЖАН ДЖЕЛАЛ БУРАК | P100: 772393040837 | Q100: ГЕНЕРАЛЬНЫЙ ДИРЕКТОР | R100: 127051, Г.МОСКВА, Б-Р ЦВЕТНОЙ, Д. 25, СТР. 3 | S100: +74957872288,+74957872292 | T100: www.mosenka.ru | U100: marketing.department@mosenka.ru,aleksandra.lukinova@mosenka.ru,info@mosenka.ru | V100: 108000000 | W100: 1042240000 | X100: 80000 | Y100: 24118000 | Z100: 9469000 | AA100: 249087000 | AB100: 571367000 | AC100: 755743000 | AD100: 761813000 | AF100: 28 | AG100: ОСН
...

Sheet Категория С
A1: ОГРН | B1: ИНН | C1: Краткое наименование | D1: ОКВЭД наименование | E1: =ЛИК_дляСкорингаДП!L1 -> ОКВЭД | F1: =ЛИК_дляСкорингаДП!N1 -> Доп. ОКВЭД | G1: =ЛИК_дляСкорингаДП!AG1 -> Налоговый режим | H1: Класс | I1: Балл ОКВЭД | J1: Балл Доп. ОКВЭД | K1: Балл НР | L1: Итоговый Балл | M1: Стоп-фактор
A2: =ЛИК_дляСкорингаДП!A2 -> 1027700092661 | B2: =ЛИК_дляСкорингаДП!B2 -> 7712040126 | C2: =ЛИК_дляСкорингаДП!C2 -> ПАО "АЭРОФЛОТ" | D2: =ЛИК_дляСкорингаДП!M2 -> Перевозка воздушным пассажирским транспортом, подчиняющимся расписанию | E2: =ЛИК_дляСкорингаДП!L2 -> 51.10.1 | F2: =ЛИК_дляСкорингаДП!N2 -> 49.39.39,51.21.1,52.23.19,52.29,61.90.9,68.20.29,85.42.9,86.21,18.12,33.16,41.20,46.14,51.10.1,51.21.3,52.29,55.10,56.10.1,58.19,62.01,62.02,62.09,64.99,68.32.2,70.22,73.20,79.11,85.22,85.42.9,86.21 | G2: =ЛИК_дляСкорингаДП!AG2 -> ОСН | H2: =IF(ISNUMBER(E2),E2, IFERROR(LEFT(E2,FIND(".",E2)-1),E2)) -> 51 | I2: =IF(COUNTIF(Справочник_ОКВЭД_НР!$A$3:$A$62,H2)>0,Справочник_ОКВЭД_НР!$L$8, IF(COUNTIF(Справочник_ОКВЭД_НР!$C$3:$C$62,H2)>0,Справочник_ОКВЭД_НР!$L$9, IF(COUNTIF(Справочник_ОКВЭД_НР!$E$3:$E$62,H2)>0,Справочник_ОКВЭД_НР!$L$10, IF(COUNTIF(Справочник_ОКВЭД_НР!$G$3:$G$62,H2)>0,Справочник_ОКВЭД_НР!$L$11,50)))) -> 60 | J2: {=IFERROR( (SUMPRODUCT(ISNUMBER(SEARCH(","&Справочник_ОКВЭД_НР!$A$3:$A$62&".",","&SUBSTITUTE(F2," ","")&",")))*Справочник_ОКВЭД_НР!$L$9 + SUMPRODUCT(ISNUMBER(SEARCH(","&Справочник_ОКВЭД_НР!$C$3:$C$62&".",","&SUBSTITUTE(F2," ","")&",")))*Справочник_ОКВЭД_НР!$L$10 + SUMPRODUCT(ISNUMBER(SEARCH(","&Справочник_ОКВЭД_НР!$E$3:$E$62&".",","&SUBSTITUTE(F2," ","")&",")))*Справочник_ОКВЭД_НР!$L$11 + SUMPRODUCT(ISNUMBER(SEARCH(","&Справочник_ОКВЭД_НР!$G$3:$G$62&".",","&SUBSTITUTE(F2," ","")&",")))*Справочник_ОКВЭД_НР!$L$12) / (SUMPRODUCT(ISNUMBER(SEARCH(","&Справочник_ОКВЭД_НР!$A$3:$A$62&".",","&SUBSTITUTE(F2," ","")&","))) + SUMPRODUCT(ISNUMBER(SEARCH(","&Справочник_ОКВЭД_НР!$C$3:$C$62&".",","&SUBSTITUTE(F2," ","")&","))) + SUMPRODUCT(ISNUMBER(SEARCH(","&Справочник_ОКВЭД_НР!$E$3:$E$62&".",","&SUBSTITUTE(F2," ","")&","))) + SUMPRODUCT(ISNUMBER(SEARCH(","&Справочник_ОКВЭД_НР!$G$3:$G$62&".",","&SUBSTITUTE(F2," ","")&",")))), 50)} -> 50 | K2: =IFERROR(VLOOKUP(G2,Справочник_ОКВЭД_НР!$O:$P,2,FALSE()),50) -> 100 | L2: =(I2*Справочник_ОКВЭД_НР!$L$2+J2*Справочник_ОКВЭД_НР!$L$3+K2*Справочник_ОКВЭД_НР!$L$4)*M2 -> 63.5 | M2: =IF(COUNTIF(Справочник_ОКВЭД_НР!$G$3:$G$62,H2)>0,0,1) -> 1
A3: =ЛИК_дляСкорингаДП!A3 -> 1067746341024 | B3: =ЛИК_дляСкорингаДП!B3 -> 7708591995 | C3: =ЛИК_дляСкорингаДП!C3 -> ПАО "ТРАНСКОНТЕЙНЕР" | D3: =ЛИК_дляСкорингаДП!M3 -> Деятельность вспомогательная прочая, связанная с перевозками | E3: =ЛИК_дляСкорингаДП!L3 -> 52.29 | F3: =ЛИК_дляСкорингаДП!N3 -> 35.30.14,46.90,49.41.1,52.24.2,68.20.29,16.23,29.20,30.2,33.11,33.12,33.17,35.30,41.2,43.11,43.12,45.11,45.19,45.20,46.69,46.77,46.90,47.99,49.20,49.41,52.10,52.2,52.21,52.24,52.29,68.1,68.2,69.20,69.20.2,70.22,73.20.1,77.12,77.3,77.39,82.20 | G3: =ЛИК_дляСкорингаДП!AG3 -> ОСН | H3: =IF(ISNUMBER(E3),E3, IFERROR(LEFT(E3,FIND(".",E3)-1),E3)) -> 52.29 | I3: =IF(COUNTIF(Справочник_ОКВЭД_НР!$A$3:$A$62,H3)>0,Справочник_ОКВЭД_НР!$L$8, IF(COUNTIF(Справочник_ОКВЭД_НР!$C$3:$C$62,H3)>0,Справочник_ОКВЭД_НР!$L$9, IF(COUNTIF(Справочник_ОКВЭД_НР!$E$3:$E$62,H3)>0,Справочник_ОКВЭД_НР!$L$10, IF(COUNTIF(Справочник_ОКВЭД_НР!$G$3:$G$62,H3)>0,Справочник_ОКВЭД_НР!$L$11,50)))) -> 50 | J3: {=IFERROR( (SUMPRODUCT(ISNUMBER(SEARCH(","&Справочник_ОКВЭД_НР!$A$3:$A$62&".",","&SUBSTITUTE(F3," ","")&",")))*Справочник_ОКВЭД_НР!$L$9 + SUMPRODUCT(ISNUMBER(SEARCH(","&Справочник_ОКВЭД_НР!$C$3:$C$62&".",","&SUBSTITUTE(F3," ","")&",")))*Справочник_ОКВЭД_НР!$L$10 + SUMPRODUCT(ISNUMBER(SEARCH(","&Справочник_ОКВЭД_НР!$E$3:$E$62&".",","&SUBSTITUTE(F3," ","")&",")))*Справочник_ОКВЭД_НР!$L$11 + SUMPRODUCT(ISNUMBER(SEARCH(","&Справочник_ОКВЭД_НР!$G$3:$G$62&".",","&SUBSTITUTE(F3," ","")&",")))*Справочник_ОКВЭД_НР!$L$12) / (SUMPRODUCT(ISNUMBER(SEARCH(","&Справочник_ОКВЭД_НР!$A$3:$A$62&".",","&SUBSTITUTE(F3," ","")&","))) + SUMPRODUCT(ISNUMBER(SEARCH(","&Справочник_ОКВЭД_НР!$C$3:$C$62&".",","&SUBSTITUTE(F3," ","")&","))) + SUMPRODUCT(ISNUMBER(SEARCH(","&Справочник_ОКВЭД_НР!$E$3:$E$62&".",","&SUBSTITUTE(F3," ","")&","))) + SUMPRODUCT(ISNUMBER(SEARCH(","&Справочник_ОКВЭД_НР!$G$3:$G$62&".",","&SUBSTITUTE(F3," ","")&",")))), 50)} -> 50 | K3: =IFERROR(VLOOKUP(G3,Справочник_ОКВЭД_НР!$O:$P,2,FALSE()),50) -> 100 | L3: =(I3*Справочник_ОКВЭД_НР!$L$2+J3*Справочник_ОКВЭД_НР!$L$3+K3*Справочник_ОКВЭД_НР!$L$4)*M3 -> 57.5 | M3: =IF(COUNTIF(Справочник_ОКВЭД_НР!$G$3:$G$62,H3)>0,0,1) -> 1
A4: =ЛИК_дляСкорингаДП!A4 -> 1097746772738 | B4: =ЛИК_дляСкорингаДП!B4 -> 7708709686 | C4: =ЛИК_дляСкорингаДП!C4 -> АО "ФПК" | D4: =ЛИК_дляСкорингаДП!M4 -> Перевозка пассажиров железнодорожным транспортом в междугородном сообщении | E4: =ЛИК_дляСкорингаДП!L4 -> 49.10.1 | F4: =ЛИК_дляСкорингаДП!N4 -> 26.5,35.30.14,36.00,45.20,47.11,47.19,47.73,47.74,47.75,47.9,49.10,49.20,49.20,49.3,49.4,52.10,52.21,52.24,52.29,55.90,56.10,56.10.1,56.10.3,56.29,58,59.1,63.11.1,68.20,73.11,74.90.31,77.2,77.3,77.39,79.11,85.30,85.42,85.42.9,90.04,91.01,91.02,91.03,93.11,93.19,96.04 | G4: =ЛИК_дляСкорингаДП!AG4 -> ОСН | H4: =IF(ISNUMBER(E4),E4, IFERROR(LEFT(E4,FIND(".",E4)-1),E4)) -> 49 | I4: =IF(COUNTIF(Справочник_ОКВЭД_НР!$A$3:$A$62,H4)>0,Справочник_ОКВЭД_НР!$L$8, IF(COUNTIF(Справочник_ОКВЭД_НР!$C$3:$C$62,H4)>0,Справочник_ОКВЭД_НР!$L$9, IF(COUNTIF(Справочник_ОКВЭД_НР!$E$3:$E$62,H4)>0,Справочник_ОКВЭД_НР!$L$10, IF(COUNTIF(Справочник_ОКВЭД_НР!$G$3:$G$62,H4)>0,Справочник_ОКВЭД_НР!$L$11,50)))) -> 60 | J4: {=IFERROR( (SUMPRODUCT(ISNUMBER(SEARCH(","&Справочник_ОКВЭД_НР!$A$3:$A$62&".",","&SUBSTITUTE(F4," ","")&",")))*Справочник_ОКВЭД_НР!$L$9 + SUMPRODUCT(ISNUMBER(SEARCH(","&Справочник_ОКВЭД_НР!$C$3:$C$62&".",","&SUBSTITUTE(F4," ","")&",")))*Справочник_ОКВЭД_НР!$L$10 + SUMPRODUCT(ISNUMBER(SEARCH(","&Справочник_ОКВЭД_НР!$E$3:$E$62&".",","&SUBSTITUTE(F4," ","")&",")))*Справочник_ОКВЭД_НР!$L$11 + SUMPRODUCT(ISNUMBER(SEARCH(","&Справочник_ОКВЭД_НР!$G$3:$G$62&".",","&SUBSTITUTE(F4," ","")&",")))*Справочник_ОКВЭД_НР!$L$12) / (SUMPRODUCT(ISNUMBER(SEARCH(","&Справочник_ОКВЭД_НР!$A$3:$A$62&".",","&SUBSTITUTE(F4," ","")&","))) + SUMPRODUCT(ISNUMBER(SEARCH(","&Справочник_ОКВЭД_НР!$C$3:$C$62&".",","&SUBSTITUTE(F4," ","")&","))) + SUMPRODUCT(ISNUMBER(SEARCH(","&Справочник_ОКВЭД_НР!$E$3:$E$62&".",","&SUBSTITUTE(F4," ","")&","))) + SUMPRODUCT(ISNUMBER(SEARCH(","&Справочник_ОКВЭД_НР!$G$3:$G$62&".",","&SUBSTITUTE(F4," ","")&",")))), 50)} -> 50 | K4: =IFERROR(VLOOKUP(G4,Справочник_ОКВЭД_НР!$O:$P,2,FALSE()),50) -> 100 | L4: =(I4*Справочник_ОКВЭД_НР!$L$2+J4*Справочник_ОКВЭД_НР!$L$3+K4*Справочник_ОКВЭД_НР!$L$4)*M4 -> 63.5 | M4: =IF(COUNTIF(Справочник_ОКВЭД_НР!$G$3:$G$62,H4)>0,0,1) -> 1
A5: =ЛИК_дляСкорингаДП!A5 -> 1067746082546 | B5: =ЛИК_дляСкорингаДП!B5 -> 7708587205 | C5: =ЛИК_дляСкорингаДП!C5 -> АО "РЖДСТРОЙ" | D5: =ЛИК_дляСкорингаДП!M5 -> Подготовка строительной площадки | E5: =ЛИК_дляСкорингаДП!L5 -> 43.12 | F5: =ЛИК_дляСкорингаДП!N5 -> 23.32,23.51,23.61,25.11,37.00,41.10,41.2,41.20,42.11,42.12,42.13,42.91,42.99,43.11,43.12.3,43.2,43.21,43.22,43.29,43.3,43.39,43.91,43.99,43.99.1,46.73,47.52.7,49.20,68.20,71.12.1,71.12.2,71.12.45,77.32 | G5: =ЛИК_дляСкорингаДП!AG5 -> ОСН | H5: =IF(ISNUMBER(E5),E5, IFERROR(LEFT(E5,FIND(".",E5)-1),E5)) -> 43 | I5: =IF(COUNTIF(Справочник_ОКВЭД_НР!$A$3:$A$62,H5)>0,Справочник_ОКВЭД_НР!$L$8, IF(COUNTIF(Справочник_ОКВЭД_НР!$C$3:$C$62,H5)>0,Справочник_ОКВЭД_НР!$L$9, IF(COUNTIF(Справочник_ОКВЭД_НР!$E$3:$E$62,H5)>0,Справочник_ОКВЭД_НР!$L$10, IF(COUNTIF(Справочник_ОКВЭД_НР!$G$3:$G$62,H5)>0,Справочник_ОКВЭД_НР!$L$11,50)))) -> 100 | J5: {=IFERROR( (SUMPRODUCT(ISNUMBER(SEARCH(","&Справочник_ОКВЭД_НР!$A$3:$A$62&".",","&SUBSTITUTE(F5," ","")&",")))*Справочник_ОКВЭД_НР!$L$9 + SUMPRODUCT(ISNUMBER(SEARCH(","&Справочник_ОКВЭД_НР!$C$3:$C$62&".",","&SUBSTITUTE(F5," ","")&",")))*Справочник_ОКВЭД_НР!$L$10 + SUMPRODUCT(ISNUMBER(SEARCH(","&Справочник_ОКВЭД_НР!$E$3:$E$62&".",","&SUBSTITUTE(F5," ","")&",")))*Справочник_ОКВЭД_НР!$L$11 + SUMPRODUCT(ISNUMBER(SEARCH(","&Справочник_ОКВЭД_НР!$G$3:$G$62&".",","&SUBSTITUTE(F5," ","")&",")))*Справочник_ОКВЭД_НР!$L$12) / (SUMPRODUCT(ISNUMBER(SEARCH(","&Справочник_ОКВЭД_НР!$A$3:$A$62&".",","&SUBSTITUTE(F5," ","")&","))) + SUMPRODUCT(ISNUMBER(SEARCH(","&Справочник_ОКВЭД_НР!$C$3:$C$62&".",","&SUBSTITUTE(F5," ","")&","))) + SUMPRODUCT(ISNUMBER(SEARCH(","&Справочник_ОКВЭД_НР!$E$3:$E$62&".",","&SUBSTITUTE(F5," ","")&","))) + SUMPRODUCT(ISNUMBER(SEARCH(","&Справочник_ОКВЭД_НР!$G$3:$G$62&".",","&SUBSTITUTE(F5," ","")&",")))), 50)} -> 50 | K5: =IFERROR(VLOOKUP(G5,Справочник_ОКВЭД_НР!$O:$P,2,FALSE()),50) -> 100 | L5: =(I5*Справочник_ОКВЭД_НР!$L$2+J5*Справочник_ОКВЭД_НР!$L$3+K5*Справочник_ОКВЭД_НР!$L$4)*M5 -> 87.5 | M5: =IF(COUNTIF(Справочник_ОКВЭД_НР!$G$3:$G$62,H5)>0,0,1) -> 1
A6: =ЛИК_дляСкорингаДП!A6 -> 1117746460358 | B6: =ЛИК_дляСкорингаДП!B6 -> 7704784450 | C6: =ЛИК_дляСкорингаДП!C6 -> АО "ИНТЕР РАО-ЭЛЕКТРОГЕНЕРАЦИЯ" | D6: =ЛИК_дляСкорингаДП!M6 -> Производство электроэнергии тепловыми электростанциями, в том числе деятельность по обеспечению работоспособности электростанций | E6: =ЛИК_дляСкорингаДП!L6 -> 35.11.1 | F6: =ЛИК_дляСкорингаДП!N6 -> 25.62,33.12,33.14,35.11.2,35.14,35.23,35.30.11,35.30.14,35.30.4,36.00.1,36.00.2,37.00,46.90,49.42,49.50.21,52.10.21,52.10.9,52.21.11,61.10.1,68.20.1,68.20.29,69.20.2,71.20.4,77.39.11,77.39.23,77.39.29,82.99,93.11,96.09.9,03.21.4,03.22.5,20.11,23.61,33.13,33.14,33.14,33.20,35.11,35.11.1,35.11.1,35.11.2,35.11.2,35.12,35.12,35.13,35.14,35.14,35.22,35.30.1,35.30.11,35.30.14,35.30.2,35.30.3,35.30.4,35.30.5,36.00.1,36.00.2,37.00,37.00,41.2,41.20,42.21,42.22.1,42.22.3,43.21,46.71,46.90,49.20,49.3,49.4,49.41.1,49.41.2,49.50.21,49.50.22,52.10,52.10.21,52.10.23,52.21.1,52.21.2,52.24,56.29,61.10.1,68.10,68.20,68.20.1,68.20.2,68.32,70.10.1,70.10.2,70.22,71.12.1,71.12.6,71.12.62,71.20.1,72.19,73.20,77.39,85.23,85.42,86.21,86.23,86.90.4,91.01,93.11,96.09 | G6: =ЛИК_дляСкорингаДП!AG6 -> ОСН | H6: =IF(ISNUMBER(E6),E6, IFERROR(LEFT(E6,FIND(".",E6)-1),E6)) -> 35 | I6: =IF(COUNTIF(Справочник_ОКВЭД_НР!$A$3:$A$62,H6)>0,Справочник_ОКВЭД_НР!$L$8, IF(COUNTIF(Справочник_ОКВЭД_НР!$C$3:$C$62,H6)>0,Справочник_ОКВЭД_НР!$L$9, IF(COUNTIF(Справочник_ОКВЭД_НР!$E$3:$E$62,H6)>0,Справочник_ОКВЭД_НР!$L$10, IF(COUNTIF(Справочник_ОКВЭД_НР!$G$3:$G$62,H6)>0,Справочник_ОКВЭД_НР!$L$11,50)))) -> 60 | J6: {=IFERROR( (SUMPRODUCT(ISNUMBER(SEARCH(","&Справочник_ОКВЭД_НР!$A$3:$A$62&".",","&SUBSTITUTE(F6," ","")&",")))*Справочник_ОКВЭД_НР!$L$9 + SUMPRODUCT(ISNUMBER(SEARCH(","&Справочник_ОКВЭД_НР!$C$3:$C$62&".",","&SUBSTITUTE(F6," ","")&",")))*Справочник_ОКВЭД_НР!$L$10 + SUMPRODUCT(ISNUMBER(SEARCH(","&Справочник_ОКВЭД_НР!$E$3:$E$62&".",","&SUBSTITUTE(F6," ","")&",")))*Справочник_ОКВЭД_НР!$L$11 + SUMPRODUCT(ISNUMBER(SEARCH(","&Справочник_ОКВЭД_НР!$G$3:$G$62&".",","&SUBSTITUTE(F6," ","")&",")))*Справочник_ОКВЭД_НР!$L$12) / (SUMPRODUCT(ISNUMBER(SEARCH(","&Справочник_ОКВЭД_НР!$A$3:$A$62&".",","&SUBSTITUTE(F6," ","")&","))) + SUMPRODUCT(ISNUMBER(SEARCH(","&Справочник_ОКВЭД_НР!$C$3:$C$62&".",","&SUBSTITUTE(F6," ","")&","))) + SUMPRODUCT(ISNUMBER(SEARCH(","&Справочник_ОКВЭД_НР!$E$3:$E$62&".",","&SUBSTITUTE(F6," ","")&","))) + SUMPRODUCT(ISNUMBER(SEARCH(","&Справочник_ОКВЭД_НР!$G$3:$G$62&".",","&SUBSTITUTE(F6," ","")&",")))), 50)} -> 50 | K6: =IFERROR(VLOOKUP(G6,Справочник_ОКВЭД_НР!$O:$P,2,FALSE()),50) -> 100 | L6: =(I6*Справочник_ОКВЭД_НР!$L$2+J6*Справочник_ОКВЭД_НР!$L$3+K6*Справочник_ОКВЭД_НР!$L$4)*M6 -> 63.5 | M6: =IF(COUNTIF(Справочник_ОКВЭД_НР!$G$3:$G$62,H6)>0,0,1) -> 1
A7: =ЛИК_дляСкорингаДП!A7 -> 5087746119951 | B7: =ЛИК_дляСкорингаДП!B7 -> 7721632827 | C7: =ЛИК_дляСкорингаДП!C7 -> АО "КОНЦЕРН РОСЭНЕРГОАТОМ" | D7: =ЛИК_дляСкорингаДП!M7 -> Производство электроэнергии атомными электростанциями, в том числе деятельность по обеспечению работоспособности электростанций | E7: =ЛИК_дляСкорингаДП!L7 -> 35.11.3 | F7: =ЛИК_дляСкорингаДП!N7 -> 35.11.3,35.12,35.12,35.13,35.30.12,35.30.2,35.30.3,35.30.5,36.00.1,37.00,38.1,38.2,42.22.3,42.99,43.21,51.10,55.10,55.90,61.10,63.11,70.22,71.11.1,71.12,71.12.1,71.12.45,71.20,72.19,84.24,85.30,85.42,86.90.4 | G7: =ЛИК_дляСкорингаДП!AG7 -> ОСН | H7: =IF(ISNUMBER(E7),E7, IFERROR(LEFT(E7,FIND(".",E7)-1),E7)) -> 35 | I7: =IF(COUNTIF(Справочник_ОКВЭД_НР!$A$3:$A$62,H7)>0,Справочник_ОКВЭД_НР!$L$8, IF(COUNTIF(Справочник_ОКВЭД_НР!$C$3:$C$62,H7)>0,Справочник_ОКВЭД_НР!$L$9, IF(COUNTIF(Справочник_ОКВЭД_НР!$E$3:$E$62,H7)>0,Справочник_ОКВЭД_НР!$L$10, IF(COUNTIF(Справочник_ОКВЭД_НР!$G$3:$G$62,H7)>0,Справочник_ОКВЭД_НР!$L$11,50)))) -> 60 | J7: {=IFERROR( (SUMPRODUCT(ISNUMBER(SEARCH(","&Справочник_ОКВЭД_НР!$A$3:$A$62&".",","&SUBSTITUTE(F7," ","")&",")))*Справочник_ОКВЭД_НР!$L$9 + SUMPRODUCT(ISNUMBER(SEARCH(","&Справочник_ОКВЭД_НР!$C$3:$C$62&".",","&SUBSTITUTE(F7," ","")&",")))*Справочник_ОКВЭД_НР!$L$10 + SUMPRODUCT(ISNUMBER(SEARCH(","&Справочник_ОКВЭД_НР!$E$3:$E$62&".",","&SUBSTITUTE(F7," ","")&",")))*Справочник_ОКВЭД_НР!$L$11 + SUMPRODUCT(ISNUMBER(SEARCH(","&Справочник_ОКВЭД_НР!$G$3:$G$62&".",","&SUBSTITUTE(F7," ","")&",")))*Справочник_ОКВЭД_НР!$L$12) / (SUMPRODUCT(ISNUMBER(SEARCH(","&Справочник_ОКВЭД_НР!$A$3:$A$62&".",","&SUBSTITUTE(F7," ","")&","))) + SUMPRODUCT(ISNUMBER(SEARCH(","&Справочник_ОКВЭД_НР!$C$3:$C$62&".",","&SUBSTITUTE(F7," ","")&","))) + SUMPRODUCT(ISNUMBER(SEARCH(","&Справочник_ОКВЭД_НР!$E$3:$E$62&".",","&SUBSTITUTE(F7," ","")&","))) + SUMPRODUCT(ISNUMBER(SEARCH(","&Справочник_ОКВЭД_НР!$G$3:$G$62&".",","&SUBSTITUTE(F7," ","")&",")))), 50)} -> 50 | K7: =IFERROR(VLOOKUP(G7,Справочник_ОКВЭД_НР!$O:$P,2,FALSE()),50) -> 100 | L7: =(I7*Справочник_ОКВЭД_НР!$L$2+J7*Справочник_ОКВЭД_НР!$L$3+K7*Справочник_ОКВЭД_НР!$L$4)*M7 -> 63.5 | M7: =IF(COUNTIF(Справочник_ОКВЭД_НР!$G$3:$G$62,H7)>0,0,1) -> 1
A8: =ЛИК_дляСкорингаДП!A8 -> 5087746570830 | B8: =ЛИК_дляСкорингаДП!B8 -> 7715729877 | C8: =ЛИК_дляСкорингаДП!C8 -> АО "ЖЕЛДОРРЕММАШ" | D8: =ЛИК_дляСкорингаДП!M8 -> Предоставление услуг по восстановлению и оснащению (завершению) железнодорожных локомотивов, трамвайных моторных вагонов и прочего подвижного состава | E8: =ЛИК_дляСкорингаДП!L8 -> 30.20.9 | F8: =ЛИК_дляСкорингаДП!N8 -> 16.24,16.29.11,18.12,22.19.7,23.61,25.50.1,25.61,25.62,25.73,28.15.2,30.20.1,30.20.4,33.12,33.14,33.17,33.20,35.12,35.13,35.22,35.30.14,35.30.2,35.30.3,35.30.4,36.00.2,38.32.5,41.20,43.11,43.12.1,43.12.3,43.29,46.69.1,46.69.2,46.77,46.90,47.9,49.10,49.20,49.3,49.31,49.4,49.41.2,52.21.1,55.10,55.90,56.10,56.10.1,56.10.3,56.29,61.10.1,62.01,62.02,62.09,63.11.1,68.20.1,68.20.2,68.32.1,71.1,71.11,71.11.1,71.12.12,71.12.45,71.12.5,71.12.6,71.20,72.1,72.19,73.20.1,74.20,74.30,82.92,82.99,85.42,85.42.9,86.21,91.01 | G8: =ЛИК_дляСкорингаДП!AG8 -> ОСН | H8: =IF(ISNUMBER(E8),E8, IFERROR(LEFT(E8,FIND(".",E8)-1),E8)) -> 30 | I8: =IF(COUNTIF(Справочник_ОКВЭД_НР!$A$3:$A$62,H8)>0,Справочник_ОКВЭД_НР!$L$8, IF(COUNTIF(Справочник_ОКВЭД_НР!$C$3:$C$62,H8)>0,Справочник_ОКВЭД_НР!$L$9, IF(COUNTIF(Справочник_ОКВЭД_НР!$E$3:$E$62,H8)>0,Справочник_ОКВЭД_НР!$L$10, IF(COUNTIF(Справочник_ОКВЭД_НР!$G$3:$G$62,H8)>0,Справочник_ОКВЭД_НР!$L$11,50)))) -> 60 | J8: {=IFERROR( (SUMPRODUCT(ISNUMBER(SEARCH(","&Справочник_ОКВЭД_НР!$A$3:$A$62&".",","&SUBSTITUTE(F8," ","")&",")))*Справочник_ОКВЭД_НР!$L$9 + SUMPRODUCT(ISNUMBER(SEARCH(","&Справочник_ОКВЭД_НР!$C$3:$C$62&".",","&SUBSTITUTE(F8," ","")&",")))*Справочник_ОКВЭД_НР!$L$10 + SUMPRODUCT(ISNUMBER(SEARCH(","&Справочник_ОКВЭД_НР!$E$3:$E$62&".",","&SUBSTITUTE(F8," ","")&",")))*Справочник_ОКВЭД_НР!$L$11 + SUMPRODUCT(ISNUMBER(SEARCH(","&Справочник_ОКВЭД_НР!$G$3:$G$62&".",","&SUBSTITUTE(F8," ","")&",")))*Справочник_ОКВЭД_НР!$L$12) / (SUMPRODUCT(ISNUMBER(SEARCH(","&Справочник_ОКВЭД_НР!$A$3:$A$62&".",","&SUBSTITUTE(F8," ","")&","))) + SUMPRODUCT(ISNUMBER(SEARCH(","&Справочник_ОКВЭД_НР!$C$3:$C$62&".",","&SUBSTITUTE(F8," ","")&","))) + SUMPRODUCT(ISNUMBER(SEARCH(","&Справочник_ОКВЭД_НР!$E$3:$E$62&".",","&SUBSTITUTE(F8," ","")&","))) + SUMPRODUCT(ISNUMBER(SEARCH(","&Справочник_ОКВЭД_НР!$G$3:$G$62&".",","&SUBSTITUTE(F8," ","")&",")))), 50)} -> 50 | K8: =IFERROR(VLOOKUP(G8,Справочник_ОКВЭД_НР!$O:$P,2,FALSE()),50) -> 100 | L8: =(I8*Справочник_ОКВЭД_НР!$L$2+J8*Справочник_ОКВЭД_НР!$L$3+K8*Справочник_ОКВЭД_НР!$L$4)*M8 -> 63.5 | M8: =IF(COUNTIF(Справочник_ОКВЭД_НР!$G$3:$G$62,H8)>0,0,1) -> 1
A9: =ЛИК_дляСкорингаДП!A9 -> 1057747320278 | B9: =ЛИК_дляСкорингаДП!B9 -> 7728551528 | C9: =ЛИК_дляСкорингаДП!C9 -> ООО "СПОРТМАСТЕР" | D9: =ЛИК_дляСкорингаДП!M9 -> Торговля розничная одеждой в специализированных магазинах | E9: =ЛИК_дляСкорингаДП!L9 -> 47.71 | F9: =ЛИК_дляСкорингаДП!N9 -> 46.49,47.91,53.20.39,95.29,37.00,46.42.11,46.42.12,46.42.13,46.42.14,46.42.2,47.25,47.64,47.71.1,47.71.2,47.71.3,47.71.4,47.71.5,47.71.6,47.71.7,47.71.8,47.72.1,47.72.2,47.74,47.78,47.91.2,52.10,53.20.3,62.01,62.02,68.31.12,73.11,85.42,85.42.9,95.11,95.29 | G9: =ЛИК_дляСкорингаДП!AG9 -> ОСН | H9: =IF(ISNUMBER(E9),E9, IFERROR(LEFT(E9,FIND(".",E9)-1),E9)) -> 47 | I9: =IF(COUNTIF(Справочник_ОКВЭД_НР!$A$3:$A$62,H9)>0,Справочник_ОКВЭД_НР!$L$8, IF(COUNTIF(Справочник_ОКВЭД_НР!$C$3:$C$62,H9)>0,Справочник_ОКВЭД_НР!$L$9, IF(COUNTIF(Справочник_ОКВЭД_НР!$E$3:$E$62,H9)>0,Справочник_ОКВЭД_НР!$L$10, IF(COUNTIF(Справочник_ОКВЭД_НР!$G$3:$G$62,H9)>0,Справочник_ОКВЭД_НР!$L$11,50)))) -> 60 | J9: {=IFERROR( (SUMPRODUCT(ISNUMBER(SEARCH(","&Справочник_ОКВЭД_НР!$A$3:$A$62&".",","&SUBSTITUTE(F9," ","")&",")))*Справочник_ОКВЭД_НР!$L$9 + SUMPRODUCT(ISNUMBER(SEARCH(","&Справочник_ОКВЭД_НР!$C$3:$C$62&".",","&SUBSTITUTE(F9," ","")&",")))*Справочник_ОКВЭД_НР!$L$10 + SUMPRODUCT(ISNUMBER(SEARCH(","&Справочник_ОКВЭД_НР!$E$3:$E$62&".",","&SUBSTITUTE(F9," ","")&",")))*Справочник_ОКВЭД_НР!$L$11 + SUMPRODUCT(ISNUMBER(SEARCH(","&Справочник_ОКВЭД_НР!$G$3:$G$62&".",","&SUBSTITUTE(F9," ","")&",")))*Справочник_ОКВЭД_НР!$L$12) / (SUMPRODUCT(ISNUMBER(SEARCH(","&Справочник_ОКВЭД_НР!$A$3:$A$62&".",","&SUBSTITUTE(F9," ","")&","))) + SUMPRODUCT(ISNUMBER(SEARCH(","&Справочник_ОКВЭД_НР!$C$3:$C$62&".",","&SUBSTITUTE(F9," ","")&","))) + SUMPRODUCT(ISNUMBER(SEARCH(","&Справочник_ОКВЭД_НР!$E$3:$E$62&".",","&SUBSTITUTE(F9," ","")&","))) + SUMPRODUCT(ISNUMBER(SEARCH(","&Справочник_ОКВЭД_НР!$G$3:$G$62&".",","&SUBSTITUTE(F9," ","")&",")))), 50)} -> 50 | K9: =IFERROR(VLOOKUP(G9,Справочник_ОКВЭД_НР!$O:$P,2,FALSE()),50) -> 100 | L9: =(I9*Справочник_ОКВЭД_НР!$L$2+J9*Справочник_ОКВЭД_НР!$L$3+K9*Справочник_ОКВЭД_НР!$L$4)*M9 -> 63.5 | M9: =IF(COUNTIF(Справочник_ОКВЭД_НР!$G$3:$G$62,H9)>0,0,1) -> 1
A10: =ЛИК_дляСкорингаДП!A10 -> 1027717003467 | B10: =ЛИК_дляСкорингаДП!B10 -> 7717133960 | C10: =ЛИК_дляСкорингаДП!C10 -> ПАО НК "РУССНЕФТЬ" | D10: =ЛИК_дляСкорингаДП!M10 -> Добыча нефти | E10: =ЛИК_дляСкорингаДП!L10 -> 06.10.1 | F10: =ЛИК_дляСкорингаДП!N10 -> 06.10,08.12.1,09.10.1,09.10.9,23.51,28.13,33.20,35.11,35.12,35.13,35.22,35.30.14,46.71,46.71.2,46.71.3,49.41,49.41.1,49.50.11,49.50.21,52.10,52.10.22,52.21.2,52.29,64.20,64.99,69.10,69.20,70.10,70.10.1,70.10.2,71.12,71.12.1,71.20,82.11,84.13 | G10: =ЛИК_дляСкорингаДП!AG10 -> ОСН | H10: =IF(ISNUMBER(E10),E10, IFERROR(LEFT(E10,FIND(".",E10)-1),E10)) -> 06 | I10: =IF(COUNTIF(Справочник_ОКВЭД_НР!$A$3:$A$62,H10)>0,Справочник_ОКВЭД_НР!$L$8, IF(COUNTIF(Справочник_ОКВЭД_НР!$C$3:$C$62,H10)>0,Справочник_ОКВЭД_НР!$L$9, IF(COUNTIF(Справочник_ОКВЭД_НР!$E$3:$E$62,H10)>0,Справочник_ОКВЭД_НР!$L$10, IF(COUNTIF(Справочник_ОКВЭД_НР!$G$3:$G$62,H10)>0,Справочник_ОКВЭД_НР!$L$11,50)))) -> 60 | J10: {=IFERROR( (SUMPRODUCT(ISNUMBER(SEARCH(","&Справочник_ОКВЭД_НР!$A$3:$A$62&".",","&SUBSTITUTE(F10," ","")&",")))*Справочник_ОКВЭД_НР!$L$9 + SUMPRODUCT(ISNUMBER(SEARCH(","&Справочник_ОКВЭД_НР!$C$3:$C$62&".",","&SUBSTITUTE(F10," ","")&",")))*Справочник_ОКВЭД_НР!$L$10 + SUMPRODUCT(ISNUMBER(SEARCH(","&Справочник_ОКВЭД_НР!$E$3:$E$62&".",","&SUBSTITUTE(F10," ","")&",")))*Справочник_ОКВЭД_НР!$L$11 + SUMPRODUCT(ISNUMBER(SEARCH(","&Справочник_ОКВЭД_НР!$G$3:$G$62&".",","&SUBSTITUTE(F10," ","")&",")))*Справочник_ОКВЭД_НР!$L$12) / (SUMPRODUCT(ISNUMBER(SEARCH(","&Справочник_ОКВЭД_НР!$A$3:$A$62&".",","&SUBSTITUTE(F10," ","")&","))) + SUMPRODUCT(ISNUMBER(SEARCH(","&Справочник_ОКВЭД_НР!$C$3:$C$62&".",","&SUBSTITUTE(F10," ","")&","))) + SUMPRODUCT(ISNUMBER(SEARCH(","&Справочник_ОКВЭД_НР!$E$3:$E$62&".",","&SUBSTITUTE(F10," ","")&","))) + SUMPRODUCT(ISNUMBER(SEARCH(","&Справочник_ОКВЭД_НР!$G$3:$G$62&".",","&SUBSTITUTE(F10," ","")&",")))), 50)} -> 50 | K10: =IFERROR(VLOOKUP(G10,Справочник_ОКВЭД_НР!$O:$P,2,FALSE()),50) -> 100 | L10: =(I10*Справочник_ОКВЭД_НР!$L$2+J10*Справочник_ОКВЭД_НР!$L$3+K10*Справочник_ОКВЭД_НР!$L$4)*M10 -> 63.5 | M10: =IF(COUNTIF(Справочник_ОКВЭД_НР!$G$3:$G$62,H10)>0,0,1) -> 1
A11: =ЛИК_дляСкорингаДП!A11 -> 1065009017920 | B11: =ЛИК_дляСкорингаДП!B11 -> 5009053687 | C11: =ЛИК_дляСкорингаДП!C11 -> ООО "ТАТНЕФТЬ-АЗС-ЗАПАД" | D11: =ЛИК_дляСкорингаДП!M11 -> Торговля розничная моторным топливом в специализированных магазинах | E11: =ЛИК_дляСкорингаДП!L11 -> 47.30 | F11: =ЛИК_дляСкорингаДП!N11 -> 10.71.1,10.85,68.20.21,10.13.4,10.32,10.71,10.72,10.72.4,10.82,10.82.2,10.85,10.89,11.07.2,19.20,42.21,45.2,45.20.5,46.12.1,46.71,46.71.1,46.71.2,46.90,47.11,47.2,47.24,47.25,47.26,47.30,47.30.2,47.73,47.74,47.75,47.78.9,47.91,47.91.1,47.91.2,47.91.29,49.31,49.50.1,52.10.21,52.29,56.10,56.10.21,56.10.22,56.10.24,56.29,56.30,66.19,73.11,74.20,74.30,77.40,82.92,85.30,85.42.9 | G11: =ЛИК_дляСкорингаДП!AG11 -> ОСН | H11: =IF(ISNUMBER(E11),E11, IFERROR(LEFT(E11,FIND(".",E11)-1),E11)) -> 47 | I11: =IF(COUNTIF(Справочник_ОКВЭД_НР!$A$3:$A$62,H11)>0,Справочник_ОКВЭД_НР!$L$8, IF(COUNTIF(Справочник_ОКВЭД_НР!$C$3:$C$62,H11)>0,Справочник_ОКВЭД_НР!$L$9, IF(COUNTIF(Справочник_ОКВЭД_НР!$E$3:$E$62,H11)>0,Справочник_ОКВЭД_НР!$L$10, IF(COUNTIF(Справочник_ОКВЭД_НР!$G$3:$G$62,H11)>0,Справочник_ОКВЭД_НР!$L$11,50)))) -> 60 | J11: {=IFERROR( (SUMPRODUCT(ISNUMBER(SEARCH(","&Справочник_ОКВЭД_НР!$A$3:$A$62&".",","&SUBSTITUTE(F11," ","")&",")))*Справочник_ОКВЭД_НР!$L$9 + SUMPRODUCT(ISNUMBER(SEARCH(","&Справочник_ОКВЭД_НР!$C$3:$C$62&".",","&SUBSTITUTE(F11," ","")&",")))*Справочник_ОКВЭД_НР!$L$10 + SUMPRODUCT(ISNUMBER(SEARCH(","&Справочник_ОКВЭД_НР!$E$3:$E$62&".",","&SUBSTITUTE(F11," ","")&",")))*Справочник_ОКВЭД_НР!$L$11 + SUMPRODUCT(ISNUMBER(SEARCH(","&Справочник_ОКВЭД_НР!$G$3:$G$62&".",","&SUBSTITUTE(F11," ","")&",")))*Справочник_ОКВЭД_НР!$L$12) / (SUMPRODUCT(ISNUMBER(SEARCH(","&Справочник_ОКВЭД_НР!$A$3:$A$62&".",","&SUBSTITUTE(F11," ","")&","))) + SUMPRODUCT(ISNUMBER(SEARCH(","&Справочник_ОКВЭД_НР!$C$3:$C$62&".",","&SUBSTITUTE(F11," ","")&","))) + SUMPRODUCT(ISNUMBER(SEARCH(","&Справочник_ОКВЭД_НР!$E$3:$E$62&".",","&SUBSTITUTE(F11," ","")&","))) + SUMPRODUCT(ISNUMBER(SEARCH(","&Справочник_ОКВЭД_НР!$G$3:$G$62&".",","&SUBSTITUTE(F11," ","")&",")))), 50)} -> 50 | K11: =IFERROR(VLOOKUP(G11,Справочник_ОКВЭД_НР!$O:$P,2,FALSE()),50) -> 100 | L11: =(I11*Справочник_ОКВЭД_НР!$L$2+J11*Справочник_ОКВЭД_НР!$L$3+K11*Справочник_ОКВЭД_НР!$L$4)*M11 -> 63.5 | M11: =IF(COUNTIF(Справочник_ОКВЭД_НР!$G$3:$G$62,H11)>0,0,1) -> 1
A12: =ЛИК_дляСкорингаДП!A12 -> 1077763638578 | B12: =ЛИК_дляСкорингаДП!B12 -> 7704670879 | C12: =ЛИК_дляСкорингаДП!C12 -> АО "ИКАО" | D12: =ЛИК_дляСкорингаДП!M12 -> Деятельность заказчика-застройщика, генерального подрядчика | E12: =ЛИК_дляСкорингаДП!L12 -> 71.12.2 | F12: =ЛИК_дляСкорингаДП!N12 -> 41.2,55.90,64.92.3,68.1,68.2,68.3,70.22,71.11.1 | G12: =ЛИК_дляСкорингаДП!AG12 -> ОСН | H12: =IF(ISNUMBER(E12),E12, IFERROR(LEFT(E12,FIND(".",E12)-1),E12)) -> 71 | I12: =IF(COUNTIF(Справочник_ОКВЭД_НР!$A$3:$A$62,H12)>0,Справочник_ОКВЭД_НР!$L$8, IF(COUNTIF(Справочник_ОКВЭД_НР!$C$3:$C$62,H12)>0,Справочник_ОКВЭД_НР!$L$9, IF(COUNTIF(Справочник_ОКВЭД_НР!$E$3:$E$62,H12)>0,Справочник_ОКВЭД_НР!$L$10, IF(COUNTIF(Справочник_ОКВЭД_НР!$G$3:$G$62,H12)>0,Справочник_ОКВЭД_НР!$L$11,50)))) -> 100 | J12: {=IFERROR( (SUMPRODUCT(ISNUMBER(SEARCH(","&Справочник_ОКВЭД_НР!$A$3:$A$62&".",","&SUBSTITUTE(F12," ","")&",")))*Справочник_ОКВЭД_НР!$L$9 + SUMPRODUCT(ISNUMBER(SEARCH(","&Справочник_ОКВЭД_НР!$C$3:$C$62&".",","&SUBSTITUTE(F12," ","")&",")))*Справочник_ОКВЭД_НР!$L$10 + SUMPRODUCT(ISNUMBER(SEARCH(","&Справочник_ОКВЭД_НР!$E$3:$E$62&".",","&SUBSTITUTE(F12," ","")&",")))*Справочник_ОКВЭД_НР!$L$11 + SUMPRODUCT(ISNUMBER(SEARCH(","&Справочник_ОКВЭД_НР!$G$3:$G$62&".",","&SUBSTITUTE(F12," ","")&",")))*Справочник_ОКВЭД_НР!$L$12) / (SUMPRODUCT(ISNUMBER(SEARCH(","&Справочник_ОКВЭД_НР!$A$3:$A$62&".",","&SUBSTITUTE(F12," ","")&","))) + SUMPRODUCT(ISNUMBER(SEARCH(","&Справочник_ОКВЭД_НР!$C$3:$C$62&".",","&SUBSTITUTE(F12," ","")&","))) + SUMPRODUCT(ISNUMBER(SEARCH(","&Справочник_ОКВЭД_НР!$E$3:$E$62&".",","&SUBSTITUTE(F12," ","")&","))) + SUMPRODUCT(ISNUMBER(SEARCH(","&Справочник_ОКВЭД_НР!$G$3:$G$62&".",","&SUBSTITUTE(F12," ","")&",")))), 50)} -> 50 | K12: =IFERROR(VLOOKUP(G12,Справочник_ОКВЭД_НР!$O:$P,2,FALSE()),50) -> 100 | L12: =(I12*Справочник_ОКВЭД_НР!$L$2+J12*Справочник_ОКВЭД_НР!$L$3+K12*Справочник_ОКВЭД_НР!$L$4)*M12 -> 87.5 | M12: =IF(COUNTIF(Справочник_ОКВЭД_НР!$G$3:$G$62,H12)>0,0,1) -> 1
A13: =ЛИК_дляСкорингаДП!A13 -> 1117746491500 | B13: =ЛИК_дляСкорингаДП!B13 -> 7702764909 | C13: =ЛИК_дляСкорингаДП!C13 -> ООО "КАРИ" | D13: =ЛИК_дляСкорингаДП!M13 -> Торговля розничная обувью и изделиями из кожи в специализированных магазинах | E13: =ЛИК_дляСкорингаДП!L13 -> 47.72 | F13: =ЛИК_дляСкорингаДП!N13 -> 46.42,16.29.13,23.19.9,24.10.2,32.12.1,32.12.2,32.12.3,32.12.4,32.12.5,32.13,38.32.2,38.32.59,46.12.22,46.18.2,46.18.2,46.41,46.41.2,46.42,46.43,46.44,46.45,46.46,46.48.2,46.49,46.72.23,46.76.4,47.19,47.43,47.51,47.54,47.7,47.71,47.72,47.75,47.77.2,47.91,47.91.1,47.91.2,47.91.4,63.99.1,66.19.5,69.10,69.20,70.22,78.10,95.25 | G13: =ЛИК_дляСкорингаДП!AG13 -> ОСН | H13: =IF(ISNUMBER(E13),E13, IFERROR(LEFT(E13,FIND(".",E13)-1),E13)) -> 47 | I13: =IF(COUNTIF(Справочник_ОКВЭД_НР!$A$3:$A$62,H13)>0,Справочник_ОКВЭД_НР!$L$8, IF(COUNTIF(Справочник_ОКВЭД_НР!$C$3:$C$62,H13)>0,Справочник_ОКВЭД_НР!$L$9, IF(COUNTIF(Справочник_ОКВЭД_НР!$E$3:$E$62,H13)>0,Справочник_ОКВЭД_НР!$L$10, IF(COUNTIF(Справочник_ОКВЭД_НР!$G$3:$G$62,H13)>0,Справочник_ОКВЭД_НР!$L$11,50)))) -> 60 | J13: {=IFERROR( (SUMPRODUCT(ISNUMBER(SEARCH(","&Справочник_ОКВЭД_НР!$A$3:$A$62&".",","&SUBSTITUTE(F13," ","")&",")))*Справочник_ОКВЭД_НР!$L$9 + SUMPRODUCT(ISNUMBER(SEARCH(","&Справочник_ОКВЭД_НР!$C$3:$C$62&".",","&SUBSTITUTE(F13," ","")&",")))*Справочник_ОКВЭД_НР!$L$10 + SUMPRODUCT(ISNUMBER(SEARCH(","&Справочник_ОКВЭД_НР!$E$3:$E$62&".",","&SUBSTITUTE(F13," ","")&",")))*Справочник_ОКВЭД_НР!$L$11 + SUMPRODUCT(ISNUMBER(SEARCH(","&Справочник_ОКВЭД_НР!$G$3:$G$62&".",","&SUBSTITUTE(F13," ","")&",")))*Справочник_ОКВЭД_НР!$L$12) / (SUMPRODUCT(ISNUMBER(SEARCH(","&Справочник_ОКВЭД_НР!$A$3:$A$62&".",","&SUBSTITUTE(F13," ","")&","))) + SUMPRODUCT(ISNUMBER(SEARCH(","&Справочник_ОКВЭД_НР!$C$3:$C$62&".",","&SUBSTITUTE(F13," ","")&","))) + SUMPRODUCT(ISNUMBER(SEARCH(","&Справочник_ОКВЭД_НР!$E$3:$E$62&".",","&SUBSTITUTE(F13," ","")&","))) + SUMPRODUCT(ISNUMBER(SEARCH(","&Справочник_ОКВЭД_НР!$G$3:$G$62&".",","&SUBSTITUTE(F13," ","")&",")))), 50)} -> 50 | K13: =IFERROR(VLOOKUP(G13,Справочник_ОКВЭД_НР!$O:$P,2,FALSE()),50) -> 100 | L13: =(I13*Справочник_ОКВЭД_НР!$L$2+J13*Справочник_ОКВЭД_НР!$L$3+K13*Справочник_ОКВЭД_НР!$L$4)*M13 -> 63.5 | M13: =IF(COUNTIF(Справочник_ОКВЭД_НР!$G$3:$G$62,H13)>0,0,1) -> 1
... A1001: =ЛИК_дляСкорингаДП!A1001 -> 1107746101495 | B1001: =ЛИК_дляСкорингаДП!B1001 -> 7720678138 | C1001: =ЛИК_дляСкорингаДП!C1001 -> ООО СТОМАТОЛОГИЯ "АМЕЛИЯ" | D1001: =ЛИК_дляСкорингаДП!M1001 -> Стоматологическая практика | E1001: =ЛИК_дляСкорингаДП!L1001 -> 86.23 | F1001: =ЛИК_дляСкорингаДП!N1001 -> 47.74,47.78,86.90.9,86.90.9 | G1001: =ЛИК_дляСкорингаДП!AG1001 -> УСН | H1001: =IF(ISNUMBER(E1001),E1001, IFERROR(LEFT(E1001,FIND(".",E1001)-1),E1001)) -> 86 | I1001: =IF(COUNTIF(Справочник_ОКВЭД_НР!$A$3:$A$62,H1001)>0,Справочник_ОКВЭД_НР!$L$8, IF(COUNTIF(Справочник_ОКВЭД_НР!$C$3:$C$62,H1001)>0,Справочник_ОКВЭД_НР!$L$9, IF(COUNTIF(Справочник_ОКВЭД_НР!$E$3:$E$62,H1001)>0,Справочник_ОКВЭД_НР!$L$10, IF(COUNTIF(Справочник_ОКВЭД_НР!$G$3:$G$62,H1001)>0,Справочник_ОКВЭД_НР!$L$11,50)))) -> 100 | J1001: {=IFERROR( (SUMPRODUCT(ISNUMBER(SEARCH(","&Справочник_ОКВЭД_НР!$A$3:$A$62&".",","&SUBSTITUTE(F1001," ","")&",")))*Справочник_ОКВЭД_НР!$L$9 + SUMPRODUCT(ISNUMBER(SEARCH(","&Справочник_ОКВЭД_НР!$C$3:$C$62&".",","&SUBSTITUTE(F1001," ","")&",")))*Справочник_ОКВЭД_НР!$L$10 + SUMPRODUCT(ISNUMBER(SEARCH(","&Справочник_ОКВЭД_НР!$E$3:$E$62&".",","&SUBSTITUTE(F1001," ","")&",")))*Справочник_ОКВЭД_НР!$L$11 + SUMPRODUCT(ISNUMBER(SEARCH(","&Справочник_ОКВЭД_НР!$G$3:$G$62&".",","&SUBSTITUTE(F1001," ","")&",")))*Справочник_ОКВЭД_НР!$L$12) / (SUMPRODUCT(ISNUMBER(SEARCH(","&Справочник_ОКВЭД_НР!$A$3:$A$62&".",","&SUBSTITUTE(F1001," ","")&","))) + SUMPRODUCT(ISNUMBER(SEARCH(","&Справочник_ОКВЭД_НР!$C$3:$C$62&".",","&SUBSTITUTE(F1001," ","")&","))) + SUMPRODUCT(ISNUMBER(SEARCH(","&Справочник_ОКВЭД_НР!$E$3:$E$62&".",","&SUBSTITUTE(F1001," ","")&","))) + SUMPRODUCT(ISNUMBER(SEARCH(","&Справочник_ОКВЭД_НР!$G$3:$G$62&".",","&SUBSTITUTE(F1001," ","")&",")))), 50)} -> 50 | K1001: =IFERROR(VLOOKUP(G1001,Справочник_ОКВЭД_НР!$O:$P,2,FALSE()),50) -> 50 | L1001: =(I1001*Справочник_ОКВЭД_НР!$L$2+J1001*Справочник_ОКВЭД_НР!$L$3+K1001*Справочник_ОКВЭД_НР!$L$4)*M1001 -> 80 | M1001: =IF(COUNTIF(Справочник_ОКВЭД_НР!$G$3:$G$62,H1001)>0,0,1) -> 1

Sheet Справочник_ОКВЭД_НР
A1: ТИР 1 — 100 баллов (целевые отрасли) | C1: ТИР 2 — 60 баллов (смежные отрасли) | E1: ТИР 3 — 30 баллов (нейтральные отрасли) | G1: ТИР 4 — 0 баллов, СТОП-ФАКТОР (бюджет/НКО) | K1: Признак | L1: Вес | M1: Обоснование | O1: Режим | P1: Балл | Q1: Обоснование
A2: Класс | B2: Название (для справки) | C2: Класс | D2: Название (для справки) | E2: Класс | F2: Название (для справки) | G2: Класс | H2: Название (для справки) | K2: ОКВЭД | L2: 0.6 | M2: Основной вид деятельности — самый прямой и надёжный индикатор отраслевой принадлежности лида. | O2: ОСН | P2: 100 | Q2: Сложный учёт, НДС-администрирование — максимальная потребность в консалтинге.
A3: 68 | B3: Аренда и управление собственным или арендованным недвижимым имуществом (148 комп. в базе) | C3: 46 | D3: Торговля оптовая неспециализированная (102 комп. в базе) | E3: 56 | F3: Деятельность ресторанов и услуги по доставке продуктов питания (31 комп. в базе) | G3: 84 | H3: Деятельность органов местного самоуправления муниципальных округов (42 комп. в базе) | K3: Налоговый Режим | L3: 0.25 | M3: Налоговый режим напрямую отражает сложность бухучёта (НДС на ОСН против упрощёнки на УСН). | O3: УСН | P3: 50 | Q3: Упрощённый учёт — меньшая зависимость от внешнего сопровождения.
A4: 86 | B4: Стоматологическая практика (37 комп. в базе) | C4: 47 | D4: Торговля розничная лекарственными средствами в специализированных магазинах (аптеках) (43 комп. в базе) | E4: 85 | F4: Образование среднее общее (18 комп. в базе) | G4: 94 | H4: Деятельность прочих общественных организаций и некоммерческих организаций, кроме религиозных и политических организаций (31 комп. в базе) | K4: Доп. ОКВЭД | L4: 0.15 | M4: Вторичный, уточняющий сигнал диверсификации бизнеса — не должен перевешивать основной вид деятельности. | O4: ЕСХН | P4: 40 | Q4: Нишевый режим, обычно небольшие сельхозкомпании.
A5: 71 | B5: Деятельность заказчика-застройщика, генерального подрядчика (35 комп. в базе) | C5: 64 | D5: Предоставление прочих финансовых услуг, кроме услуг по страхованию и пенсионному обеспечению, не включенных в другие группировки (24 комп. в базе) | E5: 93 | F5: Деятельность в области спорта прочая (16 комп. в базе) | G5: 91 | H5: Деятельность библиотек и архивов (2 комп. в базе)
A6: 41 | B6: Строительство жилых и нежилых зданий (31 комп. в базе) | C6: 52 | D6: Деятельность вспомогательная прочая, связанная с перевозками (20 комп. в базе) | E6: 81 | F6: Деятельность по чистке и уборке жилых зданий и нежилых помещений прочая (15 комп. в базе)
A7: 62 | B7: Разработка компьютерного программного обеспечения (31 комп. в базе) | C7: 45 | D7: Торговля розничная легковыми автомобилями и легкими автотранспортными средствами в специализированных магазинах (19 комп. в базе) | E7: 69 | F7: Деятельность по оказанию услуг в области бухгалтерского учета, по проведению финансового аудита, по налоговому консультированию (11 комп. в базе) | K7: Тир | L7: Балл | M7: Смысл
A8: 10 | B8: Производство колбасных изделий (22 комп. в базе) | C8: 49 | D8: Деятельность автомобильного грузового транспорта и услуги по перевозкам (18 комп. в базе) | E8: 18 | F8: Прочие виды полиграфической деятельности (9 комп. в базе) | K8: Балл_Тир1 | L8: 100 | M8: Целевые отрасли
A9: 27 | B9: Производство электрической распределительной и регулирующей аппаратуры (21 комп. в базе) | C9: 35 | D9: Производство электроэнергии тепловыми электростанциями, в том числе деятельность по обеспечению работоспособности электростанций (15 комп. в базе) | E9: 82 | F9: Деятельность по предоставлению прочих вспомогательных услуг для бизнеса, не включенная в другие группировки (9 комп. в базе) | K9: Балл_Тир2 | L9: 60 | M9: Смежные отрасли
A10: 43 | B10: Производство электромонтажных работ (20 комп. в базе) | C10: 1 | D10: Производство сырого коровьего молока (14 комп. в базе) | E10: 73 | F10: Деятельность рекламных агентств (8 комп. в базе) | K10: Балл_Тир3 | L10: 30 | M10: Нейтральные отрасли
A11: 63 | B11: Деятельность по созданию и использованию баз данных и информационных ресурсов (10 комп. в базе) | C11: 70 | D11: Консультирование по вопросам коммерческой деятельности и управления (13 комп. в базе) | E11: 55 | F11: Деятельность гостиниц и прочих мест для временного проживания (7 комп. в базе) | K11: Балл_Тир4 | L11: 0 | M11: Бюджет/НКО — стоп-фактор
A12: 42 | B12: Строительство автомобильных дорог и автомагистралей (6 комп. в базе) | C12: 28 | D12: Производство машин и оборудования для добычи полезных ископаемых и строительства (12 комп. в базе) | E12: 59 | F12: Производство кинофильмов, видеофильмов и телевизионных программ (7 комп. в базе) | K12: Балл при отсутствии данных (пропуск) | L12: 50 | M12: Требуется ручная проверка
A13: 11 | B13: Производство дистиллированных питьевых алкогольных напитков: водки, виски, бренди, джина, ликеров и т. п. (5 комп. в базе) | C13: 33 | D13: Ремонт машин и оборудования (11 комп. в базе) | E13: 79 | F13: Деятельность туристических агентств (7 комп. в базе)
C14: 61 | D14: Деятельность в области связи на базе проводных технологий (10 комп. в базе) | E14: 31 | F14: Производство прочей мебели (6 комп. в базе)
C15: 20 | D15: Производство парфюмерных и косметических средств (8 комп. в базе) | E15: 88 | F15: Предоставление прочих социальных услуг без обеспечения проживания, не включенных в другие группировки (5 комп. в базе)
C16: 26 | D16: Производство инструментов и приборов для измерения, тестирования и навигации (7 комп. в базе) | E16: 96 | F16: Стирка и химическая чистка текстильных и меховых изделий (5 комп. в базе)
C17: 77 | D17: Аренда и лизинг железнодорожного транспорта и оборудования (7 комп. в базе) | E17: 58 | F17: Издание книг (4 комп. в базе)
C18: 23 | D18: Производство изделий из бетона, цемента и гипса (6 комп. в базе) | E18: 90 | F18: Деятельность вспомогательная, связанная с исполнительскими искусствами (4 комп. в базе)
C19: 66 | D19: Деятельность вспомогательная прочая в сфере страхования, кроме обязательного социального страхования (6 комп. в базе) | E19: 74 | F19: Деятельность в области фотографии (3 комп. в базе)
C20: 72 | D20: Научные исследования и разработки в области естественных и технических наук прочие (6 комп. в базе) | E20: 80 | F20: Деятельность систем обеспечения безопасности (3 комп. в базе)
C21: 16 | D21: Производство деревянных строительных конструкций и столярных изделий (5 комп. в базе) | E21: 95 | F21: Ремонт компьютеров и периферийного компьютерного оборудования (3 комп. в базе)
C22: 22 | D22: Предоставление услуг в области производства прочих пластмассовых изделий (5 комп. в базе) | E22: 38 | F22: Заготовка, хранение, переработка и реализация лома и отходов черных металлов (2 комп. в базе)
C23: 29 | D23: Производство автомобилей специального назначения (5 комп. в базе) | E23: 60 | F23: Деятельность в области радиовещания (2 комп. в базе)
C24: 17 | D24: Производство гофрированной бумаги и картона, бумажной и картонной тары (4 комп. в базе) | E24: 32 | F24: Производство спортивных товаров (1 комп. в базе)
C25: 25 | D25: Производство металлических бочек и аналогичных емкостей (4 комп. в базе) | E25: 36 | F25: Забор и очистка воды для питьевых и промышленных нужд (1 комп. в базе)
... C28: 21 | D28: Производство материалов, применяемых в медицинских целях (2 комп. в базе) | E28: 87 | F28: Деятельность по уходу с обеспечением проживания (1 комп. в базе)
C29: 50 | D29: Перевозка прочих грузов морскими судами каботажного плавания (2 комп. в базе)
C30: 51 | D30: Перевозка воздушным пассажирским транспортом, подчиняющимся расписанию (2 комп. в базе)
C31: 6 | D31: Добыча нефти (1 комп. в базе)
C32: 8 | D32: Разработка гравийных и песчаных карьеров, добыча глины и каолина (1 комп. в базе)
C33: 24 | D33: Литье чугуна (1 комп. в базе)
